Workbook

Sheet Inputs
A1: Fernhill Commons: independent Excel check of the AVIANCRE multifamily engine
A2: Built only from inputs.md, rules.md and rent-roll.csv (fictional sample data). Blue = input from inputs.md; black = formula.
A4: Input | B4: Value | C4: Source
A5: Analysis start date | B5: 46327 | C5: inputs.md: analysis start
A6: Units | B6: 120 | C6: inputs.md: property
A7: Market rent growth (annual step each Nov) | B7: 0.03 | C7: inputs.md: revenue
A8: General vacancy (floor) | B8: 0.05 | C8: inputs.md: revenue
A9: Credit loss | B9: 0.01 | C9: inputs.md: revenue
A10: Operating expenses $/unit/yr (year 1) | B10: 6800 | C10: inputs.md: operating expenses
A11: Expense growth | B11: 0.03 | C11: inputs.md: operating expenses
A12: Management fee (% of EGI) | B12: 0.03 | C12: inputs.md: operating expenses
A13: Capital reserves $/unit/yr (flat) | B13: 300 | C13: inputs.md: capital
A14: Initial capex | B14: 0 | C14: inputs.md: capital
A15: Turnover share per roll | B15: 0.5 | C15: inputs.md: capital
A16: Turnover cost per move-out (year 1) | B16: 1000 | C16: inputs.md: capital
... A29: Discount rate (unlevered NPV) | B29: 0.08 | C29: inputs.md: returns

Sheet Returns
A1: Acquisition, debt, sale and returns
A4: Year-1 NOI | C4: =Annual!C16 -> 1311652.5
A5: Purchase price (Y1 NOI / market cap) | C5: =C4/Inputs!$B$19 -> 20986440
A6: Closing costs | C6: =Inputs!$B$20*C5 -> 314796.6
A7: Total cost | C7: =C5+C6+Inputs!$B$14 -> 21301237
A8: Loan (LTV x price) | C8: =Inputs!$B$22*C5 -> 12591864
A9: Loan fee | C9: =Inputs!$B$26*C8 -> 125918.64
A10: Equity | C10: =C7-C8+C9 -> 8835291.3
A11: Amortizing payment (months 25+) | C11: =-PMT(Inputs!$B$23/12,Inputs!$B$25*12,C8) -> 79589.147
A12: Loan payoff (balance after month 120) | C12: =INDEX(Monthly!$N$2:$N$133,Inputs!$B$21*12) -> 11163528
A13: Exit NOI (normalized year 11) | C13: =Annual!M36 -> 1778732.6
A14: Gross sale price | C14: =C13/Inputs!$B$27 -> 27365116
A15: Net sale proceeds | C15: =C14*(1-Inputs!$B$28) -> 26817814
A16: Going-in cap | C16: =C4/C5 -> 0.0625
A17: Debt yield | C17: =C4/C8 -> 0.10416667
A19: Year | C19: 0 | D19: 1 | E19: 2 | F19: 3 | G19: 4 | H19: 5 | I19: 6 | J19: 7 | K19: 8 | L19: 9 | M19: 10
A20: Unlevered cash flow | C20: =-C7 -> -21301237 | D20: =Annual!C19 -> 1220152.5 | E20: =Annual!D19 -> 1256174.3 | F20: =Annual!E19 -> 1302475.9 | G20: =Annual!F19 -> 1344407.4 | H20: =Annual!G19 -> 1386130 | I20: =Annual!H19 -> 1428793.9 | J20: =Annual!I19 -> 1472737.7 | K20: =Annual!J19 -> 1517999.8 | L20: =Annual!K19 -> 1564619.8 | M20: =Annual!L19+$C$15 -> 28430452
A21: Levered cash flow | C21: =-C10 -> -8835291.3 | D21: =Annual!C21 -> 401681.35 | E21: =Annual!D21 -> 437703.15 | F21: =Annual!E21 -> 347406.18 | G21: =Annual!F21 -> 389337.68 | H21: =Annual!G21 -> 431060.23 | I21: =Annual!H21 -> 473724.13 | J21: =Annual!I21 -> 517667.94 | K21: =Annual!J21 -> 562930.07 | L21: =Annual!K21 -> 609550.07 | M21: =Annual!L21+$C$15-$C$12 -> 16311854
A23: Unlevered IRR | C23: =IRR(C20:M20) -> 0.082560126
A24: Levered IRR | C24: =IRR(C21:M21) -> 0.10043024
A25: Unlevered NPV @ discount rate | C25: =C20+NPV(Inputs!$B$29,D20:M20) -> 402343.56
A26: Unlevered equity multiple | C26: =SUM(D20:M20)/C7 -> 1.9212004
A27: Levered equity multiple | C27: =SUM(D21:M21)/C10 -> 2.3183067
A28: Minimum DSCR (years 1-10) | C28: =MIN(Annual!C25:L25) -> 1.4680916
A29: Year-1 cash-on-cash | C29: =Annual!C26 -> 0.045463282

Sheet Annual
A1: Annual cash flow ($)
A3: Analysis year | C3: 1 | D3: 2 | E3: 3 | F3: 4 | G3: 5 | H3: 6 | I3: 7 | J3: 8 | K3: 9 | L3: 10 | M3: 11
A4: Gross potential rent | C4: =SUMIF(Monthly!$B$2:$B$133,1,Monthly!$C$2:$C$133) -> 2333160 | D4: =SUMIF(Monthly!$B$2:$B$133,2,Monthly!$C$2:$C$133) -> 2403154.8 | E4: =SUMIF(Monthly!$B$2:$B$133,3,Monthly!$C$2:$C$133) -> 2475249.4 | F4: =SUMIF(Monthly!$B$2:$B$133,4,Monthly!$C$2:$C$133) -> 2549506.9 | G4: =SUMIF(Monthly!$B$2:$B$133,5,Monthly!$C$2:$C$133) -> 2625992.1 | H4: =SUMIF(Monthly!$B$2:$B$133,6,Monthly!$C$2:$C$133) -> 2704771.9 | I4: =SUMIF(Monthly!$B$2:$B$133,7,Monthly!$C$2:$C$133) -> 2785915.1 | J4: =SUMIF(Monthly!$B$2:$B$133,8,Monthly!$C$2:$C$133) -> 2869492.5 | K4: =SUMIF(Monthly!$B$2:$B$133,9,Monthly!$C$2:$C$133) -> 2955577.3 | L4: =SUMIF(Monthly!$B$2:$B$133,10,Monthly!$C$2:$C$133) -> 3044244.6 | M4: =SUMIF(Monthly!$B$2:$B$133,11,Monthly!$C$2:$C$133) -> 3135571.9
A5: Less: loss to lease | C5: =SUMIF(Monthly!$B$2:$B$133,1,Monthly!$F$2:$F$133) -> 40080.5 | D5: =SUMIF(Monthly!$B$2:$B$133,2,Monthly!$F$2:$F$133) -> 38024.912 | E5: =SUMIF(Monthly!$B$2:$B$133,3,Monthly!$F$2:$F$133) -> 30904.654 | F5: =SUMIF(Monthly!$B$2:$B$133,4,Monthly!$F$2:$F$133) -> 29883.693 | G5: =SUMIF(Monthly!$B$2:$B$133,5,Monthly!$F$2:$F$133) -> 30440.041 | H5: =SUMIF(Monthly!$B$2:$B$133,6,Monthly!$F$2:$F$133) -> 31353.243 | I5: =SUMIF(Monthly!$B$2:$B$133,7,Monthly!$F$2:$F$133) -> 32293.84 | J5: =SUMIF(Monthly!$B$2:$B$133,8,Monthly!$F$2:$F$133) -> 33262.655 | K5: =SUMIF(Monthly!$B$2:$B$133,9,Monthly!$F$2:$F$133) -> 34260.535 | L5: =SUMIF(Monthly!$B$2:$B$133,10,Monthly!$F$2:$F$133) -> 35288.351 | M5: =SUMIF(Monthly!$B$2:$B$133,11,Monthly!$F$2:$F$133) -> 36347.001
A6: Other income | C6: =Units!$G$123*12*(1+Inputs!$B$7)^(1-1) -> 39144 | D6: =Units!$G$123*12*(1+Inputs!$B$7)^(2-1) -> 40318.32 | E6: =Units!$G$123*12*(1+Inputs!$B$7)^(3-1) -> 41527.87 | F6: =Units!$G$123*12*(1+Inputs!$B$7)^(4-1) -> 42773.706 | G6: =Units!$G$123*12*(1+Inputs!$B$7)^(5-1) -> 44056.917 | H6: =Units!$G$123*12*(1+Inputs!$B$7)^(6-1) -> 45378.624 | I6: =Units!$G$123*12*(1+Inputs!$B$7)^(7-1) -> 46739.983 | J6: =Units!$G$123*12*(1+Inputs!$B$7)^(8-1) -> 48142.183 | K6: =Units!$G$123*12*(1+Inputs!$B$7)^(9-1) -> 49586.448 | L6: =Units!$G$123*12*(1+Inputs!$B$7)^(10-1) -> 51074.042 | M6: =Units!$G$123*12*(1+Inputs!$B$7)^(11-1) -> 52606.263
A7: Potential gross income | C7: =C4-C5+C6 -> 2332223.5 | D7: =D4-D5+D6 -> 2405448.2 | E7: =E4-E5+E6 -> 2485872.7 | F7: =F4-F5+F6 -> 2562396.9 | G7: =G4-G5+G6 -> 2639609 | H7: =H4-H5+H6 -> 2718797.3 | I7: =I4-I5+I6 -> 2800361.2 | J7: =J4-J5+J6 -> 2884372 | ... M7: =M4-M5+M6 -> 3151831.2
A8: Less: absorption vacancy | C8: =SUMIF(Monthly!$B$2:$B$133,1,Monthly!$G$2:$G$133) -> 3375 | D8: =SUMIF(Monthly!$B$2:$B$133,2,Monthly!$G$2:$G$133) -> 0 | E8: =SUMIF(Monthly!$B$2:$B$133,3,Monthly!$G$2:$G$133) -> 0 | F8: =SUMIF(Monthly!$B$2:$B$133,4,Monthly!$G$2:$G$133) -> 0 | G8: =SUMIF(Monthly!$B$2:$B$133,5,Monthly!$G$2:$G$133) -> 0 | H8: =SUMIF(Monthly!$B$2:$B$133,6,Monthly!$G$2:$G$133) -> 0 | I8: =SUMIF(Monthly!$B$2:$B$133,7,Monthly!$G$2:$G$133) -> 0 | J8: =SUMIF(Monthly!$B$2:$B$133,8,Monthly!$G$2:$G$133) -> 0 | K8: =SUMIF(Monthly!$B$2:$B$133,9,Monthly!$G$2:$G$133) -> 0 | L8: =SUMIF(Monthly!$B$2:$B$133,10,Monthly!$G$2:$G$133) -> 0 | M8: =SUMIF(Monthly!$B$2:$B$133,11,Monthly!$G$2:$G$133) -> 0
A9: Less: general vacancy (floor) | C9: =MAX(0,Inputs!$B$8*C7-C8) -> 113236.18 | D9: =MAX(0,Inputs!$B$8*D7-D8) -> 120272.41 | E9: =MAX(0,Inputs!$B$8*E7-E8) -> 124293.63 | F9: =MAX(0,Inputs!$B$8*F7-F8) -> 128119.85 | G9: =MAX(0,Inputs!$B$8*G7-G8) -> 131980.45 | H9: =MAX(0,Inputs!$B$8*H7-H8) -> 135939.86 | I9: =MAX(0,Inputs!$B$8*I7-I8) -> 140018.06 | J9: =MAX(0,Inputs!$B$8*J7-J8) -> 144218.6 | ... M9: =MAX(0,Inputs!$B$8*M7-M8) -> 157591.56
A10: Income before credit loss | C10: =C7-C8-C9 -> 2215612.3 | D10: =D7-D8-D9 -> 2285175.8 | E10: =E7-E8-E9 -> 2361579 | F10: =F7-F8-F9 -> 2434277.1 | G10: =G7-G8-G9 -> 2507628.6 | H10: =H7-H8-H9 -> 2582857.4 | I10: =I7-I8-I9 -> 2660343.1 | J10: =J7-J8-J9 -> 2740153.4 | ... M10: =M7-M8-M9 -> 2994239.6
A11: Less: credit loss | C11: =Inputs!$B$9*C10 -> 22156.123 | D11: =Inputs!$B$9*D10 -> 22851.758 | E11: =Inputs!$B$9*E10 -> 23615.79 | F11: =Inputs!$B$9*F10 -> 24342.771 | G11: =Inputs!$B$9*G10 -> 25076.286 | H11: =Inputs!$B$9*H10 -> 25828.574 | I11: =Inputs!$B$9*I10 -> 26603.431 | J11: =Inputs!$B$9*J10 -> 27401.534 | ... M11: =Inputs!$B$9*M10 -> 29942.396
A12: Effective gross income | C12: =C10-C11 -> 2193456.2 | D12: =D10-D11 -> 2262324 | E12: =E10-E11 -> 2337963.2 | F12: =F10-F11 -> 2409934.3 | G12: =G10-G11 -> 2482552.3 | H12: =H10-H11 -> 2557028.8 | I12: =I10-I11 -> 2633739.7 | J12: =J10-J11 -> 2712751.9 | ... M12: =M10-M11 -> 2964297.2
A13: Operating expenses | C13: =Inputs!$B$10*Inputs!$B$6*(1+Inputs!$B$11)^(1-1) -> 816000 | D13: =Inputs!$B$10*Inputs!$B$6*(1+Inputs!$B$11)^(2-1) -> 840480 | E13: =Inputs!$B$10*Inputs!$B$6*(1+Inputs!$B$11)^(3-1) -> 865694.4 | F13: =Inputs!$B$10*Inputs!$B$6*(1+Inputs!$B$11)^(4-1) -> 891665.23 | G13: =Inputs!$B$10*Inputs!$B$6*(1+Inputs!$B$11)^(5-1) -> 918415.19 | H13: =Inputs!$B$10*Inputs!$B$6*(1+Inputs!$B$11)^(6-1) -> 945967.64 | I13: =Inputs!$B$10*Inputs!$B$6*(1+Inputs!$B$11)^(7-1) -> 974346.67 | J13: =Inputs!$B$10*Inputs!$B$6*(1+Inputs!$B$11)^(8-1) -> 1003577.1 | K13: =Inputs!$B$10*Inputs!$B$6*(1+Inputs!$B$11)^(9-1) -> 1033684.4 | L13: =Inputs!$B$10*Inputs!$B$6*(1+Inputs!$B$11)^(10-1) -> 1064694.9 | M13: =Inputs!$B$10*Inputs!$B$6*(1+Inputs!$B$11)^(11-1) -> 1096635.8
A14: Management fee | C14: =Inputs!$B$12*C12 -> 65803.686 | D14: =Inputs!$B$12*D12 -> 67869.721 | E14: =Inputs!$B$12*E12 -> 70138.897 | F14: =Inputs!$B$12*F12 -> 72298.03 | G14: =Inputs!$B$12*G12 -> 74476.568 | H14: =Inputs!$B$12*H12 -> 76710.865 | I14: =Inputs!$B$12*I12 -> 79012.191 | J14: =Inputs!$B$12*J12 -> 81382.557 | ... M14: =Inputs!$B$12*M12 -> 88928.917
A15: Total operating expenses | C15: =C13+C14 -> 881803.69 | D15: =D13+D14 -> 908349.72 | E15: =E13+E14 -> 935833.3 | F15: =F13+F14 -> 963963.26 | G15: =G13+G14 -> 992891.76 | H15: =H13+H14 -> 1022678.5 | I15: =I13+I14 -> 1053358.9 | J15: =J13+J14 -> 1084959.6 | ... M15: =M13+M14 -> 1185564.7
A16: Net operating income | C16: =C12-C15 -> 1311652.5 | D16: =D12-D15 -> 1353974.3 | E16: =E12-E15 -> 1402129.9 | F16: =F12-F15 -> 1445971.1 | G16: =G12-G15 -> 1489660.5 | H16: =H12-H15 -> 1534350.3 | I16: =I12-I15 -> 1580380.8 | J16: =J12-J15 -> 1627792.3 | ... M16: =M12-M15 -> 1778732.6
A17: Turnover cost | C17: =SUMIF(Monthly!$B$2:$B$133,1,Monthly!$I$2:$I$133) -> 55500 | D17: =SUMIF(Monthly!$B$2:$B$133,2,Monthly!$I$2:$I$133) -> 61800 | E17: =SUMIF(Monthly!$B$2:$B$133,3,Monthly!$I$2:$I$133) -> 63654 | F17: =SUMIF(Monthly!$B$2:$B$133,4,Monthly!$I$2:$I$133) -> 65563.62 | G17: =SUMIF(Monthly!$B$2:$B$133,5,Monthly!$I$2:$I$133) -> 67530.529 | H17: =SUMIF(Monthly!$B$2:$B$133,6,Monthly!$I$2:$I$133) -> 69556.444 | I17: =SUMIF(Monthly!$B$2:$B$133,7,Monthly!$I$2:$I$133) -> 71643.138 | J17: =SUMIF(Monthly!$B$2:$B$133,8,Monthly!$I$2:$I$133) -> 73792.432 | K17: =SUMIF(Monthly!$B$2:$B$133,9,Monthly!$I$2:$I$133) -> 76006.205 | L17: =SUMIF(Monthly!$B$2:$B$133,10,Monthly!$I$2:$I$133) -> 78286.391 | M17: =SUMIF(Monthly!$B$2:$B$133,11,Monthly!$I$2:$I$133) -> 80634.983
A18: Capital reserves | C18: =Inputs!$B$13*Inputs!$B$6 -> 36000 | D18: =Inputs!$B$13*Inputs!$B$6 -> 36000 | E18: =Inputs!$B$13*Inputs!$B$6 -> 36000 | F18: =Inputs!$B$13*Inputs!$B$6 -> 36000 | G18: =Inputs!$B$13*Inputs!$B$6 -> 36000 | H18: =Inputs!$B$13*Inputs!$B$6 -> 36000 | I18: =Inputs!$B$13*Inputs!$B$6 -> 36000 | J18: =Inputs!$B$13*Inputs!$B$6 -> 36000 | ... M18: =Inputs!$B$13*Inputs!$B$6 -> 36000
A19: Cash flow before debt | C19: =C16-C17-C18 -> 1220152.5 | D19: =D16-D17-D18 -> 1256174.3 | E19: =E16-E17-E18 -> 1302475.9 | F19: =F16-F17-F18 -> 1344407.4 | G19: =G16-G17-G18 -> 1386130 | H19: =H16-H17-H18 -> 1428793.9 | I19: =I16-I17-I18 -> 1472737.7 | J19: =J16-J17-J18 -> 1517999.8 | ... M19: =M16-M17-M18 -> 1662097.6
A20: Debt service | C20: =SUMIF(Monthly!$B$2:$B$133,1,Monthly!$K$2:$K$133) -> 818471.17 | D20: =SUMIF(Monthly!$B$2:$B$133,2,Monthly!$K$2:$K$133) -> 818471.17 | E20: =SUMIF(Monthly!$B$2:$B$133,3,Monthly!$K$2:$K$133) -> 955069.76 | F20: =SUMIF(Monthly!$B$2:$B$133,4,Monthly!$K$2:$K$133) -> 955069.76 | G20: =SUMIF(Monthly!$B$2:$B$133,5,Monthly!$K$2:$K$133) -> 955069.76 | H20: =SUMIF(Monthly!$B$2:$B$133,6,Monthly!$K$2:$K$133) -> 955069.76 | I20: =SUMIF(Monthly!$B$2:$B$133,7,Monthly!$K$2:$K$133) -> 955069.76 | J20: =SUMIF(Monthly!$B$2:$B$133,8,Monthly!$K$2:$K$133) -> 955069.76 | K20: =SUMIF(Monthly!$B$2:$B$133,9,Monthly!$K$2:$K$133) -> 955069.76 | L20: =SUMIF(Monthly!$B$2:$B$133,10,Monthly!$K$2:$K$133) -> 955069.76 | M20: =SUMIF(Monthly!$B$2:$B$133,11,Monthly!$K$2:$K$133) -> 0
A21: Cash flow after debt | C21: =C19-C20 -> 401681.35 | D21: =D19-D20 -> 437703.15 | E21: =E19-E20 -> 347406.18 | F21: =F19-F20 -> 389337.68 | G21: =G19-G20 -> 431060.23 | H21: =H19-H20 -> 473724.13 | I21: =I19-I20 -> 517667.94 | J21: =J19-J20 -> 562930.07 | ... M21: =M19-M20 -> 1662097.6
A23: Occupied unit-months | C23: =SUMIF(Monthly!$B$2:$B$133,1,Monthly!$H$2:$H$133) -> 1438 | D23: =SUMIF(Monthly!$B$2:$B$133,2,Monthly!$H$2:$H$133) -> 1440 | E23: =SUMIF(Monthly!$B$2:$B$133,3,Monthly!$H$2:$H$133) -> 1440 | F23: =SUMIF(Monthly!$B$2:$B$133,4,Monthly!$H$2:$H$133) -> 1440 | G23: =SUMIF(Monthly!$B$2:$B$133,5,Monthly!$H$2:$H$133) -> 1440 | H23: =SUMIF(Monthly!$B$2:$B$133,6,Monthly!$H$2:$H$133) -> 1440 | I23: =SUMIF(Monthly!$B$2:$B$133,7,Monthly!$H$2:$H$133) -> 1440 | J23: =SUMIF(Monthly!$B$2:$B$133,8,Monthly!$H$2:$H$133) -> 1440 | K23: =SUMIF(Monthly!$B$2:$B$133,9,Monthly!$H$2:$H$133) -> 1440 | L23: =SUMIF(Monthly!$B$2:$B$133,10,Monthly!$H$2:$H$133) -> 1440 | M23: =SUMIF(Monthly!$B$2:$B$133,11,Monthly!$H$2:$H$133) -> 1440
A24: Physical occupancy | C24: =C23/(Inputs!$B$6*12) -> 0.99861111 | D24: =D23/(Inputs!$B$6*12) -> 1 | E24: =E23/(Inputs!$B$6*12) -> 1 | F24: =F23/(Inputs!$B$6*12) -> 1 | G24: =G23/(Inputs!$B$6*12) -> 1 | H24: =H23/(Inputs!$B$6*12) -> 1 | I24: =I23/(Inputs!$B$6*12) -> 1 | J24: =J23/(Inputs!$B$6*12) -> 1 | ... M24: =M23/(Inputs!$B$6*12) -> 1
A25: DSCR | C25: =IF(C20=0,"",C16/C20) -> 1.6025641 | D25: =IF(D20=0,"",D16/D20) -> 1.6542725 | E25: =IF(E20=0,"",E16/E20) -> 1.4680916 | F25: =IF(F20=0,"",F16/F20) -> 1.5139952 | G25: =IF(G20=0,"",G16/G20) -> 1.55974 | H25: =IF(H20=0,"",H16/H20) -> 1.6065322 | I25: =IF(I20=0,"",I16/I20) -> 1.6547282 | J25: =IF(J20=0,"",J16/J20) -> 1.70437 | ... M25: =IF(M20=0,"",M16/M20)
A26: Cash-on-cash | C26: =C21/Returns!$C$10 -> 0.045463282 | D26: =D21/Returns!$C$10 -> 0.049540319 | E26: =E21/Returns!$C$10 -> 0.039320285 | F26: =F21/Returns!$C$10 -> 0.044066196 | G26: =G21/Returns!$C$10 -> 0.048788456 | H26: =H21/Returns!$C$10 -> 0.053617261 | I26: =I21/Returns!$C$10 -> 0.058590931 | J26: =J21/Returns!$C$10 -> 0.06371381 | ... M26: =M21/Returns!$C$10 -> 0.18812029
A28: Year 11 normalized for exit (absorption vacancy removed, full 5% general vacancy)
A29: Potential gross income | M29: =M7 -> 3151831.2
A30: General vacancy (full) | M30: =Inputs!$B$8*M29 -> 157591.56
A31: Income before credit loss | M31: =M29-M30 -> 2994239.6
A32: Credit loss | M32: =Inputs!$B$9*M31 -> 29942.396
A33: Effective gross income | M33: =M31-M32 -> 2964297.2
A34: Operating expenses | M34: =M13 -> 1096635.8
A35: Management fee | M35: =Inputs!$B$12*M33 -> 88928.917
A36: Normalized year-11 NOI | M36: =M33-M34-M35 -> 1778732.6
A37: Note: rows 20, 21, 25, 26 are blank in year 11 (sale after month 120).

Sheet Units
A1: Unit | B1: Floor plan | C1: SF | D1: Status | E1: Market rent $/mo | F1: In-place rent $/mo | G1: Other income $/mo | H1: Lease end | I1: Pre-leased | J1: Future lease rent | K1: Occupied (1/0) | L1: On notice w/ signed resident | M1: First roll month (occupied) | N1: Lease-up queue position | O1: Lease-up start month | P1: Leased from month | Q1: First regular roll month | R1: Rent at lease-up start
A2: 101 | B2: 735 SF | C2: 735 | D2: Occupied | E2: 1525 | F2: 1565 | G2: 0 | H2: 46356 | K2: =IF(D2="Occupied",1,0) -> 1 | L2: =IF(AND(K2=1,I2="Yes"),1,0) -> 0 | M2: =IF(K2=1,IF(OR(H2="",H2<Inputs!$B$5),1,(YEAR(H2)-YEAR(Inputs!$B$5))*12+MONTH(H2)-MONTH(Inputs!$B$5)+2),"") -> 2 | N2: =IF(K2=0,IF(I2="Yes",COUNTIFS(K$2:K2,0,I$2:I2,"Yes")-1,COUNTIFS(K$2:K$121,0,I$2:I$121,"Yes")+COUNTIFS(K$2:K2,0,I$2:I2,"<>Yes")-1),"") | O2: =IF(K2=0,INT(N2/Inputs!$B$17)+1,"") | P2: =IF(K2=1,1,O2) -> 1 | Q2: =IF(K2=1,M2,O2+12) -> 2 | R2: =IF(K2=0,IF(AND(I2="Yes",J2<>""),J2,E2*(1+Inputs!$B$7)^(INT((O2-1)/12))),"")
A3: 102 | B3: 735 SF | C3: 735 | D3: Occupied | E3: 1525 | F3: 1235 | G3: 45 | H3: 46477 | K3: =IF(D3="Occupied",1,0) -> 1 | L3: =IF(AND(K3=1,I3="Yes"),1,0) -> 0 | M3: =IF(K3=1,IF(OR(H3="",H3<Inputs!$B$5),1,(YEAR(H3)-YEAR(Inputs!$B$5))*12+MONTH(H3)-MONTH(Inputs!$B$5)+2),"") -> 6 | N3: =IF(K3=0,IF(I3="Yes",COUNTIFS(K$2:K3,0,I$2:I3,"Yes")-1,COUNTIFS(K$2:K$121,0,I$2:I$121,"Yes")+COUNTIFS(K$2:K3,0,I$2:I3,"<>Yes")-1),"") | O3: =IF(K3=0,INT(N3/Inputs!$B$17)+1,"") | P3: =IF(K3=1,1,O3) -> 1 | Q3: =IF(K3=1,M3,O3+12) -> 6 | R3: =IF(K3=0,IF(AND(I3="Yes",J3<>""),J3,E3*(1+Inputs!$B$7)^(INT((O3-1)/12))),"")
A4: 103 | B4: 735 SF | C4: 735 | D4: Occupied | E4: 1525 | F4: 1475 | G4: 62 | H4: 46630 | K4: =IF(D4="Occupied",1,0) -> 1 | L4: =IF(AND(K4=1,I4="Yes"),1,0) -> 0 | M4: =IF(K4=1,IF(OR(H4="",H4<Inputs!$B$5),1,(YEAR(H4)-YEAR(Inputs!$B$5))*12+MONTH(H4)-MONTH(Inputs!$B$5)+2),"") -> 11 | N4: =IF(K4=0,IF(I4="Yes",COUNTIFS(K$2:K4,0,I$2:I4,"Yes")-1,COUNTIFS(K$2:K$121,0,I$2:I$121,"Yes")+COUNTIFS(K$2:K4,0,I$2:I4,"<>Yes")-1),"") | O4: =IF(K4=0,INT(N4/Inputs!$B$17)+1,"") | P4: =IF(K4=1,1,O4) -> 1 | Q4: =IF(K4=1,M4,O4+12) -> 11 | R4: =IF(K4=0,IF(AND(I4="Yes",J4<>""),J4,E4*(1+Inputs!$B$7)^(INT((O4-1)/12))),"")
A5: 104 | B5: 735 SF | C5: 735 | D5: Vacant | E5: 1525 | F5: 0 | G5: 0 | K5: =IF(D5="Occupied",1,0) -> 0 | L5: =IF(AND(K5=1,I5="Yes"),1,0) -> 0 | M5: =IF(K5=1,IF(OR(H5="",H5<Inputs!$B$5),1,(YEAR(H5)-YEAR(Inputs!$B$5))*12+MONTH(H5)-MONTH(Inputs!$B$5)+2),"") | N5: =IF(K5=0,IF(I5="Yes",COUNTIFS(K$2:K5,0,I$2:I5,"Yes")-1,COUNTIFS(K$2:K$121,0,I$2:I$121,"Yes")+COUNTIFS(K$2:K5,0,I$2:I5,"<>Yes")-1),"") -> 3 | O5: =IF(K5=0,INT(N5/Inputs!$B$17)+1,"") -> 1 | P5: =IF(K5=1,1,O5) -> 1 | Q5: =IF(K5=1,M5,O5+12) -> 13 | R5: =IF(K5=0,IF(AND(I5="Yes",J5<>""),J5,E5*(1+Inputs!$B$7)^(INT((O5-1)/12))),"") -> 1525
A6: 105 | B6: 735 SF | C6: 735 | D6: Occupied | E6: 1525 | F6: 1445 | G6: 0 | H6: 46387 | K6: =IF(D6="Occupied",1,0) -> 1 | L6: =IF(AND(K6=1,I6="Yes"),1,0) -> 0 | M6: =IF(K6=1,IF(OR(H6="",H6<Inputs!$B$5),1,(YEAR(H6)-YEAR(Inputs!$B$5))*12+MONTH(H6)-MONTH(Inputs!$B$5)+2),"") -> 3 | N6: =IF(K6=0,IF(I6="Yes",COUNTIFS(K$2:K6,0,I$2:I6,"Yes")-1,COUNTIFS(K$2:K$121,0,I$2:I$121,"Yes")+COUNTIFS(K$2:K6,0,I$2:I6,"<>Yes")-1),"") | O6: =IF(K6=0,INT(N6/Inputs!$B$17)+1,"") | P6: =IF(K6=1,1,O6) -> 1 | Q6: =IF(K6=1,M6,O6+12) -> 3 | R6: =IF(K6=0,IF(AND(I6="Yes",J6<>""),J6,E6*(1+Inputs!$B$7)^(INT((O6-1)/12))),"")
A7: 106 | B7: 735 SF | C7: 735 | D7: Occupied | E7: 1525 | F7: 1400 | G7: 52 | H7: 46418 | K7: =IF(D7="Occupied",1,0) -> 1 | L7: =IF(AND(K7=1,I7="Yes"),1,0) -> 0 | M7: =IF(K7=1,IF(OR(H7="",H7<Inputs!$B$5),1,(YEAR(H7)-YEAR(Inputs!$B$5))*12+MONTH(H7)-MONTH(Inputs!$B$5)+2),"") -> 4 | N7: =IF(K7=0,IF(I7="Yes",COUNTIFS(K$2:K7,0,I$2:I7,"Yes")-1,COUNTIFS(K$2:K$121,0,I$2:I$121,"Yes")+COUNTIFS(K$2:K7,0,I$2:I7,"<>Yes")-1),"") | O7: =IF(K7=0,INT(N7/Inputs!$B$17)+1,"") | P7: =IF(K7=1,1,O7) -> 1 | Q7: =IF(K7=1,M7,O7+12) -> 4 | R7: =IF(K7=0,IF(AND(I7="Yes",J7<>""),J7,E7*(1+Inputs!$B$7)^(INT((O7-1)/12))),"")
A8: 107 | B8: 735 SF | C8: 735 | D8: Occupied | E8: 1525 | F8: 1580 | G8: 45 | H8: 46387 | K8: =IF(D8="Occupied",1,0) -> 1 | L8: =IF(AND(K8=1,I8="Yes"),1,0) -> 0 | M8: =IF(K8=1,IF(OR(H8="",H8<Inputs!$B$5),1,(YEAR(H8)-YEAR(Inputs!$B$5))*12+MONTH(H8)-MONTH(Inputs!$B$5)+2),"") -> 3 | N8: =IF(K8=0,IF(I8="Yes",COUNTIFS(K$2:K8,0,I$2:I8,"Yes")-1,COUNTIFS(K$2:K$121,0,I$2:I$121,"Yes")+COUNTIFS(K$2:K8,0,I$2:I8,"<>Yes")-1),"") | O8: =IF(K8=0,INT(N8/Inputs!$B$17)+1,"") | P8: =IF(K8=1,1,O8) -> 1 | Q8: =IF(K8=1,M8,O8+12) -> 3 | R8: =IF(K8=0,IF(AND(I8="Yes",J8<>""),J8,E8*(1+Inputs!$B$7)^(INT((O8-1)/12))),"")
A9: 108 | B9: 735 SF | C9: 735 | D9: Occupied | E9: 1525 | F9: 1475 | G9: 0 | H9: 46538 | K9: =IF(D9="Occupied",1,0) -> 1 | L9: =IF(AND(K9=1,I9="Yes"),1,0) -> 0 | M9: =IF(K9=1,IF(OR(H9="",H9<Inputs!$B$5),1,(YEAR(H9)-YEAR(Inputs!$B$5))*12+MONTH(H9)-MONTH(Inputs!$B$5)+2),"") -> 8 | N9: =IF(K9=0,IF(I9="Yes",COUNTIFS(K$2:K9,0,I$2:I9,"Yes")-1,COUNTIFS(K$2:K$121,0,I$2:I$121,"Yes")+COUNTIFS(K$2:K9,0,I$2:I9,"<>Yes")-1),"") | O9: =IF(K9=0,INT(N9/Inputs!$B$17)+1,"") | P9: =IF(K9=1,1,O9) -> 1 | Q9: =IF(K9=1,M9,O9+12) -> 8 | R9: =IF(K9=0,IF(AND(I9="Yes",J9<>""),J9,E9*(1+Inputs!$B$7)^(INT((O9-1)/12))),"")
A10: 109 | B10: 735 SF | C10: 735 | D10: Occupied | E10: 1525 | F10: 1565 | G10: 12 | H10: 46568 | K10: =IF(D10="Occupied",1,0) -> 1 | L10: =IF(AND(K10=1,I10="Yes"),1,0) -> 0 | M10: =IF(K10=1,IF(OR(H10="",H10<Inputs!$B$5),1,(YEAR(H10)-YEAR(Inputs!$B$5))*12+MONTH(H10)-MONTH(Inputs!$B$5)+2),"") -> 9 | N10: =IF(K10=0,IF(I10="Yes",COUNTIFS(K$2:K10,0,I$2:I10,"Yes")-1,COUNTIFS(K$2:K$121,0,I$2:I$121,"Yes")+COUNTIFS(K$2:K10,0,I$2:I10,"<>Yes")-1),"") | O10: =IF(K10=0,INT(N10/Inputs!$B$17)+1,"") | P10: =IF(K10=1,1,O10) -> 1 | Q10: =IF(K10=1,M10,O10+12) -> 9 | R10: =IF(K10=0,IF(AND(I10="Yes",J10<>""),J10,E10*(1+Inputs!$B$7)^(INT((O10-1)/12))),"")
A11: 110 | B11: 735 SF | C11: 735 | D11: Occupied | E11: 1525 | F11: 1500 | G11: 37 | H11: 46660 | K11: =IF(D11="Occupied",1,0) -> 1 | L11: =IF(AND(K11=1,I11="Yes"),1,0) -> 0 | M11: =IF(K11=1,IF(OR(H11="",H11<Inputs!$B$5),1,(YEAR(H11)-YEAR(Inputs!$B$5))*12+MONTH(H11)-MONTH(Inputs!$B$5)+2),"") -> 12 | N11: =IF(K11=0,IF(I11="Yes",COUNTIFS(K$2:K11,0,I$2:I11,"Yes")-1,COUNTIFS(K$2:K$121,0,I$2:I$121,"Yes")+COUNTIFS(K$2:K11,0,I$2:I11,"<>Yes")-1),"") | O11: =IF(K11=0,INT(N11/Inputs!$B$17)+1,"") | P11: =IF(K11=1,1,O11) -> 1 | Q11: =IF(K11=1,M11,O11+12) -> 12 | R11: =IF(K11=0,IF(AND(I11="Yes",J11<>""),J11,E11*(1+Inputs!$B$7)^(INT((O11-1)/12))),"")
A12: 111 | B12: 735 SF | C12: 735 | D12: Occupied | E12: 1525 | F12: 1450 | G12: 47 | H12: 46538 | K12: =IF(D12="Occupied",1,0) -> 1 | L12: =IF(AND(K12=1,I12="Yes"),1,0) -> 0 | M12: =IF(K12=1,IF(OR(H12="",H12<Inputs!$B$5),1,(YEAR(H12)-YEAR(Inputs!$B$5))*12+MONTH(H12)-MONTH(Inputs!$B$5)+2),"") -> 8 | N12: =IF(K12=0,IF(I12="Yes",COUNTIFS(K$2:K12,0,I$2:I12,"Yes")-1,COUNTIFS(K$2:K$121,0,I$2:I$121,"Yes")+COUNTIFS(K$2:K12,0,I$2:I12,"<>Yes")-1),"") | O12: =IF(K12=0,INT(N12/Inputs!$B$17)+1,"") | P12: =IF(K12=1,1,O12) -> 1 | Q12: =IF(K12=1,M12,O12+12) -> 8 | R12: =IF(K12=0,IF(AND(I12="Yes",J12<>""),J12,E12*(1+Inputs!$B$7)^(INT((O12-1)/12))),"")
A13: 112 | B13: 735 SF | C13: 735 | D13: Occupied | E13: 1525 | F13: 1555 | G13: 12 | H13: 46418 | K13: =IF(D13="Occupied",1,0) -> 1 | L13: =IF(AND(K13=1,I13="Yes"),1,0) -> 0 | M13: =IF(K13=1,IF(OR(H13="",H13<Inputs!$B$5),1,(YEAR(H13)-YEAR(Inputs!$B$5))*12+MONTH(H13)-MONTH(Inputs!$B$5)+2),"") -> 4 | N13: =IF(K13=0,IF(I13="Yes",COUNTIFS(K$2:K13,0,I$2:I13,"Yes")-1,COUNTIFS(K$2:K$121,0,I$2:I$121,"Yes")+COUNTIFS(K$2:K13,0,I$2:I13,"<>Yes")-1),"") | O13: =IF(K13=0,INT(N13/Inputs!$B$17)+1,"") | P13: =IF(K13=1,1,O13) -> 1 | Q13: =IF(K13=1,M13,O13+12) -> 4 | R13: =IF(K13=0,IF(AND(I13="Yes",J13<>""),J13,E13*(1+Inputs!$B$7)^(INT((O13-1)/12))),"")
A14: 113 | B14: 560 SF | C14: 560 | D14: Occupied | E14: 1295 | F14: 1320 | G14: 12 | H14: 46568 | K14: =IF(D14="Occupied",1,0) -> 1 | L14: =IF(AND(K14=1,I14="Yes"),1,0) -> 0 | M14: =IF(K14=1,IF(OR(H14="",H14<Inputs!$B$5),1,(YEAR(H14)-YEAR(Inputs!$B$5))*12+MONTH(H14)-MONTH(Inputs!$B$5)+2),"") -> 9 | N14: =IF(K14=0,IF(I14="Yes",COUNTIFS(K$2:K14,0,I$2:I14,"Yes")-1,COUNTIFS(K$2:K$121,0,I$2:I$121,"Yes")+COUNTIFS(K$2:K14,0,I$2:I14,"<>Yes")-1),"") | O14: =IF(K14=0,INT(N14/Inputs!$B$17)+1,"") | P14: =IF(K14=1,1,O14) -> 1 | Q14: =IF(K14=1,M14,O14+12) -> 9 | R14: =IF(K14=0,IF(AND(I14="Yes",J14<>""),J14,E14*(1+Inputs!$B$7)^(INT((O14-1)/12))),"")
A15: 114 | B15: 560 SF | C15: 560 | D15: Occupied | E15: 1295 | F15: 1245 | G15: 0 | H15: 46599 | K15: =IF(D15="Occupied",1,0) -> 1 | L15: =IF(AND(K15=1,I15="Yes"),1,0) -> 0 | M15: =IF(K15=1,IF(OR(H15="",H15<Inputs!$B$5),1,(YEAR(H15)-YEAR(Inputs!$B$5))*12+MONTH(H15)-MONTH(Inputs!$B$5)+2),"") -> 10 | N15: =IF(K15=0,IF(I15="Yes",COUNTIFS(K$2:K15,0,I$2:I15,"Yes")-1,COUNTIFS(K$2:K$121,0,I$2:I$121,"Yes")+COUNTIFS(K$2:K15,0,I$2:I15,"<>Yes")-1),"") | O15: =IF(K15=0,INT(N15/Inputs!$B$17)+1,"") | P15: =IF(K15=1,1,O15) -> 1 | Q15: =IF(K15=1,M15,O15+12) -> 10 | R15: =IF(K15=0,IF(AND(I15="Yes",J15<>""),J15,E15*(1+Inputs!$B$7)^(INT((O15-1)/12))),"")
A16: 115 | B16: 560 SF | C16: 560 | D16: Occupied | E16: 1295 | F16: 1030 | G16: 35 | H16: 46599 | K16: =IF(D16="Occupied",1,0) -> 1 | L16: =IF(AND(K16=1,I16="Yes"),1,0) -> 0 | M16: =IF(K16=1,IF(OR(H16="",H16<Inputs!$B$5),1,(YEAR(H16)-YEAR(Inputs!$B$5))*12+MONTH(H16)-MONTH(Inputs!$B$5)+2),"") -> 10 | N16: =IF(K16=0,IF(I16="Yes",COUNTIFS(K$2:K16,0,I$2:I16,"Yes")-1,COUNTIFS(K$2:K$121,0,I$2:I$121,"Yes")+COUNTIFS(K$2:K16,0,I$2:I16,"<>Yes")-1),"") | O16: =IF(K16=0,INT(N16/Inputs!$B$17)+1,"") | P16: =IF(K16=1,1,O16) -> 1 | Q16: =IF(K16=1,M16,O16+12) -> 10 | R16: =IF(K16=0,IF(AND(I16="Yes",J16<>""),J16,E16*(1+Inputs!$B$7)^(INT((O16-1)/12))),"")
A17: 116 | B17: 560 SF | C17: 560 | D17: Occupied | E17: 1295 | F17: 1330 | G17: 45 | H17: 46356 | K17: =IF(D17="Occupied",1,0) -> 1 | L17: =IF(AND(K17=1,I17="Yes"),1,0) -> 0 | M17: =IF(K17=1,IF(OR(H17="",H17<Inputs!$B$5),1,(YEAR(H17)-YEAR(Inputs!$B$5))*12+MONTH(H17)-MONTH(Inputs!$B$5)+2),"") -> 2 | N17: =IF(K17=0,IF(I17="Yes",COUNTIFS(K$2:K17,0,I$2:I17,"Yes")-1,COUNTIFS(K$2:K$121,0,I$2:I$121,"Yes")+COUNTIFS(K$2:K17,0,I$2:I17,"<>Yes")-1),"") | O17: =IF(K17=0,INT(N17/Inputs!$B$17)+1,"") | P17: =IF(K17=1,1,O17) -> 1 | Q17: =IF(K17=1,M17,O17+12) -> 2 | R17: =IF(K17=0,IF(AND(I17="Yes",J17<>""),J17,E17*(1+Inputs!$B$7)^(INT((O17-1)/12))),"")
A18: 117 | B18: 560 SF | C18: 560 | D18: Vacant | E18: 1295 | F18: 0 | G18: 0 | I18: Yes | K18: =IF(D18="Occupied",1,0) -> 0 | L18: =IF(AND(K18=1,I18="Yes"),1,0) -> 0 | M18: =IF(K18=1,IF(OR(H18="",H18<Inputs!$B$5),1,(YEAR(H18)-YEAR(Inputs!$B$5))*12+MONTH(H18)-MONTH(Inputs!$B$5)+2),"") | N18: =IF(K18=0,IF(I18="Yes",COUNTIFS(K$2:K18,0,I$2:I18,"Yes")-1,COUNTIFS(K$2:K$121,0,I$2:I$121,"Yes")+COUNTIFS(K$2:K18,0,I$2:I18,"<>Yes")-1),"") -> 0 | O18: =IF(K18=0,INT(N18/Inputs!$B$17)+1,"") -> 1 | P18: =IF(K18=1,1,O18) -> 1 | Q18: =IF(K18=1,M18,O18+12) -> 13 | R18: =IF(K18=0,IF(AND(I18="Yes",J18<>""),J18,E18*(1+Inputs!$B$7)^(INT((O18-1)/12))),"") -> 1295
A19: 118 | B19: 560 SF | C19: 560 | D19: Occupied | E19: 1295 | F19: 1225 | G19: 0 | H19: 46568 | K19: =IF(D19="Occupied",1,0) -> 1 | L19: =IF(AND(K19=1,I19="Yes"),1,0) -> 0 | M19: =IF(K19=1,IF(OR(H19="",H19<Inputs!$B$5),1,(YEAR(H19)-YEAR(Inputs!$B$5))*12+MONTH(H19)-MONTH(Inputs!$B$5)+2),"") -> 9 | N19: =IF(K19=0,IF(I19="Yes",COUNTIFS(K$2:K19,0,I$2:I19,"Yes")-1,COUNTIFS(K$2:K$121,0,I$2:I$121,"Yes")+COUNTIFS(K$2:K19,0,I$2:I19,"<>Yes")-1),"") | O19: =IF(K19=0,INT(N19/Inputs!$B$17)+1,"") | P19: =IF(K19=1,1,O19) -> 1 | Q19: =IF(K19=1,M19,O19+12) -> 9 | R19: =IF(K19=0,IF(AND(I19="Yes",J19<>""),J19,E19*(1+Inputs!$B$7)^(INT((O19-1)/12))),"")
A20: 119 | B20: 560 SF | C20: 560 | D20: Occupied | E20: 1295 | F20: 1270 | G20: 0 | H20: 46568 | K20: =IF(D20="Occupied",1,0) -> 1 | L20: =IF(AND(K20=1,I20="Yes"),1,0) -> 0 | M20: =IF(K20=1,IF(OR(H20="",H20<Inputs!$B$5),1,(YEAR(H20)-YEAR(Inputs!$B$5))*12+MONTH(H20)-MONTH(Inputs!$B$5)+2),"") -> 9 | N20: =IF(K20=0,IF(I20="Yes",COUNTIFS(K$2:K20,0,I$2:I20,"Yes")-1,COUNTIFS(K$2:K$121,0,I$2:I$121,"Yes")+COUNTIFS(K$2:K20,0,I$2:I20,"<>Yes")-1),"") | O20: =IF(K20=0,INT(N20/Inputs!$B$17)+1,"") | P20: =IF(K20=1,1,O20) -> 1 | Q20: =IF(K20=1,M20,O20+12) -> 9 | R20: =IF(K20=0,IF(AND(I20="Yes",J20<>""),J20,E20*(1+Inputs!$B$7)^(INT((O20-1)/12))),"")
A21: 120 | B21: 560 SF | C21: 560 | D21: Occupied | E21: 1295 | F21: 1190 | G21: 0 | H21: 46568 | K21: =IF(D21="Occupied",1,0) -> 1 | L21: =IF(AND(K21=1,I21="Yes"),1,0) -> 0 | M21: =IF(K21=1,IF(OR(H21="",H21<Inputs!$B$5),1,(YEAR(H21)-YEAR(Inputs!$B$5))*12+MONTH(H21)-MONTH(Inputs!$B$5)+2),"") -> 9 | N21: =IF(K21=0,IF(I21="Yes",COUNTIFS(K$2:K21,0,I$2:I21,"Yes")-1,COUNTIFS(K$2:K$121,0,I$2:I$121,"Yes")+COUNTIFS(K$2:K21,0,I$2:I21,"<>Yes")-1),"") | O21: =IF(K21=0,INT(N21/Inputs!$B$17)+1,"") | P21: =IF(K21=1,1,O21) -> 1 | Q21: =IF(K21=1,M21,O21+12) -> 9 | R21: =IF(K21=0,IF(AND(I21="Yes",J21<>""),J21,E21*(1+Inputs!$B$7)^(INT((O21-1)/12))),"")
A22: 121 | B22: 960 SF | C22: 960 | D22: Occupied | E22: 1850 | F22: 1800 | G22: 40 | H22: 46387 | K22: =IF(D22="Occupied",1,0) -> 1 | L22: =IF(AND(K22=1,I22="Yes"),1,0) -> 0 | M22: =IF(K22=1,IF(OR(H22="",H22<Inputs!$B$5),1,(YEAR(H22)-YEAR(Inputs!$B$5))*12+MONTH(H22)-MONTH(Inputs!$B$5)+2),"") -> 3 | N22: =IF(K22=0,IF(I22="Yes",COUNTIFS(K$2:K22,0,I$2:I22,"Yes")-1,COUNTIFS(K$2:K$121,0,I$2:I$121,"Yes")+COUNTIFS(K$2:K22,0,I$2:I22,"<>Yes")-1),"") | O22: =IF(K22=0,INT(N22/Inputs!$B$17)+1,"") | P22: =IF(K22=1,1,O22) -> 1 | Q22: =IF(K22=1,M22,O22+12) -> 3 | R22: =IF(K22=0,IF(AND(I22="Yes",J22<>""),J22,E22*(1+Inputs!$B$7)^(INT((O22-1)/12))),"")
A23: 122 | B23: 960 SF | C23: 960 | D23: Occupied | E23: 1850 | F23: 1725 | G23: 0 | H23: 46599 | K23: =IF(D23="Occupied",1,0) -> 1 | L23: =IF(AND(K23=1,I23="Yes"),1,0) -> 0 | M23: =IF(K23=1,IF(OR(H23="",H23<Inputs!$B$5),1,(YEAR(H23)-YEAR(Inputs!$B$5))*12+MONTH(H23)-MONTH(Inputs!$B$5)+2),"") -> 10 | N23: =IF(K23=0,IF(I23="Yes",COUNTIFS(K$2:K23,0,I$2:I23,"Yes")-1,COUNTIFS(K$2:K$121,0,I$2:I$121,"Yes")+COUNTIFS(K$2:K23,0,I$2:I23,"<>Yes")-1),"") | O23: =IF(K23=0,INT(N23/Inputs!$B$17)+1,"") | P23: =IF(K23=1,1,O23) -> 1 | Q23: =IF(K23=1,M23,O23+12) -> 10 | R23: =IF(K23=0,IF(AND(I23="Yes",J23<>""),J23,E23*(1+Inputs!$B$7)^(INT((O23-1)/12))),"")
A24: 123 | B24: 960 SF | C24: 960 | D24: Occupied | E24: 1850 | F24: 1750 | G24: 45 | H24: 46507 | K24: =IF(D24="Occupied",1,0) -> 1 | L24: =IF(AND(K24=1,I24="Yes"),1,0) -> 0 | M24: =IF(K24=1,IF(OR(H24="",H24<Inputs!$B$5),1,(YEAR(H24)-YEAR(Inputs!$B$5))*12+MONTH(H24)-MONTH(Inputs!$B$5)+2),"") -> 7 | N24: =IF(K24=0,IF(I24="Yes",COUNTIFS(K$2:K24,0,I$2:I24,"Yes")-1,COUNTIFS(K$2:K$121,0,I$2:I$121,"Yes")+COUNTIFS(K$2:K24,0,I$2:I24,"<>Yes")-1),"") | O24: =IF(K24=0,INT(N24/Inputs!$B$17)+1,"") | P24: =IF(K24=1,1,O24) -> 1 | Q24: =IF(K24=1,M24,O24+12) -> 7 | R24: =IF(K24=0,IF(AND(I24="Yes",J24<>""),J24,E24*(1+Inputs!$B$7)^(INT((O24-1)/12))),"")
A25: 124 | B25: 960 SF | C25: 960 | D25: Occupied | E25: 1850 | F25: 1680 | G25: 80 | H25: 46630 | K25: =IF(D25="Occupied",1,0) -> 1 | L25: =IF(AND(K25=1,I25="Yes"),1,0) -> 0 | M25: =IF(K25=1,IF(OR(H25="",H25<Inputs!$B$5),1,(YEAR(H25)-YEAR(Inputs!$B$5))*12+MONTH(H25)-MONTH(Inputs!$B$5)+2),"") -> 11 | N25: =IF(K25=0,IF(I25="Yes",COUNTIFS(K$2:K25,0,I$2:I25,"Yes")-1,COUNTIFS(K$2:K$121,0,I$2:I$121,"Yes")+COUNTIFS(K$2:K25,0,I$2:I25,"<>Yes")-1),"") | O25: =IF(K25=0,INT(N25/Inputs!$B$17)+1,"") | P25: =IF(K25=1,1,O25) -> 1 | Q25: =IF(K25=1,M25,O25+12) -> 11 | R25: =IF(K25=0,IF(AND(I25="Yes",J25<>""),J25,E25*(1+Inputs!$B$7)^(INT((O25-1)/12))),"")
A26: 125 | B26: 960 SF | C26: 960 | D26: Occupied | E26: 1850 | F26: 1895 | G26: 0 | H26: 46660 | K26: =IF(D26="Occupied",1,0) -> 1 | L26: =IF(AND(K26=1,I26="Yes"),1,0) -> 0 | M26: =IF(K26=1,IF(OR(H26="",H26<Inputs!$B$5),1,(YEAR(H26)-YEAR(Inputs!$B$5))*12+MONTH(H26)-MONTH(Inputs!$B$5)+2),"") -> 12 | N26: =IF(K26=0,IF(I26="Yes",COUNTIFS(K$2:K26,0,I$2:I26,"Yes")-1,COUNTIFS(K$2:K$121,0,I$2:I$121,"Yes")+COUNTIFS(K$2:K26,0,I$2:I26,"<>Yes")-1),"") | O26: =IF(K26=0,INT(N26/Inputs!$B$17)+1,"") | P26: =IF(K26=1,1,O26) -> 1 | Q26: =IF(K26=1,M26,O26+12) -> 12 | R26: =IF(K26=0,IF(AND(I26="Yes",J26<>""),J26,E26*(1+Inputs!$B$7)^(INT((O26-1)/12))),"")
A27: 126 | B27: 960 SF | C27: 960 | D27: Occupied | E27: 1850 | F27: 1895 | G27: 0 | H27: 46234 | K27: =IF(D27="Occupied",1,0) -> 1 | L27: =IF(AND(K27=1,I27="Yes"),1,0) -> 0 | M27: =IF(K27=1,IF(OR(H27="",H27<Inputs!$B$5),1,(YEAR(H27)-YEAR(Inputs!$B$5))*12+MONTH(H27)-MONTH(Inputs!$B$5)+2),"") -> 1 | N27: =IF(K27=0,IF(I27="Yes",COUNTIFS(K$2:K27,0,I$2:I27,"Yes")-1,COUNTIFS(K$2:K$121,0,I$2:I$121,"Yes")+COUNTIFS(K$2:K27,0,I$2:I27,"<>Yes")-1),"") | O27: =IF(K27=0,INT(N27/Inputs!$B$17)+1,"") | P27: =IF(K27=1,1,O27) -> 1 | Q27: =IF(K27=1,M27,O27+12) -> 1 | R27: =IF(K27=0,IF(AND(I27="Yes",J27<>""),J27,E27*(1+Inputs!$B$7)^(INT((O27-1)/12))),"")
A28: 127 | B28: 960 SF | C28: 960 | D28: Occupied | E28: 1850 | F28: 1855 | G28: 12 | H28: 46418 | K28: =IF(D28="Occupied",1,0) -> 1 | L28: =IF(AND(K28=1,I28="Yes"),1,0) -> 0 | M28: =IF(K28=1,IF(OR(H28="",H28<Inputs!$B$5),1,(YEAR(H28)-YEAR(Inputs!$B$5))*12+MONTH(H28)-MONTH(Inputs!$B$5)+2),"") -> 4 | N28: =IF(K28=0,IF(I28="Yes",COUNTIFS(K$2:K28,0,I$2:I28,"Yes")-1,COUNTIFS(K$2:K$121,0,I$2:I$121,"Yes")+COUNTIFS(K$2:K28,0,I$2:I28,"<>Yes")-1),"") | O28: =IF(K28=0,INT(N28/Inputs!$B$17)+1,"") | P28: =IF(K28=1,1,O28) -> 1 | Q28: =IF(K28=1,M28,O28+12) -> 4 | R28: =IF(K28=0,IF(AND(I28="Yes",J28<>""),J28,E28*(1+Inputs!$B$7)^(INT((O28-1)/12))),"")
A29: 128 | B29: 1180 SF | C29: 1180 | D29: Occupied | E29: 2240 | F29: 2130 | G29: 12 | H29: 46630 | K29: =IF(D29="Occupied",1,0) -> 1 | L29: =IF(AND(K29=1,I29="Yes"),1,0) -> 0 | M29: =IF(K29=1,IF(OR(H29="",H29<Inputs!$B$5),1,(YEAR(H29)-YEAR(Inputs!$B$5))*12+MONTH(H29)-MONTH(Inputs!$B$5)+2),"") -> 11 | N29: =IF(K29=0,IF(I29="Yes",COUNTIFS(K$2:K29,0,I$2:I29,"Yes")-1,COUNTIFS(K$2:K$121,0,I$2:I$121,"Yes")+COUNTIFS(K$2:K29,0,I$2:I29,"<>Yes")-1),"") | O29: =IF(K29=0,INT(N29/Inputs!$B$17)+1,"") | P29: =IF(K29=1,1,O29) -> 1 | Q29: =IF(K29=1,M29,O29+12) -> 11 | R29: =IF(K29=0,IF(AND(I29="Yes",J29<>""),J29,E29*(1+Inputs!$B$7)^(INT((O29-1)/12))),"")
A30: 129 | B30: 1180 SF | C30: 1180 | D30: Occupied | E30: 2240 | F30: 2280 | G30: 45 | H30: 46538 | K30: =IF(D30="Occupied",1,0) -> 1 | L30: =IF(AND(K30=1,I30="Yes"),1,0) -> 0 | M30: =IF(K30=1,IF(OR(H30="",H30<Inputs!$B$5),1,(YEAR(H30)-YEAR(Inputs!$B$5))*12+MONTH(H30)-MONTH(Inputs!$B$5)+2),"") -> 8 | N30: =IF(K30=0,IF(I30="Yes",COUNTIFS(K$2:K30,0,I$2:I30,"Yes")-1,COUNTIFS(K$2:K$121,0,I$2:I$121,"Yes")+COUNTIFS(K$2:K30,0,I$2:I30,"<>Yes")-1),"") | O30: =IF(K30=0,INT(N30/Inputs!$B$17)+1,"") | P30: =IF(K30=1,1,O30) -> 1 | Q30: =IF(K30=1,M30,O30+12) -> 8 | R30: =IF(K30=0,IF(AND(I30="Yes",J30<>""),J30,E30*(1+Inputs!$B$7)^(INT((O30-1)/12))),"")
... A39: 208 | B39: 735 SF | C39: 735 | D39: Occupied | E39: 1525 | F39: 1540 | G39: 65 | H39: 46387 | K39: =IF(D39="Occupied",1,0) -> 1 | L39: =IF(AND(K39=1,I39="Yes"),1,0) -> 0 | M39: =IF(K39=1,IF(OR(H39="",H39<Inputs!$B$5),1,(YEAR(H39)-YEAR(Inputs!$B$5))*12+MONTH(H39)-MONTH(Inputs!$B$5)+2),"") -> 3 | N39: =IF(K39=0,IF(I39="Yes",COUNTIFS(K$2:K39,0,I$2:I39,"Yes")-1,COUNTIFS(K$2:K$121,0,I$2:I$121,"Yes")+COUNTIFS(K$2:K39,0,I$2:I39,"<>Yes")-1),"") | O39: =IF(K39=0,INT(N39/Inputs!$B$17)+1,"") | P39: =IF(K39=1,1,O39) -> 1 | Q39: =IF(K39=1,M39,O39+12) -> 3 | R39: =IF(K39=0,IF(AND(I39="Yes",J39<>""),J39,E39*(1+Inputs!$B$7)^(INT((O39-1)/12))),"")
A40: 209 | B40: 735 SF | C40: 735 | D40: Vacant | E40: 1525 | F40: 0 | G40: 0 | K40: =IF(D40="Occupied",1,0) -> 0 | L40: =IF(AND(K40=1,I40="Yes"),1,0) -> 0 | M40: =IF(K40=1,IF(OR(H40="",H40<Inputs!$B$5),1,(YEAR(H40)-YEAR(Inputs!$B$5))*12+MONTH(H40)-MONTH(Inputs!$B$5)+2),"") | N40: =IF(K40=0,IF(I40="Yes",COUNTIFS(K$2:K40,0,I$2:I40,"Yes")-1,COUNTIFS(K$2:K$121,0,I$2:I$121,"Yes")+COUNTIFS(K$2:K40,0,I$2:I40,"<>Yes")-1),"") -> 4 | O40: =IF(K40=0,INT(N40/Inputs!$B$17)+1,"") -> 1 | P40: =IF(K40=1,1,O40) -> 1 | Q40: =IF(K40=1,M40,O40+12) -> 13 | R40: =IF(K40=0,IF(AND(I40="Yes",J40<>""),J40,E40*(1+Inputs!$B$7)^(INT((O40-1)/12))),"") -> 1525
A41: 210 | B41: 735 SF | C41: 735 | D41: Occupied | E41: 1525 | F41: 1455 | G41: 50 | H41: 46538 | K41: =IF(D41="Occupied",1,0) -> 1 | L41: =IF(AND(K41=1,I41="Yes"),1,0) -> 0 | M41: =IF(K41=1,IF(OR(H41="",H41<Inputs!$B$5),1,(YEAR(H41)-YEAR(Inputs!$B$5))*12+MONTH(H41)-MONTH(Inputs!$B$5)+2),"") -> 8 | N41: =IF(K41=0,IF(I41="Yes",COUNTIFS(K$2:K41,0,I$2:I41,"Yes")-1,COUNTIFS(K$2:K$121,0,I$2:I$121,"Yes")+COUNTIFS(K$2:K41,0,I$2:I41,"<>Yes")-1),"") | O41: =IF(K41=0,INT(N41/Inputs!$B$17)+1,"") | P41: =IF(K41=1,1,O41) -> 1 | Q41: =IF(K41=1,M41,O41+12) -> 8 | R41: =IF(K41=0,IF(AND(I41="Yes",J41<>""),J41,E41*(1+Inputs!$B$7)^(INT((O41-1)/12))),"")
A42: 211 | B42: 735 SF | C42: 735 | D42: Occupied | E42: 1525 | F42: 1375 | G42: 45 | H42: 46418 | K42: =IF(D42="Occupied",1,0) -> 1 | L42: =IF(AND(K42=1,I42="Yes"),1,0) -> 0 | M42: =IF(K42=1,IF(OR(H42="",H42<Inputs!$B$5),1,(YEAR(H42)-YEAR(Inputs!$B$5))*12+MONTH(H42)-MONTH(Inputs!$B$5)+2),"") -> 4 | N42: =IF(K42=0,IF(I42="Yes",COUNTIFS(K$2:K42,0,I$2:I42,"Yes")-1,COUNTIFS(K$2:K$121,0,I$2:I$121,"Yes")+COUNTIFS(K$2:K42,0,I$2:I42,"<>Yes")-1),"") | O42: =IF(K42=0,INT(N42/Inputs!$B$17)+1,"") | P42: =IF(K42=1,1,O42) -> 1 | Q42: =IF(K42=1,M42,O42+12) -> 4 | R42: =IF(K42=0,IF(AND(I42="Yes",J42<>""),J42,E42*(1+Inputs!$B$7)^(INT((O42-1)/12))),"")
A43: 212 | B43: 735 SF | C43: 735 | D43: Occupied | E43: 1525 | F43: 1390 | G43: 0 | H43: 46568 | K43: =IF(D43="Occupied",1,0) -> 1 | L43: =IF(AND(K43=1,I43="Yes"),1,0) -> 0 | M43: =IF(K43=1,IF(OR(H43="",H43<Inputs!$B$5),1,(YEAR(H43)-YEAR(Inputs!$B$5))*12+MONTH(H43)-MONTH(Inputs!$B$5)+2),"") -> 9 | N43: =IF(K43=0,IF(I43="Yes",COUNTIFS(K$2:K43,0,I$2:I43,"Yes")-1,COUNTIFS(K$2:K$121,0,I$2:I$121,"Yes")+COUNTIFS(K$2:K43,0,I$2:I43,"<>Yes")-1),"") | O43: =IF(K43=0,INT(N43/Inputs!$B$17)+1,"") | P43: =IF(K43=1,1,O43) -> 1 | Q43: =IF(K43=1,M43,O43+12) -> 9 | R43: =IF(K43=0,IF(AND(I43="Yes",J43<>""),J43,E43*(1+Inputs!$B$7)^(INT((O43-1)/12))),"")
A44: 213 | B44: 560 SF | C44: 560 | D44: Occupied | E44: 1295 | F44: 1195 | G44: 85 | H44: 46660 | K44: =IF(D44="Occupied",1,0) -> 1 | L44: =IF(AND(K44=1,I44="Yes"),1,0) -> 0 | M44: =IF(K44=1,IF(OR(H44="",H44<Inputs!$B$5),1,(YEAR(H44)-YEAR(Inputs!$B$5))*12+MONTH(H44)-MONTH(Inputs!$B$5)+2),"") -> 12 | N44: =IF(K44=0,IF(I44="Yes",COUNTIFS(K$2:K44,0,I$2:I44,"Yes")-1,COUNTIFS(K$2:K$121,0,I$2:I$121,"Yes")+COUNTIFS(K$2:K44,0,I$2:I44,"<>Yes")-1),"") | O44: =IF(K44=0,INT(N44/Inputs!$B$17)+1,"") | P44: =IF(K44=1,1,O44) -> 1 | Q44: =IF(K44=1,M44,O44+12) -> 12 | R44: =IF(K44=0,IF(AND(I44="Yes",J44<>""),J44,E44*(1+Inputs!$B$7)^(INT((O44-1)/12))),"")
A45: 214 | B45: 560 SF | C45: 560 | D45: Occupied | E45: 1295 | F45: 1260 | G45: 12 | H45: 46326 | I45: Yes | K45: =IF(D45="Occupied",1,0) -> 1 | L45: =IF(AND(K45=1,I45="Yes"),1,0) -> 1 | M45: =IF(K45=1,IF(OR(H45="",H45<Inputs!$B$5),1,(YEAR(H45)-YEAR(Inputs!$B$5))*12+MONTH(H45)-MONTH(Inputs!$B$5)+2),"") -> 1 | N45: =IF(K45=0,IF(I45="Yes",COUNTIFS(K$2:K45,0,I$2:I45,"Yes")-1,COUNTIFS(K$2:K$121,0,I$2:I$121,"Yes")+COUNTIFS(K$2:K45,0,I$2:I45,"<>Yes")-1),"") | O45: =IF(K45=0,INT(N45/Inputs!$B$17)+1,"") | P45: =IF(K45=1,1,O45) -> 1 | Q45: =IF(K45=1,M45,O45+12) -> 1 | R45: =IF(K45=0,IF(AND(I45="Yes",J45<>""),J45,E45*(1+Inputs!$B$7)^(INT((O45-1)/12))),"")
A46: 215 | B46: 560 SF | C46: 560 | D46: Occupied | E46: 1295 | F46: 1310 | G46: 75 | H46: 46630 | K46: =IF(D46="Occupied",1,0) -> 1 | L46: =IF(AND(K46=1,I46="Yes"),1,0) -> 0 | M46: =IF(K46=1,IF(OR(H46="",H46<Inputs!$B$5),1,(YEAR(H46)-YEAR(Inputs!$B$5))*12+MONTH(H46)-MONTH(Inputs!$B$5)+2),"") -> 11 | N46: =IF(K46=0,IF(I46="Yes",COUNTIFS(K$2:K46,0,I$2:I46,"Yes")-1,COUNTIFS(K$2:K$121,0,I$2:I$121,"Yes")+COUNTIFS(K$2:K46,0,I$2:I46,"<>Yes")-1),"") | O46: =IF(K46=0,INT(N46/Inputs!$B$17)+1,"") | P46: =IF(K46=1,1,O46) -> 1 | Q46: =IF(K46=1,M46,O46+12) -> 11 | R46: =IF(K46=0,IF(AND(I46="Yes",J46<>""),J46,E46*(1+Inputs!$B$7)^(INT((O46-1)/12))),"")
A47: 216 | B47: 560 SF | C47: 560 | D47: Occupied | E47: 1295 | F47: 1220 | G47: 25 | H47: 46660 | K47: =IF(D47="Occupied",1,0) -> 1 | L47: =IF(AND(K47=1,I47="Yes"),1,0) -> 0 | M47: =IF(K47=1,IF(OR(H47="",H47<Inputs!$B$5),1,(YEAR(H47)-YEAR(Inputs!$B$5))*12+MONTH(H47)-MONTH(Inputs!$B$5)+2),"") -> 12 | N47: =IF(K47=0,IF(I47="Yes",COUNTIFS(K$2:K47,0,I$2:I47,"Yes")-1,COUNTIFS(K$2:K$121,0,I$2:I$121,"Yes")+COUNTIFS(K$2:K47,0,I$2:I47,"<>Yes")-1),"") | O47: =IF(K47=0,INT(N47/Inputs!$B$17)+1,"") | P47: =IF(K47=1,1,O47) -> 1 | Q47: =IF(K47=1,M47,O47+12) -> 12 | R47: =IF(K47=0,IF(AND(I47="Yes",J47<>""),J47,E47*(1+Inputs!$B$7)^(INT((O47-1)/12))),"")
A48: 217 | B48: 560 SF | C48: 560 | D48: Occupied | E48: 1295 | F48: 1330 | G48: 0 | H48: 46507 | K48: =IF(D48="Occupied",1,0) -> 1 | L48: =IF(AND(K48=1,I48="Yes"),1,0) -> 0 | M48: =IF(K48=1,IF(OR(H48="",H48<Inputs!$B$5),1,(YEAR(H48)-YEAR(Inputs!$B$5))*12+MONTH(H48)-MONTH(Inputs!$B$5)+2),"") -> 7 | N48: =IF(K48=0,IF(I48="Yes",COUNTIFS(K$2:K48,0,I$2:I48,"Yes")-1,COUNTIFS(K$2:K$121,0,I$2:I$121,"Yes")+COUNTIFS(K$2:K48,0,I$2:I48,"<>Yes")-1),"") | O48: =IF(K48=0,INT(N48/Inputs!$B$17)+1,"") | P48: =IF(K48=1,1,O48) -> 1 | Q48: =IF(K48=1,M48,O48+12) -> 7 | R48: =IF(K48=0,IF(AND(I48="Yes",J48<>""),J48,E48*(1+Inputs!$B$7)^(INT((O48-1)/12))),"")
A49: 218 | B49: 560 SF | C49: 560 | D49: Occupied | E49: 1295 | F49: 1215 | G49: 0 | H49: 46477 | K49: =IF(D49="Occupied",1,0) -> 1 | L49: =IF(AND(K49=1,I49="Yes"),1,0) -> 0 | M49: =IF(K49=1,IF(OR(H49="",H49<Inputs!$B$5),1,(YEAR(H49)-YEAR(Inputs!$B$5))*12+MONTH(H49)-MONTH(Inputs!$B$5)+2),"") -> 6 | N49: =IF(K49=0,IF(I49="Yes",COUNTIFS(K$2:K49,0,I$2:I49,"Yes")-1,COUNTIFS(K$2:K$121,0,I$2:I$121,"Yes")+COUNTIFS(K$2:K49,0,I$2:I49,"<>Yes")-1),"") | O49: =IF(K49=0,INT(N49/Inputs!$B$17)+1,"") | P49: =IF(K49=1,1,O49) -> 1 | Q49: =IF(K49=1,M49,O49+12) -> 6 | R49: =IF(K49=0,IF(AND(I49="Yes",J49<>""),J49,E49*(1+Inputs!$B$7)^(INT((O49-1)/12))),"")
A50: 219 | B50: 560 SF | C50: 560 | D50: Occupied | E50: 1295 | F50: 1295 | G50: 40 | H50: 46630 | K50: =IF(D50="Occupied",1,0) -> 1 | L50: =IF(AND(K50=1,I50="Yes"),1,0) -> 0 | M50: =IF(K50=1,IF(OR(H50="",H50<Inputs!$B$5),1,(YEAR(H50)-YEAR(Inputs!$B$5))*12+MONTH(H50)-MONTH(Inputs!$B$5)+2),"") -> 11 | N50: =IF(K50=0,IF(I50="Yes",COUNTIFS(K$2:K50,0,I$2:I50,"Yes")-1,COUNTIFS(K$2:K$121,0,I$2:I$121,"Yes")+COUNTIFS(K$2:K50,0,I$2:I50,"<>Yes")-1),"") | O50: =IF(K50=0,INT(N50/Inputs!$B$17)+1,"") | P50: =IF(K50=1,1,O50) -> 1 | Q50: =IF(K50=1,M50,O50+12) -> 11 | R50: =IF(K50=0,IF(AND(I50="Yes",J50<>""),J50,E50*(1+Inputs!$B$7)^(INT((O50-1)/12))),"")
A51: 220 | B51: 560 SF | C51: 560 | D51: Occupied | E51: 1295 | F51: 1280 | G51: 50 | H51: 46356 | K51: =IF(D51="Occupied",1,0) -> 1 | L51: =IF(AND(K51=1,I51="Yes"),1,0) -> 0 | M51: =IF(K51=1,IF(OR(H51="",H51<Inputs!$B$5),1,(YEAR(H51)-YEAR(Inputs!$B$5))*12+MONTH(H51)-MONTH(Inputs!$B$5)+2),"") -> 2 | N51: =IF(K51=0,IF(I51="Yes",COUNTIFS(K$2:K51,0,I$2:I51,"Yes")-1,COUNTIFS(K$2:K$121,0,I$2:I$121,"Yes")+COUNTIFS(K$2:K51,0,I$2:I51,"<>Yes")-1),"") | O51: =IF(K51=0,INT(N51/Inputs!$B$17)+1,"") | P51: =IF(K51=1,1,O51) -> 1 | Q51: =IF(K51=1,M51,O51+12) -> 2 | R51: =IF(K51=0,IF(AND(I51="Yes",J51<>""),J51,E51*(1+Inputs!$B$7)^(INT((O51-1)/12))),"")
A52: 221 | B52: 960 SF | C52: 960 | D52: Occupied | E52: 1850 | F52: 1850 | G52: 47 | H52: 46387 | K52: =IF(D52="Occupied",1,0) -> 1 | L52: =IF(AND(K52=1,I52="Yes"),1,0) -> 0 | M52: =IF(K52=1,IF(OR(H52="",H52<Inputs!$B$5),1,(YEAR(H52)-YEAR(Inputs!$B$5))*12+MONTH(H52)-MONTH(Inputs!$B$5)+2),"") -> 3 | N52: =IF(K52=0,IF(I52="Yes",COUNTIFS(K$2:K52,0,I$2:I52,"Yes")-1,COUNTIFS(K$2:K$121,0,I$2:I$121,"Yes")+COUNTIFS(K$2:K52,0,I$2:I52,"<>Yes")-1),"") | O52: =IF(K52=0,INT(N52/Inputs!$B$17)+1,"") | P52: =IF(K52=1,1,O52) -> 1 | Q52: =IF(K52=1,M52,O52+12) -> 3 | R52: =IF(K52=0,IF(AND(I52="Yes",J52<>""),J52,E52*(1+Inputs!$B$7)^(INT((O52-1)/12))),"")
A53: 222 | B53: 960 SF | C53: 960 | D53: Vacant | E53: 1850 | F53: 0 | G53: 0 | K53: =IF(D53="Occupied",1,0) -> 0 | L53: =IF(AND(K53=1,I53="Yes"),1,0) -> 0 | M53: =IF(K53=1,IF(OR(H53="",H53<Inputs!$B$5),1,(YEAR(H53)-YEAR(Inputs!$B$5))*12+MONTH(H53)-MONTH(Inputs!$B$5)+2),"") | N53: =IF(K53=0,IF(I53="Yes",COUNTIFS(K$2:K53,0,I$2:I53,"Yes")-1,COUNTIFS(K$2:K$121,0,I$2:I$121,"Yes")+COUNTIFS(K$2:K53,0,I$2:I53,"<>Yes")-1),"") -> 5 | O53: =IF(K53=0,INT(N53/Inputs!$B$17)+1,"") -> 1 | P53: =IF(K53=1,1,O53) -> 1 | Q53: =IF(K53=1,M53,O53+12) -> 13 | R53: =IF(K53=0,IF(AND(I53="Yes",J53<>""),J53,E53*(1+Inputs!$B$7)^(INT((O53-1)/12))),"") -> 1850
A54: 223 | B54: 960 SF | C54: 960 | D54: Occupied | E54: 1850 | F54: 1720 | G54: 35 | H54: 46599 | K54: =IF(D54="Occupied",1,0) -> 1 | L54: =IF(AND(K54=1,I54="Yes"),1,0) -> 0 | M54: =IF(K54=1,IF(OR(H54="",H54<Inputs!$B$5),1,(YEAR(H54)-YEAR(Inputs!$B$5))*12+MONTH(H54)-MONTH(Inputs!$B$5)+2),"") -> 10 | N54: =IF(K54=0,IF(I54="Yes",COUNTIFS(K$2:K54,0,I$2:I54,"Yes")-1,COUNTIFS(K$2:K$121,0,I$2:I$121,"Yes")+COUNTIFS(K$2:K54,0,I$2:I54,"<>Yes")-1),"") | O54: =IF(K54=0,INT(N54/Inputs!$B$17)+1,"") | P54: =IF(K54=1,1,O54) -> 1 | Q54: =IF(K54=1,M54,O54+12) -> 10 | R54: =IF(K54=0,IF(AND(I54="Yes",J54<>""),J54,E54*(1+Inputs!$B$7)^(INT((O54-1)/12))),"")
A55: 224 | B55: 960 SF | C55: 960 | D55: Occupied | E55: 1850 | F55: 1735 | G55: 50 | H55: 46507 | K55: =IF(D55="Occupied",1,0) -> 1 | L55: =IF(AND(K55=1,I55="Yes"),1,0) -> 0 | M55: =IF(K55=1,IF(OR(H55="",H55<Inputs!$B$5),1,(YEAR(H55)-YEAR(Inputs!$B$5))*12+MONTH(H55)-MONTH(Inputs!$B$5)+2),"") -> 7 | N55: =IF(K55=0,IF(I55="Yes",COUNTIFS(K$2:K55,0,I$2:I55,"Yes")-1,COUNTIFS(K$2:K$121,0,I$2:I$121,"Yes")+COUNTIFS(K$2:K55,0,I$2:I55,"<>Yes")-1),"") | O55: =IF(K55=0,INT(N55/Inputs!$B$17)+1,"") | P55: =IF(K55=1,1,O55) -> 1 | Q55: =IF(K55=1,M55,O55+12) -> 7 | R55: =IF(K55=0,IF(AND(I55="Yes",J55<>""),J55,E55*(1+Inputs!$B$7)^(INT((O55-1)/12))),"")
A56: 225 | B56: 960 SF | C56: 960 | D56: Occupied | E56: 1850 | F56: 1865 | G56: 25 | H56: 46660 | K56: =IF(D56="Occupied",1,0) -> 1 | L56: =IF(AND(K56=1,I56="Yes"),1,0) -> 0 | M56: =IF(K56=1,IF(OR(H56="",H56<Inputs!$B$5),1,(YEAR(H56)-YEAR(Inputs!$B$5))*12+MONTH(H56)-MONTH(Inputs!$B$5)+2),"") -> 12 | N56: =IF(K56=0,IF(I56="Yes",COUNTIFS(K$2:K56,0,I$2:I56,"Yes")-1,COUNTIFS(K$2:K$121,0,I$2:I$121,"Yes")+COUNTIFS(K$2:K56,0,I$2:I56,"<>Yes")-1),"") | O56: =IF(K56=0,INT(N56/Inputs!$B$17)+1,"") | P56: =IF(K56=1,1,O56) -> 1 | Q56: =IF(K56=1,M56,O56+12) -> 12 | R56: =IF(K56=0,IF(AND(I56="Yes",J56<>""),J56,E56*(1+Inputs!$B$7)^(INT((O56-1)/12))),"")
A57: 226 | B57: 960 SF | C57: 960 | D57: Occupied | E57: 1850 | F57: 1895 | G57: 40 | H57: 46538 | K57: =IF(D57="Occupied",1,0) -> 1 | L57: =IF(AND(K57=1,I57="Yes"),1,0) -> 0 | M57: =IF(K57=1,IF(OR(H57="",H57<Inputs!$B$5),1,(YEAR(H57)-YEAR(Inputs!$B$5))*12+MONTH(H57)-MONTH(Inputs!$B$5)+2),"") -> 8 | N57: =IF(K57=0,IF(I57="Yes",COUNTIFS(K$2:K57,0,I$2:I57,"Yes")-1,COUNTIFS(K$2:K$121,0,I$2:I$121,"Yes")+COUNTIFS(K$2:K57,0,I$2:I57,"<>Yes")-1),"") | O57: =IF(K57=0,INT(N57/Inputs!$B$17)+1,"") | P57: =IF(K57=1,1,O57) -> 1 | Q57: =IF(K57=1,M57,O57+12) -> 8 | R57: =IF(K57=0,IF(AND(I57="Yes",J57<>""),J57,E57*(1+Inputs!$B$7)^(INT((O57-1)/12))),"")
A58: 227 | B58: 960 SF | C58: 960 | D58: Occupied | E58: 1850 | F58: 1895 | G58: 0 | H58: 46446 | K58: =IF(D58="Occupied",1,0) -> 1 | L58: =IF(AND(K58=1,I58="Yes"),1,0) -> 0 | M58: =IF(K58=1,IF(OR(H58="",H58<Inputs!$B$5),1,(YEAR(H58)-YEAR(Inputs!$B$5))*12+MONTH(H58)-MONTH(Inputs!$B$5)+2),"") -> 5 | N58: =IF(K58=0,IF(I58="Yes",COUNTIFS(K$2:K58,0,I$2:I58,"Yes")-1,COUNTIFS(K$2:K$121,0,I$2:I$121,"Yes")+COUNTIFS(K$2:K58,0,I$2:I58,"<>Yes")-1),"") | O58: =IF(K58=0,INT(N58/Inputs!$B$17)+1,"") | P58: =IF(K58=1,1,O58) -> 1 | Q58: =IF(K58=1,M58,O58+12) -> 5 | R58: =IF(K58=0,IF(AND(I58="Yes",J58<>""),J58,E58*(1+Inputs!$B$7)^(INT((O58-1)/12))),"")
A59: 228 | B59: 1180 SF | C59: 1180 | D59: Occupied | E59: 2240 | F59: 2235 | G59: 70 | H59: 46418 | K59: =IF(D59="Occupied",1,0) -> 1 | L59: =IF(AND(K59=1,I59="Yes"),1,0) -> 0 | M59: =IF(K59=1,IF(OR(H59="",H59<Inputs!$B$5),1,(YEAR(H59)-YEAR(Inputs!$B$5))*12+MONTH(H59)-MONTH(Inputs!$B$5)+2),"") -> 4 | N59: =IF(K59=0,IF(I59="Yes",COUNTIFS(K$2:K59,0,I$2:I59,"Yes")-1,COUNTIFS(K$2:K$121,0,I$2:I$121,"Yes")+COUNTIFS(K$2:K59,0,I$2:I59,"<>Yes")-1),"") | O59: =IF(K59=0,INT(N59/Inputs!$B$17)+1,"") | P59: =IF(K59=1,1,O59) -> 1 | Q59: =IF(K59=1,M59,O59+12) -> 4 | R59: =IF(K59=0,IF(AND(I59="Yes",J59<>""),J59,E59*(1+Inputs!$B$7)^(INT((O59-1)/12))),"")
A60: 229 | B60: 1180 SF | C60: 1180 | D60: Occupied | E60: 2240 | F60: 2255 | G60: 50 | H60: 46387 | K60: =IF(D60="Occupied",1,0) -> 1 | L60: =IF(AND(K60=1,I60="Yes"),1,0) -> 0 | M60: =IF(K60=1,IF(OR(H60="",H60<Inputs!$B$5),1,(YEAR(H60)-YEAR(Inputs!$B$5))*12+MONTH(H60)-MONTH(Inputs!$B$5)+2),"") -> 3 | N60: =IF(K60=0,IF(I60="Yes",COUNTIFS(K$2:K60,0,I$2:I60,"Yes")-1,COUNTIFS(K$2:K$121,0,I$2:I$121,"Yes")+COUNTIFS(K$2:K60,0,I$2:I60,"<>Yes")-1),"") | O60: =IF(K60=0,INT(N60/Inputs!$B$17)+1,"") | P60: =IF(K60=1,1,O60) -> 1 | Q60: =IF(K60=1,M60,O60+12) -> 3 | R60: =IF(K60=0,IF(AND(I60="Yes",J60<>""),J60,E60*(1+Inputs!$B$7)^(INT((O60-1)/12))),"")
A61: 230 | B61: 1180 SF | C61: 1180 | D61: Vacant | E61: 2240 | F61: 0 | G61: 0 | K61: =IF(D61="Occupied",1,0) -> 0 | L61: =IF(AND(K61=1,I61="Yes"),1,0) -> 0 | M61: =IF(K61=1,IF(OR(H61="",H61<Inputs!$B$5),1,(YEAR(H61)-YEAR(Inputs!$B$5))*12+MONTH(H61)-MONTH(Inputs!$B$5)+2),"") | N61: =IF(K61=0,IF(I61="Yes",COUNTIFS(K$2:K61,0,I$2:I61,"Yes")-1,COUNTIFS(K$2:K$121,0,I$2:I$121,"Yes")+COUNTIFS(K$2:K61,0,I$2:I61,"<>Yes")-1),"") -> 6 | O61: =IF(K61=0,INT(N61/Inputs!$B$17)+1,"") -> 1 | P61: =IF(K61=1,1,O61) -> 1 | Q61: =IF(K61=1,M61,O61+12) -> 13 | R61: =IF(K61=0,IF(AND(I61="Yes",J61<>""),J61,E61*(1+Inputs!$B$7)^(INT((O61-1)/12))),"") -> 2240
A62: 301 | B62: 735 SF | C62: 735 | D62: Occupied | E62: 1525 | F62: 1555 | G62: 25 | H62: 46326 | K62: =IF(D62="Occupied",1,0) -> 1 | L62: =IF(AND(K62=1,I62="Yes"),1,0) -> 0 | M62: =IF(K62=1,IF(OR(H62="",H62<Inputs!$B$5),1,(YEAR(H62)-YEAR(Inputs!$B$5))*12+MONTH(H62)-MONTH(Inputs!$B$5)+2),"") -> 1 | N62: =IF(K62=0,IF(I62="Yes",COUNTIFS(K$2:K62,0,I$2:I62,"Yes")-1,COUNTIFS(K$2:K$121,0,I$2:I$121,"Yes")+COUNTIFS(K$2:K62,0,I$2:I62,"<>Yes")-1),"") | O62: =IF(K62=0,INT(N62/Inputs!$B$17)+1,"") | P62: =IF(K62=1,1,O62) -> 1 | Q62: =IF(K62=1,M62,O62+12) -> 1 | R62: =IF(K62=0,IF(AND(I62="Yes",J62<>""),J62,E62*(1+Inputs!$B$7)^(INT((O62-1)/12))),"")
A63: 302 | B63: 735 SF | C63: 735 | D63: Occupied | E63: 1525 | F63: 1455 | G63: 0 | H63: 46477 | K63: =IF(D63="Occupied",1,0) -> 1 | L63: =IF(AND(K63=1,I63="Yes"),1,0) -> 0 | M63: =IF(K63=1,IF(OR(H63="",H63<Inputs!$B$5),1,(YEAR(H63)-YEAR(Inputs!$B$5))*12+MONTH(H63)-MONTH(Inputs!$B$5)+2),"") -> 6 | N63: =IF(K63=0,IF(I63="Yes",COUNTIFS(K$2:K63,0,I$2:I63,"Yes")-1,COUNTIFS(K$2:K$121,0,I$2:I$121,"Yes")+COUNTIFS(K$2:K63,0,I$2:I63,"<>Yes")-1),"") | O63: =IF(K63=0,INT(N63/Inputs!$B$17)+1,"") | P63: =IF(K63=1,1,O63) -> 1 | Q63: =IF(K63=1,M63,O63+12) -> 6 | R63: =IF(K63=0,IF(AND(I63="Yes",J63<>""),J63,E63*(1+Inputs!$B$7)^(INT((O63-1)/12))),"")
A64: 303 | B64: 735 SF | C64: 735 | D64: Occupied | E64: 1525 | F64: 1450 | G64: 12 | H64: 46630 | K64: =IF(D64="Occupied",1,0) -> 1 | L64: =IF(AND(K64=1,I64="Yes"),1,0) -> 0 | M64: =IF(K64=1,IF(OR(H64="",H64<Inputs!$B$5),1,(YEAR(H64)-YEAR(Inputs!$B$5))*12+MONTH(H64)-MONTH(Inputs!$B$5)+2),"") -> 11 | N64: =IF(K64=0,IF(I64="Yes",COUNTIFS(K$2:K64,0,I$2:I64,"Yes")-1,COUNTIFS(K$2:K$121,0,I$2:I$121,"Yes")+COUNTIFS(K$2:K64,0,I$2:I64,"<>Yes")-1),"") | O64: =IF(K64=0,INT(N64/Inputs!$B$17)+1,"") | P64: =IF(K64=1,1,O64) -> 1 | Q64: =IF(K64=1,M64,O64+12) -> 11 | R64: =IF(K64=0,IF(AND(I64="Yes",J64<>""),J64,E64*(1+Inputs!$B$7)^(INT((O64-1)/12))),"")
A65: 304 | B65: 735 SF | C65: 735 | D65: Occupied | E65: 1525 | F65: 1535 | G65: 0 | H65: 46446 | K65: =IF(D65="Occupied",1,0) -> 1 | L65: =IF(AND(K65=1,I65="Yes"),1,0) -> 0 | M65: =IF(K65=1,IF(OR(H65="",H65<Inputs!$B$5),1,(YEAR(H65)-YEAR(Inputs!$B$5))*12+MONTH(H65)-MONTH(Inputs!$B$5)+2),"") -> 5 | N65: =IF(K65=0,IF(I65="Yes",COUNTIFS(K$2:K65,0,I$2:I65,"Yes")-1,COUNTIFS(K$2:K$121,0,I$2:I$121,"Yes")+COUNTIFS(K$2:K65,0,I$2:I65,"<>Yes")-1),"") | O65: =IF(K65=0,INT(N65/Inputs!$B$17)+1,"") | P65: =IF(K65=1,1,O65) -> 1 | Q65: =IF(K65=1,M65,O65+12) -> 5 | R65: =IF(K65=0,IF(AND(I65="Yes",J65<>""),J65,E65*(1+Inputs!$B$7)^(INT((O65-1)/12))),"")
A66: 305 | B66: 735 SF | C66: 735 | D66: Vacant | E66: 1525 | F66: 0 | G66: 0 | I66: Yes | K66: =IF(D66="Occupied",1,0) -> 0 | L66: =IF(AND(K66=1,I66="Yes"),1,0) -> 0 | M66: =IF(K66=1,IF(OR(H66="",H66<Inputs!$B$5),1,(YEAR(H66)-YEAR(Inputs!$B$5))*12+MONTH(H66)-MONTH(Inputs!$B$5)+2),"") | N66: =IF(K66=0,IF(I66="Yes",COUNTIFS(K$2:K66,0,I$2:I66,"Yes")-1,COUNTIFS(K$2:K$121,0,I$2:I$121,"Yes")+COUNTIFS(K$2:K66,0,I$2:I66,"<>Yes")-1),"") -> 1 | O66: =IF(K66=0,INT(N66/Inputs!$B$17)+1,"") -> 1 | P66: =IF(K66=1,1,O66) -> 1 | Q66: =IF(K66=1,M66,O66+12) -> 13 | R66: =IF(K66=0,IF(AND(I66="Yes",J66<>""),J66,E66*(1+Inputs!$B$7)^(INT((O66-1)/12))),"") -> 1525
A67: 306 | B67: 735 SF | C67: 735 | D67: Occupied | E67: 1525 | F67: 1425 | G67: 0 | H67: 46507 | K67: =IF(D67="Occupied",1,0) -> 1 | L67: =IF(AND(K67=1,I67="Yes"),1,0) -> 0 | M67: =IF(K67=1,IF(OR(H67="",H67<Inputs!$B$5),1,(YEAR(H67)-YEAR(Inputs!$B$5))*12+MONTH(H67)-MONTH(Inputs!$B$5)+2),"") -> 7 | N67: =IF(K67=0,IF(I67="Yes",COUNTIFS(K$2:K67,0,I$2:I67,"Yes")-1,COUNTIFS(K$2:K$121,0,I$2:I$121,"Yes")+COUNTIFS(K$2:K67,0,I$2:I67,"<>Yes")-1),"") | O67: =IF(K67=0,INT(N67/Inputs!$B$17)+1,"") | P67: =IF(K67=1,1,O67) -> 1 | Q67: =IF(K67=1,M67,O67+12) -> 7 | R67: =IF(K67=0,IF(AND(I67="Yes",J67<>""),J67,E67*(1+Inputs!$B$7)^(INT((O67-1)/12))),"")
A68: 307 | B68: 735 SF | C68: 735 | D68: Occupied | E68: 1525 | F68: 1460 | G68: 85 | H68: 46326 | K68: =IF(D68="Occupied",1,0) -> 1 | L68: =IF(AND(K68=1,I68="Yes"),1,0) -> 0 | M68: =IF(K68=1,IF(OR(H68="",H68<Inputs!$B$5),1,(YEAR(H68)-YEAR(Inputs!$B$5))*12+MONTH(H68)-MONTH(Inputs!$B$5)+2),"") -> 1 | N68: =IF(K68=0,IF(I68="Yes",COUNTIFS(K$2:K68,0,I$2:I68,"Yes")-1,COUNTIFS(K$2:K$121,0,I$2:I$121,"Yes")+COUNTIFS(K$2:K68,0,I$2:I68,"<>Yes")-1),"") | O68: =IF(K68=0,INT(N68/Inputs!$B$17)+1,"") | P68: =IF(K68=1,1,O68) -> 1 | Q68: =IF(K68=1,M68,O68+12) -> 1 | R68: =IF(K68=0,IF(AND(I68="Yes",J68<>""),J68,E68*(1+Inputs!$B$7)^(INT((O68-1)/12))),"")
A69: 308 | B69: 735 SF | C69: 735 | D69: Occupied | E69: 1525 | F69: 1425 | G69: 0 | H69: 46326 | K69: =IF(D69="Occupied",1,0) -> 1 | L69: =IF(AND(K69=1,I69="Yes"),1,0) -> 0 | M69: =IF(K69=1,IF(OR(H69="",H69<Inputs!$B$5),1,(YEAR(H69)-YEAR(Inputs!$B$5))*12+MONTH(H69)-MONTH(Inputs!$B$5)+2),"") -> 1 | N69: =IF(K69=0,IF(I69="Yes",COUNTIFS(K$2:K69,0,I$2:I69,"Yes")-1,COUNTIFS(K$2:K$121,0,I$2:I$121,"Yes")+COUNTIFS(K$2:K69,0,I$2:I69,"<>Yes")-1),"") | O69: =IF(K69=0,INT(N69/Inputs!$B$17)+1,"") | P69: =IF(K69=1,1,O69) -> 1 | Q69: =IF(K69=1,M69,O69+12) -> 1 | R69: =IF(K69=0,IF(AND(I69="Yes",J69<>""),J69,E69*(1+Inputs!$B$7)^(INT((O69-1)/12))),"")
A70: 309 | B70: 735 SF | C70: 735 | D70: Occupied | E70: 1525 | F70: 1450 | G70: 130 | H70: 46356 | K70: =IF(D70="Occupied",1,0) -> 1 | L70: =IF(AND(K70=1,I70="Yes"),1,0) -> 0 | M70: =IF(K70=1,IF(OR(H70="",H70<Inputs!$B$5),1,(YEAR(H70)-YEAR(Inputs!$B$5))*12+MONTH(H70)-MONTH(Inputs!$B$5)+2),"") -> 2 | N70: =IF(K70=0,IF(I70="Yes",COUNTIFS(K$2:K70,0,I$2:I70,"Yes")-1,COUNTIFS(K$2:K$121,0,I$2:I$121,"Yes")+COUNTIFS(K$2:K70,0,I$2:I70,"<>Yes")-1),"") | O70: =IF(K70=0,INT(N70/Inputs!$B$17)+1,"") | P70: =IF(K70=1,1,O70) -> 1 | Q70: =IF(K70=1,M70,O70+12) -> 2 | R70: =IF(K70=0,IF(AND(I70="Yes",J70<>""),J70,E70*(1+Inputs!$B$7)^(INT((O70-1)/12))),"")
A71: 310 | B71: 735 SF | C71: 735 | D71: Occupied | E71: 1525 | F71: 1580 | G71: 35 | H71: 46599 | K71: =IF(D71="Occupied",1,0) -> 1 | L71: =IF(AND(K71=1,I71="Yes"),1,0) -> 0 | M71: =IF(K71=1,IF(OR(H71="",H71<Inputs!$B$5),1,(YEAR(H71)-YEAR(Inputs!$B$5))*12+MONTH(H71)-MONTH(Inputs!$B$5)+2),"") -> 10 | N71: =IF(K71=0,IF(I71="Yes",COUNTIFS(K$2:K71,0,I$2:I71,"Yes")-1,COUNTIFS(K$2:K$121,0,I$2:I$121,"Yes")+COUNTIFS(K$2:K71,0,I$2:I71,"<>Yes")-1),"") | O71: =IF(K71=0,INT(N71/Inputs!$B$17)+1,"") | P71: =IF(K71=1,1,O71) -> 1 | Q71: =IF(K71=1,M71,O71+12) -> 10 | R71: =IF(K71=0,IF(AND(I71="Yes",J71<>""),J71,E71*(1+Inputs!$B$7)^(INT((O71-1)/12))),"")
A72: 311 | B72: 735 SF | C72: 735 | D72: Occupied | E72: 1525 | F72: 1190 | G72: 12 | H72: 46507 | K72: =IF(D72="Occupied",1,0) -> 1 | L72: =IF(AND(K72=1,I72="Yes"),1,0) -> 0 | M72: =IF(K72=1,IF(OR(H72="",H72<Inputs!$B$5),1,(YEAR(H72)-YEAR(Inputs!$B$5))*12+MONTH(H72)-MONTH(Inputs!$B$5)+2),"") -> 7 | N72: =IF(K72=0,IF(I72="Yes",COUNTIFS(K$2:K72,0,I$2:I72,"Yes")-1,COUNTIFS(K$2:K$121,0,I$2:I$121,"Yes")+COUNTIFS(K$2:K72,0,I$2:I72,"<>Yes")-1),"") | O72: =IF(K72=0,INT(N72/Inputs!$B$17)+1,"") | P72: =IF(K72=1,1,O72) -> 1 | Q72: =IF(K72=1,M72,O72+12) -> 7 | R72: =IF(K72=0,IF(AND(I72="Yes",J72<>""),J72,E72*(1+Inputs!$B$7)^(INT((O72-1)/12))),"")
A73: 312 | B73: 735 SF | C73: 735 | D73: Occupied | E73: 1525 | F73: 1485 | G73: 0 | H73: 46418 | K73: =IF(D73="Occupied",1,0) -> 1 | L73: =IF(AND(K73=1,I73="Yes"),1,0) -> 0 | M73: =IF(K73=1,IF(OR(H73="",H73<Inputs!$B$5),1,(YEAR(H73)-YEAR(Inputs!$B$5))*12+MONTH(H73)-MONTH(Inputs!$B$5)+2),"") -> 4 | N73: =IF(K73=0,IF(I73="Yes",COUNTIFS(K$2:K73,0,I$2:I73,"Yes")-1,COUNTIFS(K$2:K$121,0,I$2:I$121,"Yes")+COUNTIFS(K$2:K73,0,I$2:I73,"<>Yes")-1),"") | O73: =IF(K73=0,INT(N73/Inputs!$B$17)+1,"") | P73: =IF(K73=1,1,O73) -> 1 | Q73: =IF(K73=1,M73,O73+12) -> 4 | R73: =IF(K73=0,IF(AND(I73="Yes",J73<>""),J73,E73*(1+Inputs!$B$7)^(INT((O73-1)/12))),"")
A74: 313 | B74: 560 SF | C74: 560 | D74: Occupied | E74: 1295 | F74: 1285 | G74: 0 | H74: 46418 | K74: =IF(D74="Occupied",1,0) -> 1 | L74: =IF(AND(K74=1,I74="Yes"),1,0) -> 0 | M74: =IF(K74=1,IF(OR(H74="",H74<Inputs!$B$5),1,(YEAR(H74)-YEAR(Inputs!$B$5))*12+MONTH(H74)-MONTH(Inputs!$B$5)+2),"") -> 4 | N74: =IF(K74=0,IF(I74="Yes",COUNTIFS(K$2:K74,0,I$2:I74,"Yes")-1,COUNTIFS(K$2:K$121,0,I$2:I$121,"Yes")+COUNTIFS(K$2:K74,0,I$2:I74,"<>Yes")-1),"") | O74: =IF(K74=0,INT(N74/Inputs!$B$17)+1,"") | P74: =IF(K74=1,1,O74) -> 1 | Q74: =IF(K74=1,M74,O74+12) -> 4 | R74: =IF(K74=0,IF(AND(I74="Yes",J74<>""),J74,E74*(1+Inputs!$B$7)^(INT((O74-1)/12))),"")
A75: 314 | B75: 560 SF | C75: 560 | D75: Occupied | E75: 1295 | F75: 1195 | G75: 12 | H75: 46326 | K75: =IF(D75="Occupied",1,0) -> 1 | L75: =IF(AND(K75=1,I75="Yes"),1,0) -> 0 | M75: =IF(K75=1,IF(OR(H75="",H75<Inputs!$B$5),1,(YEAR(H75)-YEAR(Inputs!$B$5))*12+MONTH(H75)-MONTH(Inputs!$B$5)+2),"") -> 1 | N75: =IF(K75=0,IF(I75="Yes",COUNTIFS(K$2:K75,0,I$2:I75,"Yes")-1,COUNTIFS(K$2:K$121,0,I$2:I$121,"Yes")+COUNTIFS(K$2:K75,0,I$2:I75,"<>Yes")-1),"") | O75: =IF(K75=0,INT(N75/Inputs!$B$17)+1,"") | P75: =IF(K75=1,1,O75) -> 1 | Q75: =IF(K75=1,M75,O75+12) -> 1 | R75: =IF(K75=0,IF(AND(I75="Yes",J75<>""),J75,E75*(1+Inputs!$B$7)^(INT((O75-1)/12))),"")
A76: 315 | B76: 560 SF | C76: 560 | D76: Occupied | E76: 1295 | F76: 1275 | G76: 40 | H76: 46446 | K76: =IF(D76="Occupied",1,0) -> 1 | L76: =IF(AND(K76=1,I76="Yes"),1,0) -> 0 | M76: =IF(K76=1,IF(OR(H76="",H76<Inputs!$B$5),1,(YEAR(H76)-YEAR(Inputs!$B$5))*12+MONTH(H76)-MONTH(Inputs!$B$5)+2),"") -> 5 | N76: =IF(K76=0,IF(I76="Yes",COUNTIFS(K$2:K76,0,I$2:I76,"Yes")-1,COUNTIFS(K$2:K$121,0,I$2:I$121,"Yes")+COUNTIFS(K$2:K76,0,I$2:I76,"<>Yes")-1),"") | O76: =IF(K76=0,INT(N76/Inputs!$B$17)+1,"") | P76: =IF(K76=1,1,O76) -> 1 | Q76: =IF(K76=1,M76,O76+12) -> 5 | R76: =IF(K76=0,IF(AND(I76="Yes",J76<>""),J76,E76*(1+Inputs!$B$7)^(INT((O76-1)/12))),"")
A77: 316 | B77: 560 SF | C77: 560 | D77: Occupied | E77: 1295 | F77: 1290 | G77: 0 | H77: 46326 | K77: =IF(D77="Occupied",1,0) -> 1 | L77: =IF(AND(K77=1,I77="Yes"),1,0) -> 0 | M77: =IF(K77=1,IF(OR(H77="",H77<Inputs!$B$5),1,(YEAR(H77)-YEAR(Inputs!$B$5))*12+MONTH(H77)-MONTH(Inputs!$B$5)+2),"") -> 1 | N77: =IF(K77=0,IF(I77="Yes",COUNTIFS(K$2:K77,0,I$2:I77,"Yes")-1,COUNTIFS(K$2:K$121,0,I$2:I$121,"Yes")+COUNTIFS(K$2:K77,0,I$2:I77,"<>Yes")-1),"") | O77: =IF(K77=0,INT(N77/Inputs!$B$17)+1,"") | P77: =IF(K77=1,1,O77) -> 1 | Q77: =IF(K77=1,M77,O77+12) -> 1 | R77: =IF(K77=0,IF(AND(I77="Yes",J77<>""),J77,E77*(1+Inputs!$B$7)^(INT((O77-1)/12))),"")
A78: 317 | B78: 560 SF | C78: 560 | D78: Occupied | E78: 1295 | F78: 1200 | G78: 40 | H78: 46568 | K78: =IF(D78="Occupied",1,0) -> 1 | L78: =IF(AND(K78=1,I78="Yes"),1,0) -> 0 | M78: =IF(K78=1,IF(OR(H78="",H78<Inputs!$B$5),1,(YEAR(H78)-YEAR(Inputs!$B$5))*12+MONTH(H78)-MONTH(Inputs!$B$5)+2),"") -> 9 | N78: =IF(K78=0,IF(I78="Yes",COUNTIFS(K$2:K78,0,I$2:I78,"Yes")-1,COUNTIFS(K$2:K$121,0,I$2:I$121,"Yes")+COUNTIFS(K$2:K78,0,I$2:I78,"<>Yes")-1),"") | O78: =IF(K78=0,INT(N78/Inputs!$B$17)+1,"") | P78: =IF(K78=1,1,O78) -> 1 | Q78: =IF(K78=1,M78,O78+12) -> 9 | R78: =IF(K78=0,IF(AND(I78="Yes",J78<>""),J78,E78*(1+Inputs!$B$7)^(INT((O78-1)/12))),"")
A79: 318 | B79: 560 SF | C79: 560 | D79: Vacant | E79: 1295 | F79: 0 | G79: 0 | K79: =IF(D79="Occupied",1,0) -> 0 | L79: =IF(AND(K79=1,I79="Yes"),1,0) -> 0 | M79: =IF(K79=1,IF(OR(H79="",H79<Inputs!$B$5),1,(YEAR(H79)-YEAR(Inputs!$B$5))*12+MONTH(H79)-MONTH(Inputs!$B$5)+2),"") | N79: =IF(K79=0,IF(I79="Yes",COUNTIFS(K$2:K79,0,I$2:I79,"Yes")-1,COUNTIFS(K$2:K$121,0,I$2:I$121,"Yes")+COUNTIFS(K$2:K79,0,I$2:I79,"<>Yes")-1),"") -> 7 | O79: =IF(K79=0,INT(N79/Inputs!$B$17)+1,"") -> 1 | P79: =IF(K79=1,1,O79) -> 1 | Q79: =IF(K79=1,M79,O79+12) -> 13 | R79: =IF(K79=0,IF(AND(I79="Yes",J79<>""),J79,E79*(1+Inputs!$B$7)^(INT((O79-1)/12))),"") -> 1295
A80: 319 | B80: 560 SF | C80: 560 | D80: Occupied | E80: 1295 | F80: 1270 | G80: 37 | H80: 46418 | K80: =IF(D80="Occupied",1,0) -> 1 | L80: =IF(AND(K80=1,I80="Yes"),1,0) -> 0 | M80: =IF(K80=1,IF(OR(H80="",H80<Inputs!$B$5),1,(YEAR(H80)-YEAR(Inputs!$B$5))*12+MONTH(H80)-MONTH(Inputs!$B$5)+2),"") -> 4 | N80: =IF(K80=0,IF(I80="Yes",COUNTIFS(K$2:K80,0,I$2:I80,"Yes")-1,COUNTIFS(K$2:K$121,0,I$2:I$121,"Yes")+COUNTIFS(K$2:K80,0,I$2:I80,"<>Yes")-1),"") | O80: =IF(K80=0,INT(N80/Inputs!$B$17)+1,"") | P80: =IF(K80=1,1,O80) -> 1 | Q80: =IF(K80=1,M80,O80+12) -> 4 | R80: =IF(K80=0,IF(AND(I80="Yes",J80<>""),J80,E80*(1+Inputs!$B$7)^(INT((O80-1)/12))),"")
A81: 320 | B81: 960 SF | C81: 960 | D81: Occupied | E81: 1850 | F81: 1475 | G81: 47 | H81: 46387 | K81: =IF(D81="Occupied",1,0) -> 1 | L81: =IF(AND(K81=1,I81="Yes"),1,0) -> 0 | M81: =IF(K81=1,IF(OR(H81="",H81<Inputs!$B$5),1,(YEAR(H81)-YEAR(Inputs!$B$5))*12+MONTH(H81)-MONTH(Inputs!$B$5)+2),"") -> 3 | N81: =IF(K81=0,IF(I81="Yes",COUNTIFS(K$2:K81,0,I$2:I81,"Yes")-1,COUNTIFS(K$2:K$121,0,I$2:I$121,"Yes")+COUNTIFS(K$2:K81,0,I$2:I81,"<>Yes")-1),"") | O81: =IF(K81=0,INT(N81/Inputs!$B$17)+1,"") | P81: =IF(K81=1,1,O81) -> 1 | Q81: =IF(K81=1,M81,O81+12) -> 3 | R81: =IF(K81=0,IF(AND(I81="Yes",J81<>""),J81,E81*(1+Inputs!$B$7)^(INT((O81-1)/12))),"")
A82: 321 | B82: 960 SF | C82: 960 | D82: Vacant | E82: 1850 | F82: 0 | G82: 0 | K82: =IF(D82="Occupied",1,0) -> 0 | L82: =IF(AND(K82=1,I82="Yes"),1,0) -> 0 | M82: =IF(K82=1,IF(OR(H82="",H82<Inputs!$B$5),1,(YEAR(H82)-YEAR(Inputs!$B$5))*12+MONTH(H82)-MONTH(Inputs!$B$5)+2),"") | N82: =IF(K82=0,IF(I82="Yes",COUNTIFS(K$2:K82,0,I$2:I82,"Yes")-1,COUNTIFS(K$2:K$121,0,I$2:I$121,"Yes")+COUNTIFS(K$2:K82,0,I$2:I82,"<>Yes")-1),"") -> 8 | O82: =IF(K82=0,INT(N82/Inputs!$B$17)+1,"") -> 2 | P82: =IF(K82=1,1,O82) -> 2 | Q82: =IF(K82=1,M82,O82+12) -> 14 | R82: =IF(K82=0,IF(AND(I82="Yes",J82<>""),J82,E82*(1+Inputs!$B$7)^(INT((O82-1)/12))),"") -> 1850
A83: 322 | B83: 960 SF | C83: 960 | D83: Occupied | E83: 1850 | F83: 1680 | G83: 45 | H83: 46387 | K83: =IF(D83="Occupied",1,0) -> 1 | L83: =IF(AND(K83=1,I83="Yes"),1,0) -> 0 | M83: =IF(K83=1,IF(OR(H83="",H83<Inputs!$B$5),1,(YEAR(H83)-YEAR(Inputs!$B$5))*12+MONTH(H83)-MONTH(Inputs!$B$5)+2),"") -> 3 | N83: =IF(K83=0,IF(I83="Yes",COUNTIFS(K$2:K83,0,I$2:I83,"Yes")-1,COUNTIFS(K$2:K$121,0,I$2:I$121,"Yes")+COUNTIFS(K$2:K83,0,I$2:I83,"<>Yes")-1),"") | O83: =IF(K83=0,INT(N83/Inputs!$B$17)+1,"") | P83: =IF(K83=1,1,O83) -> 1 | Q83: =IF(K83=1,M83,O83+12) -> 3 | R83: =IF(K83=0,IF(AND(I83="Yes",J83<>""),J83,E83*(1+Inputs!$B$7)^(INT((O83-1)/12))),"")
A84: 323 | B84: 960 SF | C84: 960 | D84: Occupied | E84: 1850 | F84: 1890 | G84: 0 | K84: =IF(D84="Occupied",1,0) -> 1 | L84: =IF(AND(K84=1,I84="Yes"),1,0) -> 0 | M84: =IF(K84=1,IF(OR(H84="",H84<Inputs!$B$5),1,(YEAR(H84)-YEAR(Inputs!$B$5))*12+MONTH(H84)-MONTH(Inputs!$B$5)+2),"") -> 1 | N84: =IF(K84=0,IF(I84="Yes",COUNTIFS(K$2:K84,0,I$2:I84,"Yes")-1,COUNTIFS(K$2:K$121,0,I$2:I$121,"Yes")+COUNTIFS(K$2:K84,0,I$2:I84,"<>Yes")-1),"") | O84: =IF(K84=0,INT(N84/Inputs!$B$17)+1,"") | P84: =IF(K84=1,1,O84) -> 1 | Q84: =IF(K84=1,M84,O84+12) -> 1 | R84: =IF(K84=0,IF(AND(I84="Yes",J84<>""),J84,E84*(1+Inputs!$B$7)^(INT((O84-1)/12))),"")
A85: 324 | B85: 960 SF | C85: 960 | D85: Occupied | E85: 1850 | F85: 1670 | G85: 25 | H85: 46660 | K85: =IF(D85="Occupied",1,0) -> 1 | L85: =IF(AND(K85=1,I85="Yes"),1,0) -> 0 | M85: =IF(K85=1,IF(OR(H85="",H85<Inputs!$B$5),1,(YEAR(H85)-YEAR(Inputs!$B$5))*12+MONTH(H85)-MONTH(Inputs!$B$5)+2),"") -> 12 | N85: =IF(K85=0,IF(I85="Yes",COUNTIFS(K$2:K85,0,I$2:I85,"Yes")-1,COUNTIFS(K$2:K$121,0,I$2:I$121,"Yes")+COUNTIFS(K$2:K85,0,I$2:I85,"<>Yes")-1),"") | O85: =IF(K85=0,INT(N85/Inputs!$B$17)+1,"") | P85: =IF(K85=1,1,O85) -> 1 | Q85: =IF(K85=1,M85,O85+12) -> 12 | R85: =IF(K85=0,IF(AND(I85="Yes",J85<>""),J85,E85*(1+Inputs!$B$7)^(INT((O85-1)/12))),"")
A86: 325 | B86: 960 SF | C86: 960 | D86: Occupied | E86: 1850 | F86: 1910 | G86: 35 | H86: 46538 | K86: =IF(D86="Occupied",1,0) -> 1 | L86: =IF(AND(K86=1,I86="Yes"),1,0) -> 0 | M86: =IF(K86=1,IF(OR(H86="",H86<Inputs!$B$5),1,(YEAR(H86)-YEAR(Inputs!$B$5))*12+MONTH(H86)-MONTH(Inputs!$B$5)+2),"") -> 8 | N86: =IF(K86=0,IF(I86="Yes",COUNTIFS(K$2:K86,0,I$2:I86,"Yes")-1,COUNTIFS(K$2:K$121,0,I$2:I$121,"Yes")+COUNTIFS(K$2:K86,0,I$2:I86,"<>Yes")-1),"") | O86: =IF(K86=0,INT(N86/Inputs!$B$17)+1,"") | P86: =IF(K86=1,1,O86) -> 1 | Q86: =IF(K86=1,M86,O86+12) -> 8 | R86: =IF(K86=0,IF(AND(I86="Yes",J86<>""),J86,E86*(1+Inputs!$B$7)^(INT((O86-1)/12))),"")
A87: 326 | B87: 960 SF | C87: 960 | D87: Occupied | E87: 1850 | F87: 1910 | G87: 50 | H87: 46507 | K87: =IF(D87="Occupied",1,0) -> 1 | L87: =IF(AND(K87=1,I87="Yes"),1,0) -> 0 | M87: =IF(K87=1,IF(OR(H87="",H87<Inputs!$B$5),1,(YEAR(H87)-YEAR(Inputs!$B$5))*12+MONTH(H87)-MONTH(Inputs!$B$5)+2),"") -> 7 | N87: =IF(K87=0,IF(I87="Yes",COUNTIFS(K$2:K87,0,I$2:I87,"Yes")-1,COUNTIFS(K$2:K$121,0,I$2:I$121,"Yes")+COUNTIFS(K$2:K87,0,I$2:I87,"<>Yes")-1),"") | O87: =IF(K87=0,INT(N87/Inputs!$B$17)+1,"") | P87: =IF(K87=1,1,O87) -> 1 | Q87: =IF(K87=1,M87,O87+12) -> 7 | R87: =IF(K87=0,IF(AND(I87="Yes",J87<>""),J87,E87*(1+Inputs!$B$7)^(INT((O87-1)/12))),"")
A88: 327 | B88: 960 SF | C88: 960 | D88: Occupied | E88: 1850 | F88: 1775 | G88: 0 | H88: 46356 | K88: =IF(D88="Occupied",1,0) -> 1 | L88: =IF(AND(K88=1,I88="Yes"),1,0) -> 0 | M88: =IF(K88=1,IF(OR(H88="",H88<Inputs!$B$5),1,(YEAR(H88)-YEAR(Inputs!$B$5))*12+MONTH(H88)-MONTH(Inputs!$B$5)+2),"") -> 2 | N88: =IF(K88=0,IF(I88="Yes",COUNTIFS(K$2:K88,0,I$2:I88,"Yes")-1,COUNTIFS(K$2:K$121,0,I$2:I$121,"Yes")+COUNTIFS(K$2:K88,0,I$2:I88,"<>Yes")-1),"") | O88: =IF(K88=0,INT(N88/Inputs!$B$17)+1,"") | P88: =IF(K88=1,1,O88) -> 1 | Q88: =IF(K88=1,M88,O88+12) -> 2 | R88: =IF(K88=0,IF(AND(I88="Yes",J88<>""),J88,E88*(1+Inputs!$B$7)^(INT((O88-1)/12))),"")
A89: 328 | B89: 1180 SF | C89: 1180 | D89: Occupied | E89: 2240 | F89: 2125 | G89: 70 | H89: 46538 | K89: =IF(D89="Occupied",1,0) -> 1 | L89: =IF(AND(K89=1,I89="Yes"),1,0) -> 0 | M89: =IF(K89=1,IF(OR(H89="",H89<Inputs!$B$5),1,(YEAR(H89)-YEAR(Inputs!$B$5))*12+MONTH(H89)-MONTH(Inputs!$B$5)+2),"") -> 8 | N89: =IF(K89=0,IF(I89="Yes",COUNTIFS(K$2:K89,0,I$2:I89,"Yes")-1,COUNTIFS(K$2:K$121,0,I$2:I$121,"Yes")+COUNTIFS(K$2:K89,0,I$2:I89,"<>Yes")-1),"") | O89: =IF(K89=0,INT(N89/Inputs!$B$17)+1,"") | P89: =IF(K89=1,1,O89) -> 1 | Q89: =IF(K89=1,M89,O89+12) -> 8 | R89: =IF(K89=0,IF(AND(I89="Yes",J89<>""),J89,E89*(1+Inputs!$B$7)^(INT((O89-1)/12))),"")
A90: 329 | B90: 1180 SF | C90: 1180 | D90: Occupied | E90: 2240 | F90: 2275 | G90: 50 | H90: 46507 | K90: =IF(D90="Occupied",1,0) -> 1 | L90: =IF(AND(K90=1,I90="Yes"),1,0) -> 0 | M90: =IF(K90=1,IF(OR(H90="",H90<Inputs!$B$5),1,(YEAR(H90)-YEAR(Inputs!$B$5))*12+MONTH(H90)-MONTH(Inputs!$B$5)+2),"") -> 7 | N90: =IF(K90=0,IF(I90="Yes",COUNTIFS(K$2:K90,0,I$2:I90,"Yes")-1,COUNTIFS(K$2:K$121,0,I$2:I$121,"Yes")+COUNTIFS(K$2:K90,0,I$2:I90,"<>Yes")-1),"") | O90: =IF(K90=0,INT(N90/Inputs!$B$17)+1,"") | P90: =IF(K90=1,1,O90) -> 1 | Q90: =IF(K90=1,M90,O90+12) -> 7 | R90: =IF(K90=0,IF(AND(I90="Yes",J90<>""),J90,E90*(1+Inputs!$B$7)^(INT((O90-1)/12))),"")
A91: 330 | B91: 1180 SF | C91: 1180 | D91: Occupied | E91: 2240 | F91: 2325 | G91: 0 | H91: 46387 | K91: =IF(D91="Occupied",1,0) -> 1 | L91: =IF(AND(K91=1,I91="Yes"),1,0) -> 0 | M91: =IF(K91=1,IF(OR(H91="",H91<Inputs!$B$5),1,(YEAR(H91)-YEAR(Inputs!$B$5))*12+MONTH(H91)-MONTH(Inputs!$B$5)+2),"") -> 3 | N91: =IF(K91=0,IF(I91="Yes",COUNTIFS(K$2:K91,0,I$2:I91,"Yes")-1,COUNTIFS(K$2:K$121,0,I$2:I$121,"Yes")+COUNTIFS(K$2:K91,0,I$2:I91,"<>Yes")-1),"") | O91: =IF(K91=0,INT(N91/Inputs!$B$17)+1,"") | P91: =IF(K91=1,1,O91) -> 1 | Q91: =IF(K91=1,M91,O91+12) -> 3 | R91: =IF(K91=0,IF(AND(I91="Yes",J91<>""),J91,E91*(1+Inputs!$B$7)^(INT((O91-1)/12))),"")
A92: 401 | B92: 735 SF | C92: 735 | D92: Occupied | E92: 1525 | F92: 1565 | G92: 47 | H92: 46568 | K92: =IF(D92="Occupied",1,0) -> 1 | L92: =IF(AND(K92=1,I92="Yes"),1,0) -> 0 | M92: =IF(K92=1,IF(OR(H92="",H92<Inputs!$B$5),1,(YEAR(H92)-YEAR(Inputs!$B$5))*12+MONTH(H92)-MONTH(Inputs!$B$5)+2),"") -> 9 | N92: =IF(K92=0,IF(I92="Yes",COUNTIFS(K$2:K92,0,I$2:I92,"Yes")-1,COUNTIFS(K$2:K$121,0,I$2:I$121,"Yes")+COUNTIFS(K$2:K92,0,I$2:I92,"<>Yes")-1),"") | O92: =IF(K92=0,INT(N92/Inputs!$B$17)+1,"") | P92: =IF(K92=1,1,O92) -> 1 | Q92: =IF(K92=1,M92,O92+12) -> 9 | R92: =IF(K92=0,IF(AND(I92="Yes",J92<>""),J92,E92*(1+Inputs!$B$7)^(INT((O92-1)/12))),"")
A93: 402 | B93: 735 SF | C93: 735 | D93: Occupied | E93: 1525 | F93: 1520 | G93: 35 | H93: 46507 | K93: =IF(D93="Occupied",1,0) -> 1 | L93: =IF(AND(K93=1,I93="Yes"),1,0) -> 0 | M93: =IF(K93=1,IF(OR(H93="",H93<Inputs!$B$5),1,(YEAR(H93)-YEAR(Inputs!$B$5))*12+MONTH(H93)-MONTH(Inputs!$B$5)+2),"") -> 7 | N93: =IF(K93=0,IF(I93="Yes",COUNTIFS(K$2:K93,0,I$2:I93,"Yes")-1,COUNTIFS(K$2:K$121,0,I$2:I$121,"Yes")+COUNTIFS(K$2:K93,0,I$2:I93,"<>Yes")-1),"") | O93: =IF(K93=0,INT(N93/Inputs!$B$17)+1,"") | P93: =IF(K93=1,1,O93) -> 1 | Q93: =IF(K93=1,M93,O93+12) -> 7 | R93: =IF(K93=0,IF(AND(I93="Yes",J93<>""),J93,E93*(1+Inputs!$B$7)^(INT((O93-1)/12))),"")
A94: 403 | B94: 735 SF | C94: 735 | D94: Occupied | E94: 1525 | F94: 1380 | G94: 45 | H94: 46477 | K94: =IF(D94="Occupied",1,0) -> 1 | L94: =IF(AND(K94=1,I94="Yes"),1,0) -> 0 | M94: =IF(K94=1,IF(OR(H94="",H94<Inputs!$B$5),1,(YEAR(H94)-YEAR(Inputs!$B$5))*12+MONTH(H94)-MONTH(Inputs!$B$5)+2),"") -> 6 | N94: =IF(K94=0,IF(I94="Yes",COUNTIFS(K$2:K94,0,I$2:I94,"Yes")-1,COUNTIFS(K$2:K$121,0,I$2:I$121,"Yes")+COUNTIFS(K$2:K94,0,I$2:I94,"<>Yes")-1),"") | O94: =IF(K94=0,INT(N94/Inputs!$B$17)+1,"") | P94: =IF(K94=1,1,O94) -> 1 | Q94: =IF(K94=1,M94,O94+12) -> 6 | R94: =IF(K94=0,IF(AND(I94="Yes",J94<>""),J94,E94*(1+Inputs!$B$7)^(INT((O94-1)/12))),"")
A95: 404 | B95: 735 SF | C95: 735 | D95: Occupied | E95: 1525 | F95: 1400 | G95: 0 | H95: 46356 | K95: =IF(D95="Occupied",1,0) -> 1 | L95: =IF(AND(K95=1,I95="Yes"),1,0) -> 0 | M95: =IF(K95=1,IF(OR(H95="",H95<Inputs!$B$5),1,(YEAR(H95)-YEAR(Inputs!$B$5))*12+MONTH(H95)-MONTH(Inputs!$B$5)+2),"") -> 2 | N95: =IF(K95=0,IF(I95="Yes",COUNTIFS(K$2:K95,0,I$2:I95,"Yes")-1,COUNTIFS(K$2:K$121,0,I$2:I$121,"Yes")+COUNTIFS(K$2:K95,0,I$2:I95,"<>Yes")-1),"") | O95: =IF(K95=0,INT(N95/Inputs!$B$17)+1,"") | P95: =IF(K95=1,1,O95) -> 1 | Q95: =IF(K95=1,M95,O95+12) -> 2 | R95: =IF(K95=0,IF(AND(I95="Yes",J95<>""),J95,E95*(1+Inputs!$B$7)^(INT((O95-1)/12))),"")
A96: 405 | B96: 735 SF | C96: 735 | D96: Occupied | E96: 1525 | F96: 1535 | G96: 70 | H96: 46660 | K96: =IF(D96="Occupied",1,0) -> 1 | L96: =IF(AND(K96=1,I96="Yes"),1,0) -> 0 | M96: =IF(K96=1,IF(OR(H96="",H96<Inputs!$B$5),1,(YEAR(H96)-YEAR(Inputs!$B$5))*12+MONTH(H96)-MONTH(Inputs!$B$5)+2),"") -> 12 | N96: =IF(K96=0,IF(I96="Yes",COUNTIFS(K$2:K96,0,I$2:I96,"Yes")-1,COUNTIFS(K$2:K$121,0,I$2:I$121,"Yes")+COUNTIFS(K$2:K96,0,I$2:I96,"<>Yes")-1),"") | O96: =IF(K96=0,INT(N96/Inputs!$B$17)+1,"") | P96: =IF(K96=1,1,O96) -> 1 | Q96: =IF(K96=1,M96,O96+12) -> 12 | R96: =IF(K96=0,IF(AND(I96="Yes",J96<>""),J96,E96*(1+Inputs!$B$7)^(INT((O96-1)/12))),"")
... A102: 411 | B102: 735 SF | C102: 735 | D102: Occupied | E102: 1525 | F102: 1510 | G102: 0 | H102: 46387 | K102: =IF(D102="Occupied",1,0) -> 1 | L102: =IF(AND(K102=1,I102="Yes"),1,0) -> 0 | M102: =IF(K102=1,IF(OR(H102="",H102<Inputs!$B$5),1,(YEAR(H102)-YEAR(Inputs!$B$5))*12+MONTH(H102)-MONTH(Inputs!$B$5)+2),"") -> 3 | N102: =IF(K102=0,IF(I102="Yes",COUNTIFS(K$2:K102,0,I$2:I102,"Yes")-1,COUNTIFS(K$2:K$121,0,I$2:I$121,"Yes")+COUNTIFS(K$2:K102,0,I$2:I102,"<>Yes")-1),"") | O102: =IF(K102=0,INT(N102/Inputs!$B$17)+1,"") | P102: =IF(K102=1,1,O102) -> 1 | Q102: =IF(K102=1,M102,O102+12) -> 3 | R102: =IF(K102=0,IF(AND(I102="Yes",J102<>""),J102,E102*(1+Inputs!$B$7)^(INT((O102-1)/12))),"")
A103: 412 | B103: 735 SF | C103: 735 | D103: Vacant | E103: 1525 | F103: 0 | G103: 0 | K103: =IF(D103="Occupied",1,0) -> 0 | L103: =IF(AND(K103=1,I103="Yes"),1,0) -> 0 | M103: =IF(K103=1,IF(OR(H103="",H103<Inputs!$B$5),1,(YEAR(H103)-YEAR(Inputs!$B$5))*12+MONTH(H103)-MONTH(Inputs!$B$5)+2),"") | N103: =IF(K103=0,IF(I103="Yes",COUNTIFS(K$2:K103,0,I$2:I103,"Yes")-1,COUNTIFS(K$2:K$121,0,I$2:I$121,"Yes")+COUNTIFS(K$2:K103,0,I$2:I103,"<>Yes")-1),"") -> 9 | O103: =IF(K103=0,INT(N103/Inputs!$B$17)+1,"") -> 2 | P103: =IF(K103=1,1,O103) -> 2 | Q103: =IF(K103=1,M103,O103+12) -> 14 | R103: =IF(K103=0,IF(AND(I103="Yes",J103<>""),J103,E103*(1+Inputs!$B$7)^(INT((O103-1)/12))),"") -> 1525
A104: 413 | B104: 560 SF | C104: 560 | D104: Occupied | E104: 1295 | F104: 1170 | G104: 50 | H104: 46387 | K104: =IF(D104="Occupied",1,0) -> 1 | L104: =IF(AND(K104=1,I104="Yes"),1,0) -> 0 | M104: =IF(K104=1,IF(OR(H104="",H104<Inputs!$B$5),1,(YEAR(H104)-YEAR(Inputs!$B$5))*12+MONTH(H104)-MONTH(Inputs!$B$5)+2),"") -> 3 | N104: =IF(K104=0,IF(I104="Yes",COUNTIFS(K$2:K104,0,I$2:I104,"Yes")-1,COUNTIFS(K$2:K$121,0,I$2:I$121,"Yes")+COUNTIFS(K$2:K104,0,I$2:I104,"<>Yes")-1),"") | O104: =IF(K104=0,INT(N104/Inputs!$B$17)+1,"") | P104: =IF(K104=1,1,O104) -> 1 | Q104: =IF(K104=1,M104,O104+12) -> 3 | R104: =IF(K104=0,IF(AND(I104="Yes",J104<>""),J104,E104*(1+Inputs!$B$7)^(INT((O104-1)/12))),"")
A105: 414 | B105: 560 SF | C105: 560 | D105: Occupied | E105: 1295 | F105: 1260 | G105: 12 | H105: 46446 | K105: =IF(D105="Occupied",1,0) -> 1 | L105: =IF(AND(K105=1,I105="Yes"),1,0) -> 0 | M105: =IF(K105=1,IF(OR(H105="",H105<Inputs!$B$5),1,(YEAR(H105)-YEAR(Inputs!$B$5))*12+MONTH(H105)-MONTH(Inputs!$B$5)+2),"") -> 5 | N105: =IF(K105=0,IF(I105="Yes",COUNTIFS(K$2:K105,0,I$2:I105,"Yes")-1,COUNTIFS(K$2:K$121,0,I$2:I$121,"Yes")+COUNTIFS(K$2:K105,0,I$2:I105,"<>Yes")-1),"") | O105: =IF(K105=0,INT(N105/Inputs!$B$17)+1,"") | P105: =IF(K105=1,1,O105) -> 1 | Q105: =IF(K105=1,M105,O105+12) -> 5 | R105: =IF(K105=0,IF(AND(I105="Yes",J105<>""),J105,E105*(1+Inputs!$B$7)^(INT((O105-1)/12))),"")
A106: 415 | B106: 560 SF | C106: 560 | D106: Occupied | E106: 1295 | F106: 1240 | G106: 0 | H106: 46326 | K106: =IF(D106="Occupied",1,0) -> 1 | L106: =IF(AND(K106=1,I106="Yes"),1,0) -> 0 | M106: =IF(K106=1,IF(OR(H106="",H106<Inputs!$B$5),1,(YEAR(H106)-YEAR(Inputs!$B$5))*12+MONTH(H106)-MONTH(Inputs!$B$5)+2),"") -> 1 | N106: =IF(K106=0,IF(I106="Yes",COUNTIFS(K$2:K106,0,I$2:I106,"Yes")-1,COUNTIFS(K$2:K$121,0,I$2:I$121,"Yes")+COUNTIFS(K$2:K106,0,I$2:I106,"<>Yes")-1),"") | O106: =IF(K106=0,INT(N106/Inputs!$B$17)+1,"") | P106: =IF(K106=1,1,O106) -> 1 | Q106: =IF(K106=1,M106,O106+12) -> 1 | R106: =IF(K106=0,IF(AND(I106="Yes",J106<>""),J106,E106*(1+Inputs!$B$7)^(INT((O106-1)/12))),"")
A107: 416 | B107: 560 SF | C107: 560 | D107: Occupied | E107: 1295 | F107: 1270 | G107: 0 | H107: 46356 | K107: =IF(D107="Occupied",1,0) -> 1 | L107: =IF(AND(K107=1,I107="Yes"),1,0) -> 0 | M107: =IF(K107=1,IF(OR(H107="",H107<Inputs!$B$5),1,(YEAR(H107)-YEAR(Inputs!$B$5))*12+MONTH(H107)-MONTH(Inputs!$B$5)+2),"") -> 2 | N107: =IF(K107=0,IF(I107="Yes",COUNTIFS(K$2:K107,0,I$2:I107,"Yes")-1,COUNTIFS(K$2:K$121,0,I$2:I$121,"Yes")+COUNTIFS(K$2:K107,0,I$2:I107,"<>Yes")-1),"") | O107: =IF(K107=0,INT(N107/Inputs!$B$17)+1,"") | P107: =IF(K107=1,1,O107) -> 1 | Q107: =IF(K107=1,M107,O107+12) -> 2 | R107: =IF(K107=0,IF(AND(I107="Yes",J107<>""),J107,E107*(1+Inputs!$B$7)^(INT((O107-1)/12))),"")
A108: 417 | B108: 560 SF | C108: 560 | D108: Occupied | E108: 1295 | F108: 1325 | G108: 35 | H108: 46660 | K108: =IF(D108="Occupied",1,0) -> 1 | L108: =IF(AND(K108=1,I108="Yes"),1,0) -> 0 | M108: =IF(K108=1,IF(OR(H108="",H108<Inputs!$B$5),1,(YEAR(H108)-YEAR(Inputs!$B$5))*12+MONTH(H108)-MONTH(Inputs!$B$5)+2),"") -> 12 | N108: =IF(K108=0,IF(I108="Yes",COUNTIFS(K$2:K108,0,I$2:I108,"Yes")-1,COUNTIFS(K$2:K$121,0,I$2:I$121,"Yes")+COUNTIFS(K$2:K108,0,I$2:I108,"<>Yes")-1),"") | O108: =IF(K108=0,INT(N108/Inputs!$B$17)+1,"") | P108: =IF(K108=1,1,O108) -> 1 | Q108: =IF(K108=1,M108,O108+12) -> 12 | R108: =IF(K108=0,IF(AND(I108="Yes",J108<>""),J108,E108*(1+Inputs!$B$7)^(INT((O108-1)/12))),"")
A109: 418 | B109: 560 SF | C109: 560 | D109: Occupied | E109: 1295 | F109: 1265 | G109: 25 | H109: 46418 | K109: =IF(D109="Occupied",1,0) -> 1 | L109: =IF(AND(K109=1,I109="Yes"),1,0) -> 0 | M109: =IF(K109=1,IF(OR(H109="",H109<Inputs!$B$5),1,(YEAR(H109)-YEAR(Inputs!$B$5))*12+MONTH(H109)-MONTH(Inputs!$B$5)+2),"") -> 4 | N109: =IF(K109=0,IF(I109="Yes",COUNTIFS(K$2:K109,0,I$2:I109,"Yes")-1,COUNTIFS(K$2:K$121,0,I$2:I$121,"Yes")+COUNTIFS(K$2:K109,0,I$2:I109,"<>Yes")-1),"") | O109: =IF(K109=0,INT(N109/Inputs!$B$17)+1,"") | P109: =IF(K109=1,1,O109) -> 1 | Q109: =IF(K109=1,M109,O109+12) -> 4 | R109: =IF(K109=0,IF(AND(I109="Yes",J109<>""),J109,E109*(1+Inputs!$B$7)^(INT((O109-1)/12))),"")
A110: 419 | B110: 560 SF | C110: 560 | D110: Occupied | E110: 1295 | F110: 1275 | G110: 45 | H110: 46568 | K110: =IF(D110="Occupied",1,0) -> 1 | L110: =IF(AND(K110=1,I110="Yes"),1,0) -> 0 | M110: =IF(K110=1,IF(OR(H110="",H110<Inputs!$B$5),1,(YEAR(H110)-YEAR(Inputs!$B$5))*12+MONTH(H110)-MONTH(Inputs!$B$5)+2),"") -> 9 | N110: =IF(K110=0,IF(I110="Yes",COUNTIFS(K$2:K110,0,I$2:I110,"Yes")-1,COUNTIFS(K$2:K$121,0,I$2:I$121,"Yes")+COUNTIFS(K$2:K110,0,I$2:I110,"<>Yes")-1),"") | O110: =IF(K110=0,INT(N110/Inputs!$B$17)+1,"") | P110: =IF(K110=1,1,O110) -> 1 | Q110: =IF(K110=1,M110,O110+12) -> 9 | R110: =IF(K110=0,IF(AND(I110="Yes",J110<>""),J110,E110*(1+Inputs!$B$7)^(INT((O110-1)/12))),"")
A111: 420 | B111: 960 SF | C111: 960 | D111: Occupied | E111: 1850 | F111: 1850 | G111: 0 | H111: 46630 | K111: =IF(D111="Occupied",1,0) -> 1 | L111: =IF(AND(K111=1,I111="Yes"),1,0) -> 0 | M111: =IF(K111=1,IF(OR(H111="",H111<Inputs!$B$5),1,(YEAR(H111)-YEAR(Inputs!$B$5))*12+MONTH(H111)-MONTH(Inputs!$B$5)+2),"") -> 11 | N111: =IF(K111=0,IF(I111="Yes",COUNTIFS(K$2:K111,0,I$2:I111,"Yes")-1,COUNTIFS(K$2:K$121,0,I$2:I$121,"Yes")+COUNTIFS(K$2:K111,0,I$2:I111,"<>Yes")-1),"") | O111: =IF(K111=0,INT(N111/Inputs!$B$17)+1,"") | P111: =IF(K111=1,1,O111) -> 1 | Q111: =IF(K111=1,M111,O111+12) -> 11 | R111: =IF(K111=0,IF(AND(I111="Yes",J111<>""),J111,E111*(1+Inputs!$B$7)^(INT((O111-1)/12))),"")
A112: 421 | B112: 960 SF | C112: 960 | D112: Occupied | E112: 1850 | F112: 1800 | G112: 45 | H112: 46356 | K112: =IF(D112="Occupied",1,0) -> 1 | L112: =IF(AND(K112=1,I112="Yes"),1,0) -> 0 | M112: =IF(K112=1,IF(OR(H112="",H112<Inputs!$B$5),1,(YEAR(H112)-YEAR(Inputs!$B$5))*12+MONTH(H112)-MONTH(Inputs!$B$5)+2),"") -> 2 | N112: =IF(K112=0,IF(I112="Yes",COUNTIFS(K$2:K112,0,I$2:I112,"Yes")-1,COUNTIFS(K$2:K$121,0,I$2:I$121,"Yes")+COUNTIFS(K$2:K112,0,I$2:I112,"<>Yes")-1),"") | O112: =IF(K112=0,INT(N112/Inputs!$B$17)+1,"") | P112: =IF(K112=1,1,O112) -> 1 | Q112: =IF(K112=1,M112,O112+12) -> 2 | R112: =IF(K112=0,IF(AND(I112="Yes",J112<>""),J112,E112*(1+Inputs!$B$7)^(INT((O112-1)/12))),"")
A113: 422 | B113: 960 SF | C113: 960 | D113: Occupied | E113: 1850 | F113: 1850 | G113: 47 | H113: 46660 | K113: =IF(D113="Occupied",1,0) -> 1 | L113: =IF(AND(K113=1,I113="Yes"),1,0) -> 0 | M113: =IF(K113=1,IF(OR(H113="",H113<Inputs!$B$5),1,(YEAR(H113)-YEAR(Inputs!$B$5))*12+MONTH(H113)-MONTH(Inputs!$B$5)+2),"") -> 12 | N113: =IF(K113=0,IF(I113="Yes",COUNTIFS(K$2:K113,0,I$2:I113,"Yes")-1,COUNTIFS(K$2:K$121,0,I$2:I$121,"Yes")+COUNTIFS(K$2:K113,0,I$2:I113,"<>Yes")-1),"") | O113: =IF(K113=0,INT(N113/Inputs!$B$17)+1,"") | P113: =IF(K113=1,1,O113) -> 1 | Q113: =IF(K113=1,M113,O113+12) -> 12 | R113: =IF(K113=0,IF(AND(I113="Yes",J113<>""),J113,E113*(1+Inputs!$B$7)^(INT((O113-1)/12))),"")
...

Sheet Mkt
A1: Month | B1: Market rent $/mo | C1: 1 | D1: 2 | E1: 3 | F1: 4 | G1: 5 | H1: 6 | I1: 7 | J1: 8 | K1: 9 | L1: 10 | M1: 11 | N1: 12 | O1: 13 | P1: 14 | Q1: 15 | R1: 16 | S1: 17 | T1: 18 | U1: 19 | V1: 20 | W1: 21 | X1: 22 | Y1: 23 | Z1: 24 | AA1: 25 | AB1: 26 | AC1: 27 | AD1: 28 | AE1: 29 | AF1: 30 | AG1: 31 | AH1: 32 | AI1: 33 | AJ1: 34 | AK1: 35 | AL1: 36 | AM1: 37 | AN1: 38 | AO1: 39 | AP1: 40 | AQ1: 41 | AR1: 42 | AS1: 43 | AT1: 44 | AU1: 45 | AV1: 46 | AW1: 47 | AX1: 48 | AY1: 49 | AZ1: 50 | BA1: 51 | BB1: 52 | BC1: 53 | BD1: 54 | BE1: 55 | BF1: 56 | BG1: 57 | BH1: 58 | BI1: 59 | BJ1: 60 | BK1: 61 | BL1: 62 | BM1: 63 | BN1: 64 | BO1: 65 | BP1: 66 | BQ1: 67 | BR1: 68 | BS1: 69 | BT1: 70 | BU1: 71 | BV1: 72 | BW1: 73 | BX1: 74 | BY1: 75 | BZ1: 76 | CA1: 77 | CB1: 78 | CC1: 79 | CD1: 80 | CE1: 81 | CF1: 82 | CG1: 83 | CH1: 84 | CI1: 85 | CJ1: 86 | CK1: 87 | CL1: 88 | CM1: 89 | CN1: 90 | CO1: 91 | CP1: 92 | CQ1: 93 | CR1: 94 | CS1: 95 | CT1: 96 | CU1: 97 | CV1: 98 | CW1: 99 | CX1: 100 | CY1: 101 | CZ1: 102 | DA1: 103 | DB1: 104 | DC1: 105 | DD1: 106 | DE1: 107 | DF1: 108 | DG1: 109 | DH1: 110 | DI1: 111 | DJ1: 112 | DK1: 113 | DL1: 114 | DM1: 115 | DN1: 116 | DO1: 117 | DP1: 118 | DQ1: 119 | DR1: 120 | DS1: 121 | DT1: 122 | DU1: 123 | DV1: 124 | DW1: 125 | DX1: 126 | DY1: 127 | DZ1: 128 | EA1: 129 | EB1: 130 | EC1: 131 | ED1: 132
A2: Year | C2: =ROUNDUP(C1/12,0) -> 1 | D2: =ROUNDUP(D1/12,0) -> 1 | E2: =ROUNDUP(E1/12,0) -> 1 | F2: =ROUNDUP(F1/12,0) -> 1 | G2: =ROUNDUP(G1/12,0) -> 1 | H2: =ROUNDUP(H1/12,0) -> 1 | I2: =ROUNDUP(I1/12,0) -> 1 | J2: =ROUNDUP(J1/12,0) -> 1 | ... ED2: =ROUNDUP(ED1/12,0) -> 11
A3: =Units!A2 -> 101 | C3: =Units!$E2*(1+Inputs!$B$7)^(C$2-1) -> 1525 | D3: =Units!$E2*(1+Inputs!$B$7)^(D$2-1) -> 1525 | E3: =Units!$E2*(1+Inputs!$B$7)^(E$2-1) -> 1525 | F3: =Units!$E2*(1+Inputs!$B$7)^(F$2-1) -> 1525 | G3: =Units!$E2*(1+Inputs!$B$7)^(G$2-1) -> 1525 | H3: =Units!$E2*(1+Inputs!$B$7)^(H$2-1) -> 1525 | I3: =Units!$E2*(1+Inputs!$B$7)^(I$2-1) -> 1525 | J3: =Units!$E2*(1+Inputs!$B$7)^(J$2-1) -> 1525 | ... ED3: =Units!$E2*(1+Inputs!$B$7)^(ED$2-1) -> 2049.4725
A4: =Units!A3 -> 102 | C4: =Units!$E3*(1+Inputs!$B$7)^(C$2-1) -> 1525 | D4: =Units!$E3*(1+Inputs!$B$7)^(D$2-1) -> 1525 | E4: =Units!$E3*(1+Inputs!$B$7)^(E$2-1) -> 1525 | F4: =Units!$E3*(1+Inputs!$B$7)^(F$2-1) -> 1525 | G4: =Units!$E3*(1+Inputs!$B$7)^(G$2-1) -> 1525 | H4: =Units!$E3*(1+Inputs!$B$7)^(H$2-1) -> 1525 | I4: =Units!$E3*(1+Inputs!$B$7)^(I$2-1) -> 1525 | J4: =Units!$E3*(1+Inputs!$B$7)^(J$2-1) -> 1525 | ... ED4: =Units!$E3*(1+Inputs!$B$7)^(ED$2-1) -> 2049.4725
A5: =Units!A4 -> 103 | C5: =Units!$E4*(1+Inputs!$B$7)^(C$2-1) -> 1525 | D5: =Units!$E4*(1+Inputs!$B$7)^(D$2-1) -> 1525 | E5: =Units!$E4*(1+Inputs!$B$7)^(E$2-1) -> 1525 | F5: =Units!$E4*(1+Inputs!$B$7)^(F$2-1) -> 1525 | G5: =Units!$E4*(1+Inputs!$B$7)^(G$2-1) -> 1525 | H5: =Units!$E4*(1+Inputs!$B$7)^(H$2-1) -> 1525 | I5: =Units!$E4*(1+Inputs!$B$7)^(I$2-1) -> 1525 | J5: =Units!$E4*(1+Inputs!$B$7)^(J$2-1) -> 1525 | ... ED5: =Units!$E4*(1+Inputs!$B$7)^(ED$2-1) -> 2049.4725
A6: =Units!A5 -> 104 | C6: =Units!$E5*(1+Inputs!$B$7)^(C$2-1) -> 1525 | D6: =Units!$E5*(1+Inputs!$B$7)^(D$2-1) -> 1525 | E6: =Units!$E5*(1+Inputs!$B$7)^(E$2-1) -> 1525 | F6: =Units!$E5*(1+Inputs!$B$7)^(F$2-1) -> 1525 | G6: =Units!$E5*(1+Inputs!$B$7)^(G$2-1) -> 1525 | H6: =Units!$E5*(1+Inputs!$B$7)^(H$2-1) -> 1525 | I6: =Units!$E5*(1+Inputs!$B$7)^(I$2-1) -> 1525 | J6: =Units!$E5*(1+Inputs!$B$7)^(J$2-1) -> 1525 | ... ED6: =Units!$E5*(1+Inputs!$B$7)^(ED$2-1) -> 2049.4725
A7: =Units!A6 -> 105 | C7: =Units!$E6*(1+Inputs!$B$7)^(C$2-1) -> 1525 | D7: =Units!$E6*(1+Inputs!$B$7)^(D$2-1) -> 1525 | E7: =Units!$E6*(1+Inputs!$B$7)^(E$2-1) -> 1525 | F7: =Units!$E6*(1+Inputs!$B$7)^(F$2-1) -> 1525 | G7: =Units!$E6*(1+Inputs!$B$7)^(G$2-1) -> 1525 | H7: =Units!$E6*(1+Inputs!$B$7)^(H$2-1) -> 1525 | I7: =Units!$E6*(1+Inputs!$B$7)^(I$2-1) -> 1525 | J7: =Units!$E6*(1+Inputs!$B$7)^(J$2-1) -> 1525 | ... ED7: =Units!$E6*(1+Inputs!$B$7)^(ED$2-1) -> 2049.4725
A8: =Units!A7 -> 106 | C8: =Units!$E7*(1+Inputs!$B$7)^(C$2-1) -> 1525 | D8: =Units!$E7*(1+Inputs!$B$7)^(D$2-1) -> 1525 | E8: =Units!$E7*(1+Inputs!$B$7)^(E$2-1) -> 1525 | F8: =Units!$E7*(1+Inputs!$B$7)^(F$2-1) -> 1525 | G8: =Units!$E7*(1+Inputs!$B$7)^(G$2-1) -> 1525 | H8: =Units!$E7*(1+Inputs!$B$7)^(H$2-1) -> 1525 | I8: =Units!$E7*(1+Inputs!$B$7)^(I$2-1) -> 1525 | J8: =Units!$E7*(1+Inputs!$B$7)^(J$2-1) -> 1525 | ... ED8: =Units!$E7*(1+Inputs!$B$7)^(ED$2-1) -> 2049.4725
A9: =Units!A8 -> 107 | C9: =Units!$E8*(1+Inputs!$B$7)^(C$2-1) -> 1525 | D9: =Units!$E8*(1+Inputs!$B$7)^(D$2-1) -> 1525 | E9: =Units!$E8*(1+Inputs!$B$7)^(E$2-1) -> 1525 | F9: =Units!$E8*(1+Inputs!$B$7)^(F$2-1) -> 1525 | G9: =Units!$E8*(1+Inputs!$B$7)^(G$2-1) -> 1525 | H9: =Units!$E8*(1+Inputs!$B$7)^(H$2-1) -> 1525 | I9: =Units!$E8*(1+Inputs!$B$7)^(I$2-1) -> 1525 | J9: =Units!$E8*(1+Inputs!$B$7)^(J$2-1) -> 1525 | ... ED9: =Units!$E8*(1+Inputs!$B$7)^(ED$2-1) -> 2049.4725
A10: =Units!A9 -> 108 | C10: =Units!$E9*(1+Inputs!$B$7)^(C$2-1) -> 1525 | D10: =Units!$E9*(1+Inputs!$B$7)^(D$2-1) -> 1525 | E10: =Units!$E9*(1+Inputs!$B$7)^(E$2-1) -> 1525 | F10: =Units!$E9*(1+Inputs!$B$7)^(F$2-1) -> 1525 | G10: =Units!$E9*(1+Inputs!$B$7)^(G$2-1) -> 1525 | H10: =Units!$E9*(1+Inputs!$B$7)^(H$2-1) -> 1525 | I10: =Units!$E9*(1+Inputs!$B$7)^(I$2-1) -> 1525 | J10: =Units!$E9*(1+Inputs!$B$7)^(J$2-1) -> 1525 | ... ED10: =Units!$E9*(1+Inputs!$B$7)^(ED$2-1) -> 2049.4725
A11: =Units!A10 -> 109 | C11: =Units!$E10*(1+Inputs!$B$7)^(C$2-1) -> 1525 | D11: =Units!$E10*(1+Inputs!$B$7)^(D$2-1) -> 1525 | E11: =Units!$E10*(1+Inputs!$B$7)^(E$2-1) -> 1525 | F11: =Units!$E10*(1+Inputs!$B$7)^(F$2-1) -> 1525 | G11: =Units!$E10*(1+Inputs!$B$7)^(G$2-1) -> 1525 | H11: =Units!$E10*(1+Inputs!$B$7)^(H$2-1) -> 1525 | I11: =Units!$E10*(1+Inputs!$B$7)^(I$2-1) -> 1525 | J11: =Units!$E10*(1+Inputs!$B$7)^(J$2-1) -> 1525 | ... ED11: =Units!$E10*(1+Inputs!$B$7)^(ED$2-1) -> 2049.4725
A12: =Units!A11 -> 110 | C12: =Units!$E11*(1+Inputs!$B$7)^(C$2-1) -> 1525 | D12: =Units!$E11*(1+Inputs!$B$7)^(D$2-1) -> 1525 | E12: =Units!$E11*(1+Inputs!$B$7)^(E$2-1) -> 1525 | F12: =Units!$E11*(1+Inputs!$B$7)^(F$2-1) -> 1525 | G12: =Units!$E11*(1+Inputs!$B$7)^(G$2-1) -> 1525 | H12: =Units!$E11*(1+Inputs!$B$7)^(H$2-1) -> 1525 | I12: =Units!$E11*(1+Inputs!$B$7)^(I$2-1) -> 1525 | J12: =Units!$E11*(1+Inputs!$B$7)^(J$2-1) -> 1525 | ... ED12: =Units!$E11*(1+Inputs!$B$7)^(ED$2-1) -> 2049.4725
A13: =Units!A12 -> 111 | C13: =Units!$E12*(1+Inputs!$B$7)^(C$2-1) -> 1525 | D13: =Units!$E12*(1+Inputs!$B$7)^(D$2-1) -> 1525 | E13: =Units!$E12*(1+Inputs!$B$7)^(E$2-1) -> 1525 | F13: =Units!$E12*(1+Inputs!$B$7)^(F$2-1) -> 1525 | G13: =Units!$E12*(1+Inputs!$B$7)^(G$2-1) -> 1525 | H13: =Units!$E12*(1+Inputs!$B$7)^(H$2-1) -> 1525 | I13: =Units!$E12*(1+Inputs!$B$7)^(I$2-1) -> 1525 | J13: =Units!$E12*(1+Inputs!$B$7)^(J$2-1) -> 1525 | ... ED13: =Units!$E12*(1+Inputs!$B$7)^(ED$2-1) -> 2049.4725
A14: =Units!A13 -> 112 | C14: =Units!$E13*(1+Inputs!$B$7)^(C$2-1) -> 1525 | D14: =Units!$E13*(1+Inputs!$B$7)^(D$2-1) -> 1525 | E14: =Units!$E13*(1+Inputs!$B$7)^(E$2-1) -> 1525 | F14: =Units!$E13*(1+Inputs!$B$7)^(F$2-1) -> 1525 | G14: =Units!$E13*(1+Inputs!$B$7)^(G$2-1) -> 1525 | H14: =Units!$E13*(1+Inputs!$B$7)^(H$2-1) -> 1525 | I14: =Units!$E13*(1+Inputs!$B$7)^(I$2-1) -> 1525 | J14: =Units!$E13*(1+Inputs!$B$7)^(J$2-1) -> 1525 | ... ED14: =Units!$E13*(1+Inputs!$B$7)^(ED$2-1) -> 2049.4725
... A122: =Units!A121 -> 430 | C122: =Units!$E121*(1+Inputs!$B$7)^(C$2-1) -> 2240 | D122: =Units!$E121*(1+Inputs!$B$7)^(D$2-1) -> 2240 | E122: =Units!$E121*(1+Inputs!$B$7)^(E$2-1) -> 2240 | F122: =Units!$E121*(1+Inputs!$B$7)^(F$2-1) -> 2240 | G122: =Units!$E121*(1+Inputs!$B$7)^(G$2-1) -> 2240 | H122: =Units!$E121*(1+Inputs!$B$7)^(H$2-1) -> 2240 | I122: =Units!$E121*(1+Inputs!$B$7)^(I$2-1) -> 2240 | J122: =Units!$E121*(1+Inputs!$B$7)^(J$2-1) -> 2240 | ... ED122: =Units!$E121*(1+Inputs!$B$7)^(ED$2-1) -> 3010.3727

Sheet Rent
A1: Month | B1: Opening rent | C1: 1 | D1: 2 | E1: 3 | F1: 4 | G1: 5 | H1: 6 | I1: 7 | J1: 8 | K1: 9 | L1: 10 | M1: 11 | N1: 12 | O1: 13 | P1: 14 | Q1: 15 | R1: 16 | S1: 17 | T1: 18 | U1: 19 | V1: 20 | W1: 21 | X1: 22 | Y1: 23 | Z1: 24 | AA1: 25 | AB1: 26 | AC1: 27 | AD1: 28 | AE1: 29 | AF1: 30 | AG1: 31 | AH1: 32 | AI1: 33 | AJ1: 34 | AK1: 35 | AL1: 36 | AM1: 37 | AN1: 38 | AO1: 39 | AP1: 40 | AQ1: 41 | AR1: 42 | AS1: 43 | AT1: 44 | AU1: 45 | AV1: 46 | AW1: 47 | AX1: 48 | AY1: 49 | AZ1: 50 | BA1: 51 | BB1: 52 | BC1: 53 | BD1: 54 | BE1: 55 | BF1: 56 | BG1: 57 | BH1: 58 | BI1: 59 | BJ1: 60 | BK1: 61 | BL1: 62 | BM1: 63 | BN1: 64 | BO1: 65 | BP1: 66 | BQ1: 67 | BR1: 68 | BS1: 69 | BT1: 70 | BU1: 71 | BV1: 72 | BW1: 73 | BX1: 74 | BY1: 75 | BZ1: 76 | CA1: 77 | CB1: 78 | CC1: 79 | CD1: 80 | CE1: 81 | CF1: 82 | CG1: 83 | CH1: 84 | CI1: 85 | CJ1: 86 | CK1: 87 | CL1: 88 | CM1: 89 | CN1: 90 | CO1: 91 | CP1: 92 | CQ1: 93 | CR1: 94 | CS1: 95 | CT1: 96 | CU1: 97 | CV1: 98 | CW1: 99 | CX1: 100 | CY1: 101 | CZ1: 102 | DA1: 103 | DB1: 104 | DC1: 105 | DD1: 106 | DE1: 107 | DF1: 108 | DG1: 109 | DH1: 110 | DI1: 111 | DJ1: 112 | DK1: 113 | DL1: 114 | DM1: 115 | DN1: 116 | DO1: 117 | DP1: 118 | DQ1: 119 | DR1: 120 | DS1: 121 | DT1: 122 | DU1: 123 | DV1: 124 | DW1: 125 | DX1: 126 | DY1: 127 | DZ1: 128 | EA1: 129 | EB1: 130 | EC1: 131 | ED1: 132
A2: Year | C2: =ROUNDUP(C1/12,0) -> 1 | D2: =ROUNDUP(D1/12,0) -> 1 | E2: =ROUNDUP(E1/12,0) -> 1 | F2: =ROUNDUP(F1/12,0) -> 1 | G2: =ROUNDUP(G1/12,0) -> 1 | H2: =ROUNDUP(H1/12,0) -> 1 | I2: =ROUNDUP(I1/12,0) -> 1 | J2: =ROUNDUP(J1/12,0) -> 1 | ... ED2: =ROUNDUP(ED1/12,0) -> 11
A3: =Units!A2 -> 101 | B3: =IF(Units!K2=1,Units!F2,0) -> 1565 | C3: =IF(C$1<Units!$P2,0,IF(AND(Units!$K2=0,C$1=Units!$O2),Units!$R2,IF(AND(C$1>=Units!$Q2,MOD(C$1-Units!$Q2,12)=0),IF(AND(Units!$L2=1,C$1=Units!$Q2),IF(Units!$J2<>"",Units!$J2,Mkt!C3),Inputs!$B$15*Mkt!C3+(1-Inputs!$B$15)*MIN(Mkt!C3,B3*(1+Inputs!$B$18))),B3))) -> 1565 | D3: =IF(D$1<Units!$P2,0,IF(AND(Units!$K2=0,D$1=Units!$O2),Units!$R2,IF(AND(D$1>=Units!$Q2,MOD(D$1-Units!$Q2,12)=0),IF(AND(Units!$L2=1,D$1=Units!$Q2),IF(Units!$J2<>"",Units!$J2,Mkt!D3),Inputs!$B$15*Mkt!D3+(1-Inputs!$B$15)*MIN(Mkt!D3,C3*(1+Inputs!$B$18))),C3))) -> 1525 | E3: =IF(E$1<Units!$P2,0,IF(AND(Units!$K2=0,E$1=Units!$O2),Units!$R2,IF(AND(E$1>=Units!$Q2,MOD(E$1-Units!$Q2,12)=0),IF(AND(Units!$L2=1,E$1=Units!$Q2),IF(Units!$J2<>"",Units!$J2,Mkt!E3),Inputs!$B$15*Mkt!E3+(1-Inputs!$B$15)*MIN(Mkt!E3,D3*(1+Inputs!$B$18))),D3))) -> 1525 | F3: =IF(F$1<Units!$P2,0,IF(AND(Units!$K2=0,F$1=Units!$O2),Units!$R2,IF(AND(F$1>=Units!$Q2,MOD(F$1-Units!$Q2,12)=0),IF(AND(Units!$L2=1,F$1=Units!$Q2),IF(Units!$J2<>"",Units!$J2,Mkt!F3),Inputs!$B$15*Mkt!F3+(1-Inputs!$B$15)*MIN(Mkt!F3,E3*(1+Inputs!$B$18))),E3))) -> 1525 | G3: =IF(G$1<Units!$P2,0,IF(AND(Units!$K2=0,G$1=Units!$O2),Units!$R2,IF(AND(G$1>=Units!$Q2,MOD(G$1-Units!$Q2,12)=0),IF(AND(Units!$L2=1,G$1=Units!$Q2),IF(Units!$J2<>"",Units!$J2,Mkt!G3),Inputs!$B$15*Mkt!G3+(1-Inputs!$B$15)*MIN(Mkt!G3,F3*(1+Inputs!$B$18))),F3))) -> 1525 | H3: =IF(H$1<Units!$P2,0,IF(AND(Units!$K2=0,H$1=Units!$O2),Units!$R2,IF(AND(H$1>=Units!$Q2,MOD(H$1-Units!$Q2,12)=0),IF(AND(Units!$L2=1,H$1=Units!$Q2),IF(Units!$J2<>"",Units!$J2,Mkt!H3),Inputs!$B$15*Mkt!H3+(1-Inputs!$B$15)*MIN(Mkt!H3,G3*(1+Inputs!$B$18))),G3))) -> 1525 | I3: =IF(I$1<Units!$P2,0,IF(AND(Units!$K2=0,I$1=Units!$O2),Units!$R2,IF(AND(I$1>=Units!$Q2,MOD(I$1-Units!$Q2,12)=0),IF(AND(Units!$L2=1,I$1=Units!$Q2),IF(Units!$J2<>"",Units!$J2,Mkt!I3),Inputs!$B$15*Mkt!I3+(1-Inputs!$B$15)*MIN(Mkt!I3,H3*(1+Inputs!$B$18))),H3))) -> 1525 | J3: =IF(J$1<Units!$P2,0,IF(AND(Units!$K2=0,J$1=Units!$O2),Units!$R2,IF(AND(J$1>=Units!$Q2,MOD(J$1-Units!$Q2,12)=0),IF(AND(Units!$L2=1,J$1=Units!$Q2),IF(Units!$J2<>"",Units!$J2,Mkt!J3),Inputs!$B$15*Mkt!J3+(1-Inputs!$B$15)*MIN(Mkt!J3,I3*(1+Inputs!$B$18))),I3))) -> 1525 | ... ED3: =IF(ED$1<Units!$P2,0,IF(AND(Units!$K2=0,ED$1=Units!$O2),Units!$R2,IF(AND(ED$1>=Units!$Q2,MOD(ED$1-Units!$Q2,12)=0),IF(AND(Units!$L2=1,ED$1=Units!$Q2),IF(Units!$J2<>"",Units!$J2,Mkt!ED3),Inputs!$B$15*Mkt!ED3+(1-Inputs!$B$15)*MIN(Mkt!ED3,EC3*(1+Inputs!$B$18))),EC3))) -> 2049.4725
A4: =Units!A3 -> 102 | B4: =IF(Units!K3=1,Units!F3,0) -> 1235 | C4: =IF(C$1<Units!$P3,0,IF(AND(Units!$K3=0,C$1=Units!$O3),Units!$R3,IF(AND(C$1>=Units!$Q3,MOD(C$1-Units!$Q3,12)=0),IF(AND(Units!$L3=1,C$1=Units!$Q3),IF(Units!$J3<>"",Units!$J3,Mkt!C4),Inputs!$B$15*Mkt!C4+(1-Inputs!$B$15)*MIN(Mkt!C4,B4*(1+Inputs!$B$18))),B4))) -> 1235 | D4: =IF(D$1<Units!$P3,0,IF(AND(Units!$K3=0,D$1=Units!$O3),Units!$R3,IF(AND(D$1>=Units!$Q3,MOD(D$1-Units!$Q3,12)=0),IF(AND(Units!$L3=1,D$1=Units!$Q3),IF(Units!$J3<>"",Units!$J3,Mkt!D4),Inputs!$B$15*Mkt!D4+(1-Inputs!$B$15)*MIN(Mkt!D4,C4*(1+Inputs!$B$18))),C4))) -> 1235 | E4: =IF(E$1<Units!$P3,0,IF(AND(Units!$K3=0,E$1=Units!$O3),Units!$R3,IF(AND(E$1>=Units!$Q3,MOD(E$1-Units!$Q3,12)=0),IF(AND(Units!$L3=1,E$1=Units!$Q3),IF(Units!$J3<>"",Units!$J3,Mkt!E4),Inputs!$B$15*Mkt!E4+(1-Inputs!$B$15)*MIN(Mkt!E4,D4*(1+Inputs!$B$18))),D4))) -> 1235 | F4: =IF(F$1<Units!$P3,0,IF(AND(Units!$K3=0,F$1=Units!$O3),Units!$R3,IF(AND(F$1>=Units!$Q3,MOD(F$1-Units!$Q3,12)=0),IF(AND(Units!$L3=1,F$1=Units!$Q3),IF(Units!$J3<>"",Units!$J3,Mkt!F4),Inputs!$B$15*Mkt!F4+(1-Inputs!$B$15)*MIN(Mkt!F4,E4*(1+Inputs!$B$18))),E4))) -> 1235 | G4: =IF(G$1<Units!$P3,0,IF(AND(Units!$K3=0,G$1=Units!$O3),Units!$R3,IF(AND(G$1>=Units!$Q3,MOD(G$1-Units!$Q3,12)=0),IF(AND(Units!$L3=1,G$1=Units!$Q3),IF(Units!$J3<>"",Units!$J3,Mkt!G4),Inputs!$B$15*Mkt!G4+(1-Inputs!$B$15)*MIN(Mkt!G4,F4*(1+Inputs!$B$18))),F4))) -> 1235 | H4: =IF(H$1<Units!$P3,0,IF(AND(Units!$K3=0,H$1=Units!$O3),Units!$R3,IF(AND(H$1>=Units!$Q3,MOD(H$1-Units!$Q3,12)=0),IF(AND(Units!$L3=1,H$1=Units!$Q3),IF(Units!$J3<>"",Units!$J3,Mkt!H4),Inputs!$B$15*Mkt!H4+(1-Inputs!$B$15)*MIN(Mkt!H4,G4*(1+Inputs!$B$18))),G4))) -> 1410.875 | I4: =IF(I$1<Units!$P3,0,IF(AND(Units!$K3=0,I$1=Units!$O3),Units!$R3,IF(AND(I$1>=Units!$Q3,MOD(I$1-Units!$Q3,12)=0),IF(AND(Units!$L3=1,I$1=Units!$Q3),IF(Units!$J3<>"",Units!$J3,Mkt!I4),Inputs!$B$15*Mkt!I4+(1-Inputs!$B$15)*MIN(Mkt!I4,H4*(1+Inputs!$B$18))),H4))) -> 1410.875 | J4: =IF(J$1<Units!$P3,0,IF(AND(Units!$K3=0,J$1=Units!$O3),Units!$R3,IF(AND(J$1>=Units!$Q3,MOD(J$1-Units!$Q3,12)=0),IF(AND(Units!$L3=1,J$1=Units!$Q3),IF(Units!$J3<>"",Units!$J3,Mkt!J4),Inputs!$B$15*Mkt!J4+(1-Inputs!$B$15)*MIN(Mkt!J4,I4*(1+Inputs!$B$18))),I4))) -> 1410.875 | ... ED4: =IF(ED$1<Units!$P3,0,IF(AND(Units!$K3=0,ED$1=Units!$O3),Units!$R3,IF(AND(ED$1>=Units!$Q3,MOD(ED$1-Units!$Q3,12)=0),IF(AND(Units!$L3=1,ED$1=Units!$Q3),IF(Units!$J3<>"",Units!$J3,Mkt!ED4),Inputs!$B$15*Mkt!ED4+(1-Inputs!$B$15)*MIN(Mkt!ED4,EC4*(1+Inputs!$B$18))),EC4))) -> 2049.4725
A5: =Units!A4 -> 103 | B5: =IF(Units!K4=1,Units!F4,0) -> 1475 | C5: =IF(C$1<Units!$P4,0,IF(AND(Units!$K4=0,C$1=Units!$O4),Units!$R4,IF(AND(C$1>=Units!$Q4,MOD(C$1-Units!$Q4,12)=0),IF(AND(Units!$L4=1,C$1=Units!$Q4),IF(Units!$J4<>"",Units!$J4,Mkt!C5),Inputs!$B$15*Mkt!C5+(1-Inputs!$B$15)*MIN(Mkt!C5,B5*(1+Inputs!$B$18))),B5))) -> 1475 | D5: =IF(D$1<Units!$P4,0,IF(AND(Units!$K4=0,D$1=Units!$O4),Units!$R4,IF(AND(D$1>=Units!$Q4,MOD(D$1-Units!$Q4,12)=0),IF(AND(Units!$L4=1,D$1=Units!$Q4),IF(Units!$J4<>"",Units!$J4,Mkt!D5),Inputs!$B$15*Mkt!D5+(1-Inputs!$B$15)*MIN(Mkt!D5,C5*(1+Inputs!$B$18))),C5))) -> 1475 | E5: =IF(E$1<Units!$P4,0,IF(AND(Units!$K4=0,E$1=Units!$O4),Units!$R4,IF(AND(E$1>=Units!$Q4,MOD(E$1-Units!$Q4,12)=0),IF(AND(Units!$L4=1,E$1=Units!$Q4),IF(Units!$J4<>"",Units!$J4,Mkt!E5),Inputs!$B$15*Mkt!E5+(1-Inputs!$B$15)*MIN(Mkt!E5,D5*(1+Inputs!$B$18))),D5))) -> 1475 | F5: =IF(F$1<Units!$P4,0,IF(AND(Units!$K4=0,F$1=Units!$O4),Units!$R4,IF(AND(F$1>=Units!$Q4,MOD(F$1-Units!$Q4,12)=0),IF(AND(Units!$L4=1,F$1=Units!$Q4),IF(Units!$J4<>"",Units!$J4,Mkt!F5),Inputs!$B$15*Mkt!F5+(1-Inputs!$B$15)*MIN(Mkt!F5,E5*(1+Inputs!$B$18))),E5))) -> 1475 | G5: =IF(G$1<Units!$P4,0,IF(AND(Units!$K4=0,G$1=Units!$O4),Units!$R4,IF(AND(G$1>=Units!$Q4,MOD(G$1-Units!$Q4,12)=0),IF(AND(Units!$L4=1,G$1=Units!$Q4),IF(Units!$J4<>"",Units!$J4,Mkt!G5),Inputs!$B$15*Mkt!G5+(1-Inputs!$B$15)*MIN(Mkt!G5,F5*(1+Inputs!$B$18))),F5))) -> 1475 | H5: =IF(H$1<Units!$P4,0,IF(AND(Units!$K4=0,H$1=Units!$O4),Units!$R4,IF(AND(H$1>=Units!$Q4,MOD(H$1-Units!$Q4,12)=0),IF(AND(Units!$L4=1,H$1=Units!$Q4),IF(Units!$J4<>"",Units!$J4,Mkt!H5),Inputs!$B$15*Mkt!H5+(1-Inputs!$B$15)*MIN(Mkt!H5,G5*(1+Inputs!$B$18))),G5))) -> 1475 | I5: =IF(I$1<Units!$P4,0,IF(AND(Units!$K4=0,I$1=Units!$O4),Units!$R4,IF(AND(I$1>=Units!$Q4,MOD(I$1-Units!$Q4,12)=0),IF(AND(Units!$L4=1,I$1=Units!$Q4),IF(Units!$J4<>"",Units!$J4,Mkt!I5),Inputs!$B$15*Mkt!I5+(1-Inputs!$B$15)*MIN(Mkt!I5,H5*(1+Inputs!$B$18))),H5))) -> 1475 | J5: =IF(J$1<Units!$P4,0,IF(AND(Units!$K4=0,J$1=Units!$O4),Units!$R4,IF(AND(J$1>=Units!$Q4,MOD(J$1-Units!$Q4,12)=0),IF(AND(Units!$L4=1,J$1=Units!$Q4),IF(Units!$J4<>"",Units!$J4,Mkt!J5),Inputs!$B$15*Mkt!J5+(1-Inputs!$B$15)*MIN(Mkt!J5,I5*(1+Inputs!$B$18))),I5))) -> 1475 | ... ED5: =IF(ED$1<Units!$P4,0,IF(AND(Units!$K4=0,ED$1=Units!$O4),Units!$R4,IF(AND(ED$1>=Units!$Q4,MOD(ED$1-Units!$Q4,12)=0),IF(AND(Units!$L4=1,ED$1=Units!$Q4),IF(Units!$J4<>"",Units!$J4,Mkt!ED5),Inputs!$B$15*Mkt!ED5+(1-Inputs!$B$15)*MIN(Mkt!ED5,EC5*(1+Inputs!$B$18))),EC5))) -> 2049.4725
A6: =Units!A5 -> 104 | B6: =IF(Units!K5=1,Units!F5,0) -> 0 | C6: =IF(C$1<Units!$P5,0,IF(AND(Units!$K5=0,C$1=Units!$O5),Units!$R5,IF(AND(C$1>=Units!$Q5,MOD(C$1-Units!$Q5,12)=0),IF(AND(Units!$L5=1,C$1=Units!$Q5),IF(Units!$J5<>"",Units!$J5,Mkt!C6),Inputs!$B$15*Mkt!C6+(1-Inputs!$B$15)*MIN(Mkt!C6,B6*(1+Inputs!$B$18))),B6))) -> 1525 | D6: =IF(D$1<Units!$P5,0,IF(AND(Units!$K5=0,D$1=Units!$O5),Units!$R5,IF(AND(D$1>=Units!$Q5,MOD(D$1-Units!$Q5,12)=0),IF(AND(Units!$L5=1,D$1=Units!$Q5),IF(Units!$J5<>"",Units!$J5,Mkt!D6),Inputs!$B$15*Mkt!D6+(1-Inputs!$B$15)*MIN(Mkt!D6,C6*(1+Inputs!$B$18))),C6))) -> 1525 | E6: =IF(E$1<Units!$P5,0,IF(AND(Units!$K5=0,E$1=Units!$O5),Units!$R5,IF(AND(E$1>=Units!$Q5,MOD(E$1-Units!$Q5,12)=0),IF(AND(Units!$L5=1,E$1=Units!$Q5),IF(Units!$J5<>"",Units!$J5,Mkt!E6),Inputs!$B$15*Mkt!E6+(1-Inputs!$B$15)*MIN(Mkt!E6,D6*(1+Inputs!$B$18))),D6))) -> 1525 | F6: =IF(F$1<Units!$P5,0,IF(AND(Units!$K5=0,F$1=Units!$O5),Units!$R5,IF(AND(F$1>=Units!$Q5,MOD(F$1-Units!$Q5,12)=0),IF(AND(Units!$L5=1,F$1=Units!$Q5),IF(Units!$J5<>"",Units!$J5,Mkt!F6),Inputs!$B$15*Mkt!F6+(1-Inputs!$B$15)*MIN(Mkt!F6,E6*(1+Inputs!$B$18))),E6))) -> 1525 | G6: =IF(G$1<Units!$P5,0,IF(AND(Units!$K5=0,G$1=Units!$O5),Units!$R5,IF(AND(G$1>=Units!$Q5,MOD(G$1-Units!$Q5,12)=0),IF(AND(Units!$L5=1,G$1=Units!$Q5),IF(Units!$J5<>"",Units!$J5,Mkt!G6),Inputs!$B$15*Mkt!G6+(1-Inputs!$B$15)*MIN(Mkt!G6,F6*(1+Inputs!$B$18))),F6))) -> 1525 | H6: =IF(H$1<Units!$P5,0,IF(AND(Units!$K5=0,H$1=Units!$O5),Units!$R5,IF(AND(H$1>=Units!$Q5,MOD(H$1-Units!$Q5,12)=0),IF(AND(Units!$L5=1,H$1=Units!$Q5),IF(Units!$J5<>"",Units!$J5,Mkt!H6),Inputs!$B$15*Mkt!H6+(1-Inputs!$B$15)*MIN(Mkt!H6,G6*(1+Inputs!$B$18))),G6))) -> 1525 | I6: =IF(I$1<Units!$P5,0,IF(AND(Units!$K5=0,I$1=Units!$O5),Units!$R5,IF(AND(I$1>=Units!$Q5,MOD(I$1-Units!$Q5,12)=0),IF(AND(Units!$L5=1,I$1=Units!$Q5),IF(Units!$J5<>"",Units!$J5,Mkt!I6),Inputs!$B$15*Mkt!I6+(1-Inputs!$B$15)*MIN(Mkt!I6,H6*(1+Inputs!$B$18))),H6))) -> 1525 | J6: =IF(J$1<Units!$P5,0,IF(AND(Units!$K5=0,J$1=Units!$O5),Units!$R5,IF(AND(J$1>=Units!$Q5,MOD(J$1-Units!$Q5,12)=0),IF(AND(Units!$L5=1,J$1=Units!$Q5),IF(Units!$J5<>"",Units!$J5,Mkt!J6),Inputs!$B$15*Mkt!J6+(1-Inputs!$B$15)*MIN(Mkt!J6,I6*(1+Inputs!$B$18))),I6))) -> 1525 | ... ED6: =IF(ED$1<Units!$P5,0,IF(AND(Units!$K5=0,ED$1=Units!$O5),Units!$R5,IF(AND(ED$1>=Units!$Q5,MOD(ED$1-Units!$Q5,12)=0),IF(AND(Units!$L5=1,ED$1=Units!$Q5),IF(Units!$J5<>"",Units!$J5,Mkt!ED6),Inputs!$B$15*Mkt!ED6+(1-Inputs!$B$15)*MIN(Mkt!ED6,EC6*(1+Inputs!$B$18))),EC6))) -> 2049.4725
A7: =Units!A6 -> 105 | B7: =IF(Units!K6=1,Units!F6,0) -> 1445 | C7: =IF(C$1<Units!$P6,0,IF(AND(Units!$K6=0,C$1=Units!$O6),Units!$R6,IF(AND(C$1>=Units!$Q6,MOD(C$1-Units!$Q6,12)=0),IF(AND(Units!$L6=1,C$1=Units!$Q6),IF(Units!$J6<>"",Units!$J6,Mkt!C7),Inputs!$B$15*Mkt!C7+(1-Inputs!$B$15)*MIN(Mkt!C7,B7*(1+Inputs!$B$18))),B7))) -> 1445 | D7: =IF(D$1<Units!$P6,0,IF(AND(Units!$K6=0,D$1=Units!$O6),Units!$R6,IF(AND(D$1>=Units!$Q6,MOD(D$1-Units!$Q6,12)=0),IF(AND(Units!$L6=1,D$1=Units!$Q6),IF(Units!$J6<>"",Units!$J6,Mkt!D7),Inputs!$B$15*Mkt!D7+(1-Inputs!$B$15)*MIN(Mkt!D7,C7*(1+Inputs!$B$18))),C7))) -> 1445 | E7: =IF(E$1<Units!$P6,0,IF(AND(Units!$K6=0,E$1=Units!$O6),Units!$R6,IF(AND(E$1>=Units!$Q6,MOD(E$1-Units!$Q6,12)=0),IF(AND(Units!$L6=1,E$1=Units!$Q6),IF(Units!$J6<>"",Units!$J6,Mkt!E7),Inputs!$B$15*Mkt!E7+(1-Inputs!$B$15)*MIN(Mkt!E7,D7*(1+Inputs!$B$18))),D7))) -> 1521.125 | F7: =IF(F$1<Units!$P6,0,IF(AND(Units!$K6=0,F$1=Units!$O6),Units!$R6,IF(AND(F$1>=Units!$Q6,MOD(F$1-Units!$Q6,12)=0),IF(AND(Units!$L6=1,F$1=Units!$Q6),IF(Units!$J6<>"",Units!$J6,Mkt!F7),Inputs!$B$15*Mkt!F7+(1-Inputs!$B$15)*MIN(Mkt!F7,E7*(1+Inputs!$B$18))),E7))) -> 1521.125 | G7: =IF(G$1<Units!$P6,0,IF(AND(Units!$K6=0,G$1=Units!$O6),Units!$R6,IF(AND(G$1>=Units!$Q6,MOD(G$1-Units!$Q6,12)=0),IF(AND(Units!$L6=1,G$1=Units!$Q6),IF(Units!$J6<>"",Units!$J6,Mkt!G7),Inputs!$B$15*Mkt!G7+(1-Inputs!$B$15)*MIN(Mkt!G7,F7*(1+Inputs!$B$18))),F7))) -> 1521.125 | H7: =IF(H$1<Units!$P6,0,IF(AND(Units!$K6=0,H$1=Units!$O6),Units!$R6,IF(AND(H$1>=Units!$Q6,MOD(H$1-Units!$Q6,12)=0),IF(AND(Units!$L6=1,H$1=Units!$Q6),IF(Units!$J6<>"",Units!$J6,Mkt!H7),Inputs!$B$15*Mkt!H7+(1-Inputs!$B$15)*MIN(Mkt!H7,G7*(1+Inputs!$B$18))),G7))) -> 1521.125 | I7: =IF(I$1<Units!$P6,0,IF(AND(Units!$K6=0,I$1=Units!$O6),Units!$R6,IF(AND(I$1>=Units!$Q6,MOD(I$1-Units!$Q6,12)=0),IF(AND(Units!$L6=1,I$1=Units!$Q6),IF(Units!$J6<>"",Units!$J6,Mkt!I7),Inputs!$B$15*Mkt!I7+(1-Inputs!$B$15)*MIN(Mkt!I7,H7*(1+Inputs!$B$18))),H7))) -> 1521.125 | J7: =IF(J$1<Units!$P6,0,IF(AND(Units!$K6=0,J$1=Units!$O6),Units!$R6,IF(AND(J$1>=Units!$Q6,MOD(J$1-Units!$Q6,12)=0),IF(AND(Units!$L6=1,J$1=Units!$Q6),IF(Units!$J6<>"",Units!$J6,Mkt!J7),Inputs!$B$15*Mkt!J7+(1-Inputs!$B$15)*MIN(Mkt!J7,I7*(1+Inputs!$B$18))),I7))) -> 1521.125 | ... ED7: =IF(ED$1<Units!$P6,0,IF(AND(Units!$K6=0,ED$1=Units!$O6),Units!$R6,IF(AND(ED$1>=Units!$Q6,MOD(ED$1-Units!$Q6,12)=0),IF(AND(Units!$L6=1,ED$1=Units!$Q6),IF(Units!$J6<>"",Units!$J6,Mkt!ED7),Inputs!$B$15*Mkt!ED7+(1-Inputs!$B$15)*MIN(Mkt!ED7,EC7*(1+Inputs!$B$18))),EC7))) -> 2049.4725
A8: =Units!A7 -> 106 | B8: =IF(Units!K7=1,Units!F7,0) -> 1400 | C8: =IF(C$1<Units!$P7,0,IF(AND(Units!$K7=0,C$1=Units!$O7),Units!$R7,IF(AND(C$1>=Units!$Q7,MOD(C$1-Units!$Q7,12)=0),IF(AND(Units!$L7=1,C$1=Units!$Q7),IF(Units!$J7<>"",Units!$J7,Mkt!C8),Inputs!$B$15*Mkt!C8+(1-Inputs!$B$15)*MIN(Mkt!C8,B8*(1+Inputs!$B$18))),B8))) -> 1400 | D8: =IF(D$1<Units!$P7,0,IF(AND(Units!$K7=0,D$1=Units!$O7),Units!$R7,IF(AND(D$1>=Units!$Q7,MOD(D$1-Units!$Q7,12)=0),IF(AND(Units!$L7=1,D$1=Units!$Q7),IF(Units!$J7<>"",Units!$J7,Mkt!D8),Inputs!$B$15*Mkt!D8+(1-Inputs!$B$15)*MIN(Mkt!D8,C8*(1+Inputs!$B$18))),C8))) -> 1400 | E8: =IF(E$1<Units!$P7,0,IF(AND(Units!$K7=0,E$1=Units!$O7),Units!$R7,IF(AND(E$1>=Units!$Q7,MOD(E$1-Units!$Q7,12)=0),IF(AND(Units!$L7=1,E$1=Units!$Q7),IF(Units!$J7<>"",Units!$J7,Mkt!E8),Inputs!$B$15*Mkt!E8+(1-Inputs!$B$15)*MIN(Mkt!E8,D8*(1+Inputs!$B$18))),D8))) -> 1400 | F8: =IF(F$1<Units!$P7,0,IF(AND(Units!$K7=0,F$1=Units!$O7),Units!$R7,IF(AND(F$1>=Units!$Q7,MOD(F$1-Units!$Q7,12)=0),IF(AND(Units!$L7=1,F$1=Units!$Q7),IF(Units!$J7<>"",Units!$J7,Mkt!F8),Inputs!$B$15*Mkt!F8+(1-Inputs!$B$15)*MIN(Mkt!F8,E8*(1+Inputs!$B$18))),E8))) -> 1497.5 | G8: =IF(G$1<Units!$P7,0,IF(AND(Units!$K7=0,G$1=Units!$O7),Units!$R7,IF(AND(G$1>=Units!$Q7,MOD(G$1-Units!$Q7,12)=0),IF(AND(Units!$L7=1,G$1=Units!$Q7),IF(Units!$J7<>"",Units!$J7,Mkt!G8),Inputs!$B$15*Mkt!G8+(1-Inputs!$B$15)*MIN(Mkt!G8,F8*(1+Inputs!$B$18))),F8))) -> 1497.5 | H8: =IF(H$1<Units!$P7,0,IF(AND(Units!$K7=0,H$1=Units!$O7),Units!$R7,IF(AND(H$1>=Units!$Q7,MOD(H$1-Units!$Q7,12)=0),IF(AND(Units!$L7=1,H$1=Units!$Q7),IF(Units!$J7<>"",Units!$J7,Mkt!H8),Inputs!$B$15*Mkt!H8+(1-Inputs!$B$15)*MIN(Mkt!H8,G8*(1+Inputs!$B$18))),G8))) -> 1497.5 | I8: =IF(I$1<Units!$P7,0,IF(AND(Units!$K7=0,I$1=Units!$O7),Units!$R7,IF(AND(I$1>=Units!$Q7,MOD(I$1-Units!$Q7,12)=0),IF(AND(Units!$L7=1,I$1=Units!$Q7),IF(Units!$J7<>"",Units!$J7,Mkt!I8),Inputs!$B$15*Mkt!I8+(1-Inputs!$B$15)*MIN(Mkt!I8,H8*(1+Inputs!$B$18))),H8))) -> 1497.5 | J8: =IF(J$1<Units!$P7,0,IF(AND(Units!$K7=0,J$1=Units!$O7),Units!$R7,IF(AND(J$1>=Units!$Q7,MOD(J$1-Units!$Q7,12)=0),IF(AND(Units!$L7=1,J$1=Units!$Q7),IF(Units!$J7<>"",Units!$J7,Mkt!J8),Inputs!$B$15*Mkt!J8+(1-Inputs!$B$15)*MIN(Mkt!J8,I8*(1+Inputs!$B$18))),I8))) -> 1497.5 | ... ED8: =IF(ED$1<Units!$P7,0,IF(AND(Units!$K7=0,ED$1=Units!$O7),Units!$R7,IF(AND(ED$1>=Units!$Q7,MOD(ED$1-Units!$Q7,12)=0),IF(AND(Units!$L7=1,ED$1=Units!$Q7),IF(Units!$J7<>"",Units!$J7,Mkt!ED8),Inputs!$B$15*Mkt!ED8+(1-Inputs!$B$15)*MIN(Mkt!ED8,EC8*(1+Inputs!$B$18))),EC8))) -> 2049.4725
A9: =Units!A8 -> 107 | B9: =IF(Units!K8=1,Units!F8,0) -> 1580 | C9: =IF(C$1<Units!$P8,0,IF(AND(Units!$K8=0,C$1=Units!$O8),Units!$R8,IF(AND(C$1>=Units!$Q8,MOD(C$1-Units!$Q8,12)=0),IF(AND(Units!$L8=1,C$1=Units!$Q8),IF(Units!$J8<>"",Units!$J8,Mkt!C9),Inputs!$B$15*Mkt!C9+(1-Inputs!$B$15)*MIN(Mkt!C9,B9*(1+Inputs!$B$18))),B9))) -> 1580 | D9: =IF(D$1<Units!$P8,0,IF(AND(Units!$K8=0,D$1=Units!$O8),Units!$R8,IF(AND(D$1>=Units!$Q8,MOD(D$1-Units!$Q8,12)=0),IF(AND(Units!$L8=1,D$1=Units!$Q8),IF(Units!$J8<>"",Units!$J8,Mkt!D9),Inputs!$B$15*Mkt!D9+(1-Inputs!$B$15)*MIN(Mkt!D9,C9*(1+Inputs!$B$18))),C9))) -> 1580 | E9: =IF(E$1<Units!$P8,0,IF(AND(Units!$K8=0,E$1=Units!$O8),Units!$R8,IF(AND(E$1>=Units!$Q8,MOD(E$1-Units!$Q8,12)=0),IF(AND(Units!$L8=1,E$1=Units!$Q8),IF(Units!$J8<>"",Units!$J8,Mkt!E9),Inputs!$B$15*Mkt!E9+(1-Inputs!$B$15)*MIN(Mkt!E9,D9*(1+Inputs!$B$18))),D9))) -> 1525 | F9: =IF(F$1<Units!$P8,0,IF(AND(Units!$K8=0,F$1=Units!$O8),Units!$R8,IF(AND(F$1>=Units!$Q8,MOD(F$1-Units!$Q8,12)=0),IF(AND(Units!$L8=1,F$1=Units!$Q8),IF(Units!$J8<>"",Units!$J8,Mkt!F9),Inputs!$B$15*Mkt!F9+(1-Inputs!$B$15)*MIN(Mkt!F9,E9*(1+Inputs!$B$18))),E9))) -> 1525 | G9: =IF(G$1<Units!$P8,0,IF(AND(Units!$K8=0,G$1=Units!$O8),Units!$R8,IF(AND(G$1>=Units!$Q8,MOD(G$1-Units!$Q8,12)=0),IF(AND(Units!$L8=1,G$1=Units!$Q8),IF(Units!$J8<>"",Units!$J8,Mkt!G9),Inputs!$B$15*Mkt!G9+(1-Inputs!$B$15)*MIN(Mkt!G9,F9*(1+Inputs!$B$18))),F9))) -> 1525 | H9: =IF(H$1<Units!$P8,0,IF(AND(Units!$K8=0,H$1=Units!$O8),Units!$R8,IF(AND(H$1>=Units!$Q8,MOD(H$1-Units!$Q8,12)=0),IF(AND(Units!$L8=1,H$1=Units!$Q8),IF(Units!$J8<>"",Units!$J8,Mkt!H9),Inputs!$B$15*Mkt!H9+(1-Inputs!$B$15)*MIN(Mkt!H9,G9*(1+Inputs!$B$18))),G9))) -> 1525 | I9: =IF(I$1<Units!$P8,0,IF(AND(Units!$K8=0,I$1=Units!$O8),Units!$R8,IF(AND(I$1>=Units!$Q8,MOD(I$1-Units!$Q8,12)=0),IF(AND(Units!$L8=1,I$1=Units!$Q8),IF(Units!$J8<>"",Units!$J8,Mkt!I9),Inputs!$B$15*Mkt!I9+(1-Inputs!$B$15)*MIN(Mkt!I9,H9*(1+Inputs!$B$18))),H9))) -> 1525 | J9: =IF(J$1<Units!$P8,0,IF(AND(Units!$K8=0,J$1=Units!$O8),Units!$R8,IF(AND(J$1>=Units!$Q8,MOD(J$1-Units!$Q8,12)=0),IF(AND(Units!$L8=1,J$1=Units!$Q8),IF(Units!$J8<>"",Units!$J8,Mkt!J9),Inputs!$B$15*Mkt!J9+(1-Inputs!$B$15)*MIN(Mkt!J9,I9*(1+Inputs!$B$18))),I9))) -> 1525 | ... ED9: =IF(ED$1<Units!$P8,0,IF(AND(Units!$K8=0,ED$1=Units!$O8),Units!$R8,IF(AND(ED$1>=Units!$Q8,MOD(ED$1-Units!$Q8,12)=0),IF(AND(Units!$L8=1,ED$1=Units!$Q8),IF(Units!$J8<>"",Units!$J8,Mkt!ED9),Inputs!$B$15*Mkt!ED9+(1-Inputs!$B$15)*MIN(Mkt!ED9,EC9*(1+Inputs!$B$18))),EC9))) -> 2049.4725
A10: =Units!A9 -> 108 | B10: =IF(Units!K9=1,Units!F9,0) -> 1475 | C10: =IF(C$1<Units!$P9,0,IF(AND(Units!$K9=0,C$1=Units!$O9),Units!$R9,IF(AND(C$1>=Units!$Q9,MOD(C$1-Units!$Q9,12)=0),IF(AND(Units!$L9=1,C$1=Units!$Q9),IF(Units!$J9<>"",Units!$J9,Mkt!C10),Inputs!$B$15*Mkt!C10+(1-Inputs!$B$15)*MIN(Mkt!C10,B10*(1+Inputs!$B$18))),B10))) -> 1475 | D10: =IF(D$1<Units!$P9,0,IF(AND(Units!$K9=0,D$1=Units!$O9),Units!$R9,IF(AND(D$1>=Units!$Q9,MOD(D$1-Units!$Q9,12)=0),IF(AND(Units!$L9=1,D$1=Units!$Q9),IF(Units!$J9<>"",Units!$J9,Mkt!D10),Inputs!$B$15*Mkt!D10+(1-Inputs!$B$15)*MIN(Mkt!D10,C10*(1+Inputs!$B$18))),C10))) -> 1475 | E10: =IF(E$1<Units!$P9,0,IF(AND(Units!$K9=0,E$1=Units!$O9),Units!$R9,IF(AND(E$1>=Units!$Q9,MOD(E$1-Units!$Q9,12)=0),IF(AND(Units!$L9=1,E$1=Units!$Q9),IF(Units!$J9<>"",Units!$J9,Mkt!E10),Inputs!$B$15*Mkt!E10+(1-Inputs!$B$15)*MIN(Mkt!E10,D10*(1+Inputs!$B$18))),D10))) -> 1475 | F10: =IF(F$1<Units!$P9,0,IF(AND(Units!$K9=0,F$1=Units!$O9),Units!$R9,IF(AND(F$1>=Units!$Q9,MOD(F$1-Units!$Q9,12)=0),IF(AND(Units!$L9=1,F$1=Units!$Q9),IF(Units!$J9<>"",Units!$J9,Mkt!F10),Inputs!$B$15*Mkt!F10+(1-Inputs!$B$15)*MIN(Mkt!F10,E10*(1+Inputs!$B$18))),E10))) -> 1475 | G10: =IF(G$1<Units!$P9,0,IF(AND(Units!$K9=0,G$1=Units!$O9),Units!$R9,IF(AND(G$1>=Units!$Q9,MOD(G$1-Units!$Q9,12)=0),IF(AND(Units!$L9=1,G$1=Units!$Q9),IF(Units!$J9<>"",Units!$J9,Mkt!G10),Inputs!$B$15*Mkt!G10+(1-Inputs!$B$15)*MIN(Mkt!G10,F10*(1+Inputs!$B$18))),F10))) -> 1475 | H10: =IF(H$1<Units!$P9,0,IF(AND(Units!$K9=0,H$1=Units!$O9),Units!$R9,IF(AND(H$1>=Units!$Q9,MOD(H$1-Units!$Q9,12)=0),IF(AND(Units!$L9=1,H$1=Units!$Q9),IF(Units!$J9<>"",Units!$J9,Mkt!H10),Inputs!$B$15*Mkt!H10+(1-Inputs!$B$15)*MIN(Mkt!H10,G10*(1+Inputs!$B$18))),G10))) -> 1475 | I10: =IF(I$1<Units!$P9,0,IF(AND(Units!$K9=0,I$1=Units!$O9),Units!$R9,IF(AND(I$1>=Units!$Q9,MOD(I$1-Units!$Q9,12)=0),IF(AND(Units!$L9=1,I$1=Units!$Q9),IF(Units!$J9<>"",Units!$J9,Mkt!I10),Inputs!$B$15*Mkt!I10+(1-Inputs!$B$15)*MIN(Mkt!I10,H10*(1+Inputs!$B$18))),H10))) -> 1475 | J10: =IF(J$1<Units!$P9,0,IF(AND(Units!$K9=0,J$1=Units!$O9),Units!$R9,IF(AND(J$1>=Units!$Q9,MOD(J$1-Units!$Q9,12)=0),IF(AND(Units!$L9=1,J$1=Units!$Q9),IF(Units!$J9<>"",Units!$J9,Mkt!J10),Inputs!$B$15*Mkt!J10+(1-Inputs!$B$15)*MIN(Mkt!J10,I10*(1+Inputs!$B$18))),I10))) -> 1525 | ... ED10: =IF(ED$1<Units!$P9,0,IF(AND(Units!$K9=0,ED$1=Units!$O9),Units!$R9,IF(AND(ED$1>=Units!$Q9,MOD(ED$1-Units!$Q9,12)=0),IF(AND(Units!$L9=1,ED$1=Units!$Q9),IF(Units!$J9<>"",Units!$J9,Mkt!ED10),Inputs!$B$15*Mkt!ED10+(1-Inputs!$B$15)*MIN(Mkt!ED10,EC10*(1+Inputs!$B$18))),EC10))) -> 2049.4725
A11: =Units!A10 -> 109 | B11: =IF(Units!K10=1,Units!F10,0) -> 1565 | C11: =IF(C$1<Units!$P10,0,IF(AND(Units!$K10=0,C$1=Units!$O10),Units!$R10,IF(AND(C$1>=Units!$Q10,MOD(C$1-Units!$Q10,12)=0),IF(AND(Units!$L10=1,C$1=Units!$Q10),IF(Units!$J10<>"",Units!$J10,Mkt!C11),Inputs!$B$15*Mkt!C11+(1-Inputs!$B$15)*MIN(Mkt!C11,B11*(1+Inputs!$B$18))),B11))) -> 1565 | D11: =IF(D$1<Units!$P10,0,IF(AND(Units!$K10=0,D$1=Units!$O10),Units!$R10,IF(AND(D$1>=Units!$Q10,MOD(D$1-Units!$Q10,12)=0),IF(AND(Units!$L10=1,D$1=Units!$Q10),IF(Units!$J10<>"",Units!$J10,Mkt!D11),Inputs!$B$15*Mkt!D11+(1-Inputs!$B$15)*MIN(Mkt!D11,C11*(1+Inputs!$B$18))),C11))) -> 1565 | E11: =IF(E$1<Units!$P10,0,IF(AND(Units!$K10=0,E$1=Units!$O10),Units!$R10,IF(AND(E$1>=Units!$Q10,MOD(E$1-Units!$Q10,12)=0),IF(AND(Units!$L10=1,E$1=Units!$Q10),IF(Units!$J10<>"",Units!$J10,Mkt!E11),Inputs!$B$15*Mkt!E11+(1-Inputs!$B$15)*MIN(Mkt!E11,D11*(1+Inputs!$B$18))),D11))) -> 1565 | F11: =IF(F$1<Units!$P10,0,IF(AND(Units!$K10=0,F$1=Units!$O10),Units!$R10,IF(AND(F$1>=Units!$Q10,MOD(F$1-Units!$Q10,12)=0),IF(AND(Units!$L10=1,F$1=Units!$Q10),IF(Units!$J10<>"",Units!$J10,Mkt!F11),Inputs!$B$15*Mkt!F11+(1-Inputs!$B$15)*MIN(Mkt!F11,E11*(1+Inputs!$B$18))),E11))) -> 1565 | G11: =IF(G$1<Units!$P10,0,IF(AND(Units!$K10=0,G$1=Units!$O10),Units!$R10,IF(AND(G$1>=Units!$Q10,MOD(G$1-Units!$Q10,12)=0),IF(AND(Units!$L10=1,G$1=Units!$Q10),IF(Units!$J10<>"",Units!$J10,Mkt!G11),Inputs!$B$15*Mkt!G11+(1-Inputs!$B$15)*MIN(Mkt!G11,F11*(1+Inputs!$B$18))),F11))) -> 1565 | H11: =IF(H$1<Units!$P10,0,IF(AND(Units!$K10=0,H$1=Units!$O10),Units!$R10,IF(AND(H$1>=Units!$Q10,MOD(H$1-Units!$Q10,12)=0),IF(AND(Units!$L10=1,H$1=Units!$Q10),IF(Units!$J10<>"",Units!$J10,Mkt!H11),Inputs!$B$15*Mkt!H11+(1-Inputs!$B$15)*MIN(Mkt!H11,G11*(1+Inputs!$B$18))),G11))) -> 1565 | I11: =IF(I$1<Units!$P10,0,IF(AND(Units!$K10=0,I$1=Units!$O10),Units!$R10,IF(AND(I$1>=Units!$Q10,MOD(I$1-Units!$Q10,12)=0),IF(AND(Units!$L10=1,I$1=Units!$Q10),IF(Units!$J10<>"",Units!$J10,Mkt!I11),Inputs!$B$15*Mkt!I11+(1-Inputs!$B$15)*MIN(Mkt!I11,H11*(1+Inputs!$B$18))),H11))) -> 1565 | J11: =IF(J$1<Units!$P10,0,IF(AND(Units!$K10=0,J$1=Units!$O10),Units!$R10,IF(AND(J$1>=Units!$Q10,MOD(J$1-Units!$Q10,12)=0),IF(AND(Units!$L10=1,J$1=Units!$Q10),IF(Units!$J10<>"",Units!$J10,Mkt!J11),Inputs!$B$15*Mkt!J11+(1-Inputs!$B$15)*MIN(Mkt!J11,I11*(1+Inputs!$B$18))),I11))) -> 1565 | ... ED11: =IF(ED$1<Units!$P10,0,IF(AND(Units!$K10=0,ED$1=Units!$O10),Units!$R10,IF(AND(ED$1>=Units!$Q10,MOD(ED$1-Units!$Q10,12)=0),IF(AND(Units!$L10=1,ED$1=Units!$Q10),IF(Units!$J10<>"",Units!$J10,Mkt!ED11),Inputs!$B$15*Mkt!ED11+(1-Inputs!$B$15)*MIN(Mkt!ED11,EC11*(1+Inputs!$B$18))),EC11))) -> 2049.4725
A12: =Units!A11 -> 110 | B12: =IF(Units!K11=1,Units!F11,0) -> 1500 | C12: =IF(C$1<Units!$P11,0,IF(AND(Units!$K11=0,C$1=Units!$O11),Units!$R11,IF(AND(C$1>=Units!$Q11,MOD(C$1-Units!$Q11,12)=0),IF(AND(Units!$L11=1,C$1=Units!$Q11),IF(Units!$J11<>"",Units!$J11,Mkt!C12),Inputs!$B$15*Mkt!C12+(1-Inputs!$B$15)*MIN(Mkt!C12,B12*(1+Inputs!$B$18))),B12))) -> 1500 | D12: =IF(D$1<Units!$P11,0,IF(AND(Units!$K11=0,D$1=Units!$O11),Units!$R11,IF(AND(D$1>=Units!$Q11,MOD(D$1-Units!$Q11,12)=0),IF(AND(Units!$L11=1,D$1=Units!$Q11),IF(Units!$J11<>"",Units!$J11,Mkt!D12),Inputs!$B$15*Mkt!D12+(1-Inputs!$B$15)*MIN(Mkt!D12,C12*(1+Inputs!$B$18))),C12))) -> 1500 | E12: =IF(E$1<Units!$P11,0,IF(AND(Units!$K11=0,E$1=Units!$O11),Units!$R11,IF(AND(E$1>=Units!$Q11,MOD(E$1-Units!$Q11,12)=0),IF(AND(Units!$L11=1,E$1=Units!$Q11),IF(Units!$J11<>"",Units!$J11,Mkt!E12),Inputs!$B$15*Mkt!E12+(1-Inputs!$B$15)*MIN(Mkt!E12,D12*(1+Inputs!$B$18))),D12))) -> 1500 | F12: =IF(F$1<Units!$P11,0,IF(AND(Units!$K11=0,F$1=Units!$O11),Units!$R11,IF(AND(F$1>=Units!$Q11,MOD(F$1-Units!$Q11,12)=0),IF(AND(Units!$L11=1,F$1=Units!$Q11),IF(Units!$J11<>"",Units!$J11,Mkt!F12),Inputs!$B$15*Mkt!F12+(1-Inputs!$B$15)*MIN(Mkt!F12,E12*(1+Inputs!$B$18))),E12))) -> 1500 | G12: =IF(G$1<Units!$P11,0,IF(AND(Units!$K11=0,G$1=Units!$O11),Units!$R11,IF(AND(G$1>=Units!$Q11,MOD(G$1-Units!$Q11,12)=0),IF(AND(Units!$L11=1,G$1=Units!$Q11),IF(Units!$J11<>"",Units!$J11,Mkt!G12),Inputs!$B$15*Mkt!G12+(1-Inputs!$B$15)*MIN(Mkt!G12,F12*(1+Inputs!$B$18))),F12))) -> 1500 | H12: =IF(H$1<Units!$P11,0,IF(AND(Units!$K11=0,H$1=Units!$O11),Units!$R11,IF(AND(H$1>=Units!$Q11,MOD(H$1-Units!$Q11,12)=0),IF(AND(Units!$L11=1,H$1=Units!$Q11),IF(Units!$J11<>"",Units!$J11,Mkt!H12),Inputs!$B$15*Mkt!H12+(1-Inputs!$B$15)*MIN(Mkt!H12,G12*(1+Inputs!$B$18))),G12))) -> 1500 | I12: =IF(I$1<Units!$P11,0,IF(AND(Units!$K11=0,I$1=Units!$O11),Units!$R11,IF(AND(I$1>=Units!$Q11,MOD(I$1-Units!$Q11,12)=0),IF(AND(Units!$L11=1,I$1=Units!$Q11),IF(Units!$J11<>"",Units!$J11,Mkt!I12),Inputs!$B$15*Mkt!I12+(1-Inputs!$B$15)*MIN(Mkt!I12,H12*(1+Inputs!$B$18))),H12))) -> 1500 | J12: =IF(J$1<Units!$P11,0,IF(AND(Units!$K11=0,J$1=Units!$O11),Units!$R11,IF(AND(J$1>=Units!$Q11,MOD(J$1-Units!$Q11,12)=0),IF(AND(Units!$L11=1,J$1=Units!$Q11),IF(Units!$J11<>"",Units!$J11,Mkt!J12),Inputs!$B$15*Mkt!J12+(1-Inputs!$B$15)*MIN(Mkt!J12,I12*(1+Inputs!$B$18))),I12))) -> 1500 | ... ED12: =IF(ED$1<Units!$P11,0,IF(AND(Units!$K11=0,ED$1=Units!$O11),Units!$R11,IF(AND(ED$1>=Units!$Q11,MOD(ED$1-Units!$Q11,12)=0),IF(AND(Units!$L11=1,ED$1=Units!$Q11),IF(Units!$J11<>"",Units!$J11,Mkt!ED12),Inputs!$B$15*Mkt!ED12+(1-Inputs!$B$15)*MIN(Mkt!ED12,EC12*(1+Inputs!$B$18))),EC12))) -> 2049.4725
A13: =Units!A12 -> 111 | B13: =IF(Units!K12=1,Units!F12,0) -> 1450 | C13: =IF(C$1<Units!$P12,0,IF(AND(Units!$K12=0,C$1=Units!$O12),Units!$R12,IF(AND(C$1>=Units!$Q12,MOD(C$1-Units!$Q12,12)=0),IF(AND(Units!$L12=1,C$1=Units!$Q12),IF(Units!$J12<>"",Units!$J12,Mkt!C13),Inputs!$B$15*Mkt!C13+(1-Inputs!$B$15)*MIN(Mkt!C13,B13*(1+Inputs!$B$18))),B13))) -> 1450 | D13: =IF(D$1<Units!$P12,0,IF(AND(Units!$K12=0,D$1=Units!$O12),Units!$R12,IF(AND(D$1>=Units!$Q12,MOD(D$1-Units!$Q12,12)=0),IF(AND(Units!$L12=1,D$1=Units!$Q12),IF(Units!$J12<>"",Units!$J12,Mkt!D13),Inputs!$B$15*Mkt!D13+(1-Inputs!$B$15)*MIN(Mkt!D13,C13*(1+Inputs!$B$18))),C13))) -> 1450 | E13: =IF(E$1<Units!$P12,0,IF(AND(Units!$K12=0,E$1=Units!$O12),Units!$R12,IF(AND(E$1>=Units!$Q12,MOD(E$1-Units!$Q12,12)=0),IF(AND(Units!$L12=1,E$1=Units!$Q12),IF(Units!$J12<>"",Units!$J12,Mkt!E13),Inputs!$B$15*Mkt!E13+(1-Inputs!$B$15)*MIN(Mkt!E13,D13*(1+Inputs!$B$18))),D13))) -> 1450 | F13: =IF(F$1<Units!$P12,0,IF(AND(Units!$K12=0,F$1=Units!$O12),Units!$R12,IF(AND(F$1>=Units!$Q12,MOD(F$1-Units!$Q12,12)=0),IF(AND(Units!$L12=1,F$1=Units!$Q12),IF(Units!$J12<>"",Units!$J12,Mkt!F13),Inputs!$B$15*Mkt!F13+(1-Inputs!$B$15)*MIN(Mkt!F13,E13*(1+Inputs!$B$18))),E13))) -> 1450 | G13: =IF(G$1<Units!$P12,0,IF(AND(Units!$K12=0,G$1=Units!$O12),Units!$R12,IF(AND(G$1>=Units!$Q12,MOD(G$1-Units!$Q12,12)=0),IF(AND(Units!$L12=1,G$1=Units!$Q12),IF(Units!$J12<>"",Units!$J12,Mkt!G13),Inputs!$B$15*Mkt!G13+(1-Inputs!$B$15)*MIN(Mkt!G13,F13*(1+Inputs!$B$18))),F13))) -> 1450 | H13: =IF(H$1<Units!$P12,0,IF(AND(Units!$K12=0,H$1=Units!$O12),Units!$R12,IF(AND(H$1>=Units!$Q12,MOD(H$1-Units!$Q12,12)=0),IF(AND(Units!$L12=1,H$1=Units!$Q12),IF(Units!$J12<>"",Units!$J12,Mkt!H13),Inputs!$B$15*Mkt!H13+(1-Inputs!$B$15)*MIN(Mkt!H13,G13*(1+Inputs!$B$18))),G13))) -> 1450 | I13: =IF(I$1<Units!$P12,0,IF(AND(Units!$K12=0,I$1=Units!$O12),Units!$R12,IF(AND(I$1>=Units!$Q12,MOD(I$1-Units!$Q12,12)=0),IF(AND(Units!$L12=1,I$1=Units!$Q12),IF(Units!$J12<>"",Units!$J12,Mkt!I13),Inputs!$B$15*Mkt!I13+(1-Inputs!$B$15)*MIN(Mkt!I13,H13*(1+Inputs!$B$18))),H13))) -> 1450 | J13: =IF(J$1<Units!$P12,0,IF(AND(Units!$K12=0,J$1=Units!$O12),Units!$R12,IF(AND(J$1>=Units!$Q12,MOD(J$1-Units!$Q12,12)=0),IF(AND(Units!$L12=1,J$1=Units!$Q12),IF(Units!$J12<>"",Units!$J12,Mkt!J13),Inputs!$B$15*Mkt!J13+(1-Inputs!$B$15)*MIN(Mkt!J13,I13*(1+Inputs!$B$18))),I13))) -> 1523.75 | ... ED13: =IF(ED$1<Units!$P12,0,IF(AND(Units!$K12=0,ED$1=Units!$O12),Units!$R12,IF(AND(ED$1>=Units!$Q12,MOD(ED$1-Units!$Q12,12)=0),IF(AND(Units!$L12=1,ED$1=Units!$Q12),IF(Units!$J12<>"",Units!$J12,Mkt!ED13),Inputs!$B$15*Mkt!ED13+(1-Inputs!$B$15)*MIN(Mkt!ED13,EC13*(1+Inputs!$B$18))),EC13))) -> 2049.4725
A14: =Units!A13 -> 112 | B14: =IF(Units!K13=1,Units!F13,0) -> 1555 | C14: =IF(C$1<Units!$P13,0,IF(AND(Units!$K13=0,C$1=Units!$O13),Units!$R13,IF(AND(C$1>=Units!$Q13,MOD(C$1-Units!$Q13,12)=0),IF(AND(Units!$L13=1,C$1=Units!$Q13),IF(Units!$J13<>"",Units!$J13,Mkt!C14),Inputs!$B$15*Mkt!C14+(1-Inputs!$B$15)*MIN(Mkt!C14,B14*(1+Inputs!$B$18))),B14))) -> 1555 | D14: =IF(D$1<Units!$P13,0,IF(AND(Units!$K13=0,D$1=Units!$O13),Units!$R13,IF(AND(D$1>=Units!$Q13,MOD(D$1-Units!$Q13,12)=0),IF(AND(Units!$L13=1,D$1=Units!$Q13),IF(Units!$J13<>"",Units!$J13,Mkt!D14),Inputs!$B$15*Mkt!D14+(1-Inputs!$B$15)*MIN(Mkt!D14,C14*(1+Inputs!$B$18))),C14))) -> 1555 | E14: =IF(E$1<Units!$P13,0,IF(AND(Units!$K13=0,E$1=Units!$O13),Units!$R13,IF(AND(E$1>=Units!$Q13,MOD(E$1-Units!$Q13,12)=0),IF(AND(Units!$L13=1,E$1=Units!$Q13),IF(Units!$J13<>"",Units!$J13,Mkt!E14),Inputs!$B$15*Mkt!E14+(1-Inputs!$B$15)*MIN(Mkt!E14,D14*(1+Inputs!$B$18))),D14))) -> 1555 | F14: =IF(F$1<Units!$P13,0,IF(AND(Units!$K13=0,F$1=Units!$O13),Units!$R13,IF(AND(F$1>=Units!$Q13,MOD(F$1-Units!$Q13,12)=0),IF(AND(Units!$L13=1,F$1=Units!$Q13),IF(Units!$J13<>"",Units!$J13,Mkt!F14),Inputs!$B$15*Mkt!F14+(1-Inputs!$B$15)*MIN(Mkt!F14,E14*(1+Inputs!$B$18))),E14))) -> 1525 | G14: =IF(G$1<Units!$P13,0,IF(AND(Units!$K13=0,G$1=Units!$O13),Units!$R13,IF(AND(G$1>=Units!$Q13,MOD(G$1-Units!$Q13,12)=0),IF(AND(Units!$L13=1,G$1=Units!$Q13),IF(Units!$J13<>"",Units!$J13,Mkt!G14),Inputs!$B$15*Mkt!G14+(1-Inputs!$B$15)*MIN(Mkt!G14,F14*(1+Inputs!$B$18))),F14))) -> 1525 | H14: =IF(H$1<Units!$P13,0,IF(AND(Units!$K13=0,H$1=Units!$O13),Units!$R13,IF(AND(H$1>=Units!$Q13,MOD(H$1-Units!$Q13,12)=0),IF(AND(Units!$L13=1,H$1=Units!$Q13),IF(Units!$J13<>"",Units!$J13,Mkt!H14),Inputs!$B$15*Mkt!H14+(1-Inputs!$B$15)*MIN(Mkt!H14,G14*(1+Inputs!$B$18))),G14))) -> 1525 | I14: =IF(I$1<Units!$P13,0,IF(AND(Units!$K13=0,I$1=Units!$O13),Units!$R13,IF(AND(I$1>=Units!$Q13,MOD(I$1-Units!$Q13,12)=0),IF(AND(Units!$L13=1,I$1=Units!$Q13),IF(Units!$J13<>"",Units!$J13,Mkt!I14),Inputs!$B$15*Mkt!I14+(1-Inputs!$B$15)*MIN(Mkt!I14,H14*(1+Inputs!$B$18))),H14))) -> 1525 | J14: =IF(J$1<Units!$P13,0,IF(AND(Units!$K13=0,J$1=Units!$O13),Units!$R13,IF(AND(J$1>=Units!$Q13,MOD(J$1-Units!$Q13,12)=0),IF(AND(Units!$L13=1,J$1=Units!$Q13),IF(Units!$J13<>"",Units!$J13,Mkt!J14),Inputs!$B$15*Mkt!J14+(1-Inputs!$B$15)*MIN(Mkt!J14,I14*(1+Inputs!$B$18))),I14))) -> 1525 | ... ED14: =IF(ED$1<Units!$P13,0,IF(AND(Units!$K13=0,ED$1=Units!$O13),Units!$R13,IF(AND(ED$1>=Units!$Q13,MOD(ED$1-Units!$Q13,12)=0),IF(AND(Units!$L13=1,ED$1=Units!$Q13),IF(Units!$J13<>"",Units!$J13,Mkt!ED14),Inputs!$B$15*Mkt!ED14+(1-Inputs!$B$15)*MIN(Mkt!ED14,EC14*(1+Inputs!$B$18))),EC14))) -> 2049.4725
... A122: =Units!A121 -> 430 | B122: =IF(Units!K121=1,Units!F121,0) -> 2325 | C122: =IF(C$1<Units!$P121,0,IF(AND(Units!$K121=0,C$1=Units!$O121),Units!$R121,IF(AND(C$1>=Units!$Q121,MOD(C$1-Units!$Q121,12)=0),IF(AND(Units!$L121=1,C$1=Units!$Q121),IF(Units!$J121<>"",Units!$J121,Mkt!C122),Inputs!$B$15*Mkt!C122+(1-Inputs!$B$15)*MIN(Mkt!C122,B122*(1+Inputs!$B$18))),B122))) -> 2325 | D122: =IF(D$1<Units!$P121,0,IF(AND(Units!$K121=0,D$1=Units!$O121),Units!$R121,IF(AND(D$1>=Units!$Q121,MOD(D$1-Units!$Q121,12)=0),IF(AND(Units!$L121=1,D$1=Units!$Q121),IF(Units!$J121<>"",Units!$J121,Mkt!D122),Inputs!$B$15*Mkt!D122+(1-Inputs!$B$15)*MIN(Mkt!D122,C122*(1+Inputs!$B$18))),C122))) -> 2325 | E122: =IF(E$1<Units!$P121,0,IF(AND(Units!$K121=0,E$1=Units!$O121),Units!$R121,IF(AND(E$1>=Units!$Q121,MOD(E$1-Units!$Q121,12)=0),IF(AND(Units!$L121=1,E$1=Units!$Q121),IF(Units!$J121<>"",Units!$J121,Mkt!E122),Inputs!$B$15*Mkt!E122+(1-Inputs!$B$15)*MIN(Mkt!E122,D122*(1+Inputs!$B$18))),D122))) -> 2325 | F122: =IF(F$1<Units!$P121,0,IF(AND(Units!$K121=0,F$1=Units!$O121),Units!$R121,IF(AND(F$1>=Units!$Q121,MOD(F$1-Units!$Q121,12)=0),IF(AND(Units!$L121=1,F$1=Units!$Q121),IF(Units!$J121<>"",Units!$J121,Mkt!F122),Inputs!$B$15*Mkt!F122+(1-Inputs!$B$15)*MIN(Mkt!F122,E122*(1+Inputs!$B$18))),E122))) -> 2325 | G122: =IF(G$1<Units!$P121,0,IF(AND(Units!$K121=0,G$1=Units!$O121),Units!$R121,IF(AND(G$1>=Units!$Q121,MOD(G$1-Units!$Q121,12)=0),IF(AND(Units!$L121=1,G$1=Units!$Q121),IF(Units!$J121<>"",Units!$J121,Mkt!G122),Inputs!$B$15*Mkt!G122+(1-Inputs!$B$15)*MIN(Mkt!G122,F122*(1+Inputs!$B$18))),F122))) -> 2325 | H122: =IF(H$1<Units!$P121,0,IF(AND(Units!$K121=0,H$1=Units!$O121),Units!$R121,IF(AND(H$1>=Units!$Q121,MOD(H$1-Units!$Q121,12)=0),IF(AND(Units!$L121=1,H$1=Units!$Q121),IF(Units!$J121<>"",Units!$J121,Mkt!H122),Inputs!$B$15*Mkt!H122+(1-Inputs!$B$15)*MIN(Mkt!H122,G122*(1+Inputs!$B$18))),G122))) -> 2325 | I122: =IF(I$1<Units!$P121,0,IF(AND(Units!$K121=0,I$1=Units!$O121),Units!$R121,IF(AND(I$1>=Units!$Q121,MOD(I$1-Units!$Q121,12)=0),IF(AND(Units!$L121=1,I$1=Units!$Q121),IF(Units!$J121<>"",Units!$J121,Mkt!I122),Inputs!$B$15*Mkt!I122+(1-Inputs!$B$15)*MIN(Mkt!I122,H122*(1+Inputs!$B$18))),H122))) -> 2325 | J122: =IF(J$1<Units!$P121,0,IF(AND(Units!$K121=0,J$1=Units!$O121),Units!$R121,IF(AND(J$1>=Units!$Q121,MOD(J$1-Units!$Q121,12)=0),IF(AND(Units!$L121=1,J$1=Units!$Q121),IF(Units!$J121<>"",Units!$J121,Mkt!J122),Inputs!$B$15*Mkt!J122+(1-Inputs!$B$15)*MIN(Mkt!J122,I122*(1+Inputs!$B$18))),I122))) -> 2325 | ... ED122: =IF(ED$1<Units!$P121,0,IF(AND(Units!$K121=0,ED$1=Units!$O121),Units!$R121,IF(AND(ED$1>=Units!$Q121,MOD(ED$1-Units!$Q121,12)=0),IF(AND(Units!$L121=1,ED$1=Units!$Q121),IF(Units!$J121<>"",Units!$J121,Mkt!ED122),Inputs!$B$15*Mkt!ED122+(1-Inputs!$B$15)*MIN(Mkt!ED122,EC122*(1+Inputs!$B$18))),EC122))) -> 3010.3727

Sheet Turnover
A1: Month | B1: Turnover cost $ | C1: 1 | D1: 2 | E1: 3 | F1: 4 | G1: 5 | H1: 6 | I1: 7 | J1: 8 | K1: 9 | L1: 10 | M1: 11 | N1: 12 | O1: 13 | P1: 14 | Q1: 15 | R1: 16 | S1: 17 | T1: 18 | U1: 19 | V1: 20 | W1: 21 | X1: 22 | Y1: 23 | Z1: 24 | AA1: 25 | AB1: 26 | AC1: 27 | AD1: 28 | AE1: 29 | AF1: 30 | AG1: 31 | AH1: 32 | AI1: 33 | AJ1: 34 | AK1: 35 | AL1: 36 | AM1: 37 | AN1: 38 | AO1: 39 | AP1: 40 | AQ1: 41 | AR1: 42 | AS1: 43 | AT1: 44 | AU1: 45 | AV1: 46 | AW1: 47 | AX1: 48 | AY1: 49 | AZ1: 50 | BA1: 51 | BB1: 52 | BC1: 53 | BD1: 54 | BE1: 55 | BF1: 56 | BG1: 57 | BH1: 58 | BI1: 59 | BJ1: 60 | BK1: 61 | BL1: 62 | BM1: 63 | BN1: 64 | BO1: 65 | BP1: 66 | BQ1: 67 | BR1: 68 | BS1: 69 | BT1: 70 | BU1: 71 | BV1: 72 | BW1: 73 | BX1: 74 | BY1: 75 | BZ1: 76 | CA1: 77 | CB1: 78 | CC1: 79 | CD1: 80 | CE1: 81 | CF1: 82 | CG1: 83 | CH1: 84 | CI1: 85 | CJ1: 86 | CK1: 87 | CL1: 88 | CM1: 89 | CN1: 90 | CO1: 91 | CP1: 92 | CQ1: 93 | CR1: 94 | CS1: 95 | CT1: 96 | CU1: 97 | CV1: 98 | CW1: 99 | CX1: 100 | CY1: 101 | CZ1: 102 | DA1: 103 | DB1: 104 | DC1: 105 | DD1: 106 | DE1: 107 | DF1: 108 | DG1: 109 | DH1: 110 | DI1: 111 | DJ1: 112 | DK1: 113 | DL1: 114 | DM1: 115 | DN1: 116 | DO1: 117 | DP1: 118 | DQ1: 119 | DR1: 120 | DS1: 121 | DT1: 122 | DU1: 123 | DV1: 124 | DW1: 125 | DX1: 126 | DY1: 127 | DZ1: 128 | EA1: 129 | EB1: 130 | EC1: 131 | ED1: 132
A2: Year | C2: =ROUNDUP(C1/12,0) -> 1 | D2: =ROUNDUP(D1/12,0) -> 1 | E2: =ROUNDUP(E1/12,0) -> 1 | F2: =ROUNDUP(F1/12,0) -> 1 | G2: =ROUNDUP(G1/12,0) -> 1 | H2: =ROUNDUP(H1/12,0) -> 1 | I2: =ROUNDUP(I1/12,0) -> 1 | J2: =ROUNDUP(J1/12,0) -> 1 | ... ED2: =ROUNDUP(ED1/12,0) -> 11
A3: =Units!A2 -> 101 | C3: =IF(AND(C$1>=Units!$Q2,MOD(C$1-Units!$Q2,12)=0),IF(AND(Units!$L2=1,C$1=Units!$Q2),1,Inputs!$B$15)*Inputs!$B$16*(1+Inputs!$B$11)^(C$2-1),0) -> 0 | D3: =IF(AND(D$1>=Units!$Q2,MOD(D$1-Units!$Q2,12)=0),IF(AND(Units!$L2=1,D$1=Units!$Q2),1,Inputs!$B$15)*Inputs!$B$16*(1+Inputs!$B$11)^(D$2-1),0) -> 500 | E3: =IF(AND(E$1>=Units!$Q2,MOD(E$1-Units!$Q2,12)=0),IF(AND(Units!$L2=1,E$1=Units!$Q2),1,Inputs!$B$15)*Inputs!$B$16*(1+Inputs!$B$11)^(E$2-1),0) -> 0 | F3: =IF(AND(F$1>=Units!$Q2,MOD(F$1-Units!$Q2,12)=0),IF(AND(Units!$L2=1,F$1=Units!$Q2),1,Inputs!$B$15)*Inputs!$B$16*(1+Inputs!$B$11)^(F$2-1),0) -> 0 | G3: =IF(AND(G$1>=Units!$Q2,MOD(G$1-Units!$Q2,12)=0),IF(AND(Units!$L2=1,G$1=Units!$Q2),1,Inputs!$B$15)*Inputs!$B$16*(1+Inputs!$B$11)^(G$2-1),0) -> 0 | H3: =IF(AND(H$1>=Units!$Q2,MOD(H$1-Units!$Q2,12)=0),IF(AND(Units!$L2=1,H$1=Units!$Q2),1,Inputs!$B$15)*Inputs!$B$16*(1+Inputs!$B$11)^(H$2-1),0) -> 0 | I3: =IF(AND(I$1>=Units!$Q2,MOD(I$1-Units!$Q2,12)=0),IF(AND(Units!$L2=1,I$1=Units!$Q2),1,Inputs!$B$15)*Inputs!$B$16*(1+Inputs!$B$11)^(I$2-1),0) -> 0 | J3: =IF(AND(J$1>=Units!$Q2,MOD(J$1-Units!$Q2,12)=0),IF(AND(Units!$L2=1,J$1=Units!$Q2),1,Inputs!$B$15)*Inputs!$B$16*(1+Inputs!$B$11)^(J$2-1),0) -> 0 | ... ED3: =IF(AND(ED$1>=Units!$Q2,MOD(ED$1-Units!$Q2,12)=0),IF(AND(Units!$L2=1,ED$1=Units!$Q2),1,Inputs!$B$15)*Inputs!$B$16*(1+Inputs!$B$11)^(ED$2-1),0) -> 0
A4: =Units!A3 -> 102 | C4: =IF(AND(C$1>=Units!$Q3,MOD(C$1-Units!$Q3,12)=0),IF(AND(Units!$L3=1,C$1=Units!$Q3),1,Inputs!$B$15)*Inputs!$B$16*(1+Inputs!$B$11)^(C$2-1),0) -> 0 | D4: =IF(AND(D$1>=Units!$Q3,MOD(D$1-Units!$Q3,12)=0),IF(AND(Units!$L3=1,D$1=Units!$Q3),1,Inputs!$B$15)*Inputs!$B$16*(1+Inputs!$B$11)^(D$2-1),0) -> 0 | E4: =IF(AND(E$1>=Units!$Q3,MOD(E$1-Units!$Q3,12)=0),IF(AND(Units!$L3=1,E$1=Units!$Q3),1,Inputs!$B$15)*Inputs!$B$16*(1+Inputs!$B$11)^(E$2-1),0) -> 0 | F4: =IF(AND(F$1>=Units!$Q3,MOD(F$1-Units!$Q3,12)=0),IF(AND(Units!$L3=1,F$1=Units!$Q3),1,Inputs!$B$15)*Inputs!$B$16*(1+Inputs!$B$11)^(F$2-1),0) -> 0 | G4: =IF(AND(G$1>=Units!$Q3,MOD(G$1-Units!$Q3,12)=0),IF(AND(Units!$L3=1,G$1=Units!$Q3),1,Inputs!$B$15)*Inputs!$B$16*(1+Inputs!$B$11)^(G$2-1),0) -> 0 | H4: =IF(AND(H$1>=Units!$Q3,MOD(H$1-Units!$Q3,12)=0),IF(AND(Units!$L3=1,H$1=Units!$Q3),1,Inputs!$B$15)*Inputs!$B$16*(1+Inputs!$B$11)^(H$2-1),0) -> 500 | I4: =IF(AND(I$1>=Units!$Q3,MOD(I$1-Units!$Q3,12)=0),IF(AND(Units!$L3=1,I$1=Units!$Q3),1,Inputs!$B$15)*Inputs!$B$16*(1+Inputs!$B$11)^(I$2-1),0) -> 0 | J4: =IF(AND(J$1>=Units!$Q3,MOD(J$1-Units!$Q3,12)=0),IF(AND(Units!$L3=1,J$1=Units!$Q3),1,Inputs!$B$15)*Inputs!$B$16*(1+Inputs!$B$11)^(J$2-1),0) -> 0 | ... ED4: =IF(AND(ED$1>=Units!$Q3,MOD(ED$1-Units!$Q3,12)=0),IF(AND(Units!$L3=1,ED$1=Units!$Q3),1,Inputs!$B$15)*Inputs!$B$16*(1+Inputs!$B$11)^(ED$2-1),0) -> 0
A5: =Units!A4 -> 103 | C5: =IF(AND(C$1>=Units!$Q4,MOD(C$1-Units!$Q4,12)=0),IF(AND(Units!$L4=1,C$1=Units!$Q4),1,Inputs!$B$15)*Inputs!$B$16*(1+Inputs!$B$11)^(C$2-1),0) -> 0 | D5: =IF(AND(D$1>=Units!$Q4,MOD(D$1-Units!$Q4,12)=0),IF(AND(Units!$L4=1,D$1=Units!$Q4),1,Inputs!$B$15)*Inputs!$B$16*(1+Inputs!$B$11)^(D$2-1),0) -> 0 | E5: =IF(AND(E$1>=Units!$Q4,MOD(E$1-Units!$Q4,12)=0),IF(AND(Units!$L4=1,E$1=Units!$Q4),1,Inputs!$B$15)*Inputs!$B$16*(1+Inputs!$B$11)^(E$2-1),0) -> 0 | F5: =IF(AND(F$1>=Units!$Q4,MOD(F$1-Units!$Q4,12)=0),IF(AND(Units!$L4=1,F$1=Units!$Q4),1,Inputs!$B$15)*Inputs!$B$16*(1+Inputs!$B$11)^(F$2-1),0) -> 0 | G5: =IF(AND(G$1>=Units!$Q4,MOD(G$1-Units!$Q4,12)=0),IF(AND(Units!$L4=1,G$1=Units!$Q4),1,Inputs!$B$15)*Inputs!$B$16*(1+Inputs!$B$11)^(G$2-1),0) -> 0 | H5: =IF(AND(H$1>=Units!$Q4,MOD(H$1-Units!$Q4,12)=0),IF(AND(Units!$L4=1,H$1=Units!$Q4),1,Inputs!$B$15)*Inputs!$B$16*(1+Inputs!$B$11)^(H$2-1),0) -> 0 | I5: =IF(AND(I$1>=Units!$Q4,MOD(I$1-Units!$Q4,12)=0),IF(AND(Units!$L4=1,I$1=Units!$Q4),1,Inputs!$B$15)*Inputs!$B$16*(1+Inputs!$B$11)^(I$2-1),0) -> 0 | J5: =IF(AND(J$1>=Units!$Q4,MOD(J$1-Units!$Q4,12)=0),IF(AND(Units!$L4=1,J$1=Units!$Q4),1,Inputs!$B$15)*Inputs!$B$16*(1+Inputs!$B$11)^(J$2-1),0) -> 0 | ... ED5: =IF(AND(ED$1>=Units!$Q4,MOD(ED$1-Units!$Q4,12)=0),IF(AND(Units!$L4=1,ED$1=Units!$Q4),1,Inputs!$B$15)*Inputs!$B$16*(1+Inputs!$B$11)^(ED$2-1),0) -> 0
A6: =Units!A5 -> 104 | C6: =IF(AND(C$1>=Units!$Q5,MOD(C$1-Units!$Q5,12)=0),IF(AND(Units!$L5=1,C$1=Units!$Q5),1,Inputs!$B$15)*Inputs!$B$16*(1+Inputs!$B$11)^(C$2-1),0) -> 0 | D6: =IF(AND(D$1>=Units!$Q5,MOD(D$1-Units!$Q5,12)=0),IF(AND(Units!$L5=1,D$1=Units!$Q5),1,Inputs!$B$15)*Inputs!$B$16*(1+Inputs!$B$11)^(D$2-1),0) -> 0 | E6: =IF(AND(E$1>=Units!$Q5,MOD(E$1-Units!$Q5,12)=0),IF(AND(Units!$L5=1,E$1=Units!$Q5),1,Inputs!$B$15)*Inputs!$B$16*(1+Inputs!$B$11)^(E$2-1),0) -> 0 | F6: =IF(AND(F$1>=Units!$Q5,MOD(F$1-Units!$Q5,12)=0),IF(AND(Units!$L5=1,F$1=Units!$Q5),1,Inputs!$B$15)*Inputs!$B$16*(1+Inputs!$B$11)^(F$2-1),0) -> 0 | G6: =IF(AND(G$1>=Units!$Q5,MOD(G$1-Units!$Q5,12)=0),IF(AND(Units!$L5=1,G$1=Units!$Q5),1,Inputs!$B$15)*Inputs!$B$16*(1+Inputs!$B$11)^(G$2-1),0) -> 0 | H6: =IF(AND(H$1>=Units!$Q5,MOD(H$1-Units!$Q5,12)=0),IF(AND(Units!$L5=1,H$1=Units!$Q5),1,Inputs!$B$15)*Inputs!$B$16*(1+Inputs!$B$11)^(H$2-1),0) -> 0 | I6: =IF(AND(I$1>=Units!$Q5,MOD(I$1-Units!$Q5,12)=0),IF(AND(Units!$L5=1,I$1=Units!$Q5),1,Inputs!$B$15)*Inputs!$B$16*(1+Inputs!$B$11)^(I$2-1),0) -> 0 | J6: =IF(AND(J$1>=Units!$Q5,MOD(J$1-Units!$Q5,12)=0),IF(AND(Units!$L5=1,J$1=Units!$Q5),1,Inputs!$B$15)*Inputs!$B$16*(1+Inputs!$B$11)^(J$2-1),0) -> 0 | ... ED6: =IF(AND(ED$1>=Units!$Q5,MOD(ED$1-Units!$Q5,12)=0),IF(AND(Units!$L5=1,ED$1=Units!$Q5),1,Inputs!$B$15)*Inputs!$B$16*(1+Inputs!$B$11)^(ED$2-1),0) -> 0
A7: =Units!A6 -> 105 | C7: =IF(AND(C$1>=Units!$Q6,MOD(C$1-Units!$Q6,12)=0),IF(AND(Units!$L6=1,C$1=Units!$Q6),1,Inputs!$B$15)*Inputs!$B$16*(1+Inputs!$B$11)^(C$2-1),0) -> 0 | D7: =IF(AND(D$1>=Units!$Q6,MOD(D$1-Units!$Q6,12)=0),IF(AND(Units!$L6=1,D$1=Units!$Q6),1,Inputs!$B$15)*Inputs!$B$16*(1+Inputs!$B$11)^(D$2-1),0) -> 0 | E7: =IF(AND(E$1>=Units!$Q6,MOD(E$1-Units!$Q6,12)=0),IF(AND(Units!$L6=1,E$1=Units!$Q6),1,Inputs!$B$15)*Inputs!$B$16*(1+Inputs!$B$11)^(E$2-1),0) -> 500 | F7: =IF(AND(F$1>=Units!$Q6,MOD(F$1-Units!$Q6,12)=0),IF(AND(Units!$L6=1,F$1=Units!$Q6),1,Inputs!$B$15)*Inputs!$B$16*(1+Inputs!$B$11)^(F$2-1),0) -> 0 | G7: =IF(AND(G$1>=Units!$Q6,MOD(G$1-Units!$Q6,12)=0),IF(AND(Units!$L6=1,G$1=Units!$Q6),1,Inputs!$B$15)*Inputs!$B$16*(1+Inputs!$B$11)^(G$2-1),0) -> 0 | H7: =IF(AND(H$1>=Units!$Q6,MOD(H$1-Units!$Q6,12)=0),IF(AND(Units!$L6=1,H$1=Units!$Q6),1,Inputs!$B$15)*Inputs!$B$16*(1+Inputs!$B$11)^(H$2-1),0) -> 0 | I7: =IF(AND(I$1>=Units!$Q6,MOD(I$1-Units!$Q6,12)=0),IF(AND(Units!$L6=1,I$1=Units!$Q6),1,Inputs!$B$15)*Inputs!$B$16*(1+Inputs!$B$11)^(I$2-1),0) -> 0 | J7: =IF(AND(J$1>=Units!$Q6,MOD(J$1-Units!$Q6,12)=0),IF(AND(Units!$L6=1,J$1=Units!$Q6),1,Inputs!$B$15)*Inputs!$B$16*(1+Inputs!$B$11)^(J$2-1),0) -> 0 | ... ED7: =IF(AND(ED$1>=Units!$Q6,MOD(ED$1-Units!$Q6,12)=0),IF(AND(Units!$L6=1,ED$1=Units!$Q6),1,Inputs!$B$15)*Inputs!$B$16*(1+Inputs!$B$11)^(ED$2-1),0) -> 0
A8: =Units!A7 -> 106 | C8: =IF(AND(C$1>=Units!$Q7,MOD(C$1-Units!$Q7,12)=0),IF(AND(Units!$L7=1,C$1=Units!$Q7),1,Inputs!$B$15)*Inputs!$B$16*(1+Inputs!$B$11)^(C$2-1),0) -> 0 | D8: =IF(AND(D$1>=Units!$Q7,MOD(D$1-Units!$Q7,12)=0),IF(AND(Units!$L7=1,D$1=Units!$Q7),1,Inputs!$B$15)*Inputs!$B$16*(1+Inputs!$B$11)^(D$2-1),0) -> 0 | E8: =IF(AND(E$1>=Units!$Q7,MOD(E$1-Units!$Q7,12)=0),IF(AND(Units!$L7=1,E$1=Units!$Q7),1,Inputs!$B$15)*Inputs!$B$16*(1+Inputs!$B$11)^(E$2-1),0) -> 0 | F8: =IF(AND(F$1>=Units!$Q7,MOD(F$1-Units!$Q7,12)=0),IF(AND(Units!$L7=1,F$1=Units!$Q7),1,Inputs!$B$15)*Inputs!$B$16*(1+Inputs!$B$11)^(F$2-1),0) -> 500 | G8: =IF(AND(G$1>=Units!$Q7,MOD(G$1-Units!$Q7,12)=0),IF(AND(Units!$L7=1,G$1=Units!$Q7),1,Inputs!$B$15)*Inputs!$B$16*(1+Inputs!$B$11)^(G$2-1),0) -> 0 | H8: =IF(AND(H$1>=Units!$Q7,MOD(H$1-Units!$Q7,12)=0),IF(AND(Units!$L7=1,H$1=Units!$Q7),1,Inputs!$B$15)*Inputs!$B$16*(1+Inputs!$B$11)^(H$2-1),0) -> 0 | I8: =IF(AND(I$1>=Units!$Q7,MOD(I$1-Units!$Q7,12)=0),IF(AND(Units!$L7=1,I$1=Units!$Q7),1,Inputs!$B$15)*Inputs!$B$16*(1+Inputs!$B$11)^(I$2-1),0) -> 0 | J8: =IF(AND(J$1>=Units!$Q7,MOD(J$1-Units!$Q7,12)=0),IF(AND(Units!$L7=1,J$1=Units!$Q7),1,Inputs!$B$15)*Inputs!$B$16*(1+Inputs!$B$11)^(J$2-1),0) -> 0 | ... ED8: =IF(AND(ED$1>=Units!$Q7,MOD(ED$1-Units!$Q7,12)=0),IF(AND(Units!$L7=1,ED$1=Units!$Q7),1,Inputs!$B$15)*Inputs!$B$16*(1+Inputs!$B$11)^(ED$2-1),0) -> 0
A9: =Units!A8 -> 107 | C9: =IF(AND(C$1>=Units!$Q8,MOD(C$1-Units!$Q8,12)=0),IF(AND(Units!$L8=1,C$1=Units!$Q8),1,Inputs!$B$15)*Inputs!$B$16*(1+Inputs!$B$11)^(C$2-1),0) -> 0 | D9: =IF(AND(D$1>=Units!$Q8,MOD(D$1-Units!$Q8,12)=0),IF(AND(Units!$L8=1,D$1=Units!$Q8),1,Inputs!$B$15)*Inputs!$B$16*(1+Inputs!$B$11)^(D$2-1),0) -> 0 | E9: =IF(AND(E$1>=Units!$Q8,MOD(E$1-Units!$Q8,12)=0),IF(AND(Units!$L8=1,E$1=Units!$Q8),1,Inputs!$B$15)*Inputs!$B$16*(1+Inputs!$B$11)^(E$2-1),0) -> 500 | F9: =IF(AND(F$1>=Units!$Q8,MOD(F$1-Units!$Q8,12)=0),IF(AND(Units!$L8=1,F$1=Units!$Q8),1,Inputs!$B$15)*Inputs!$B$16*(1+Inputs!$B$11)^(F$2-1),0) -> 0 | G9: =IF(AND(G$1>=Units!$Q8,MOD(G$1-Units!$Q8,12)=0),IF(AND(Units!$L8=1,G$1=Units!$Q8),1,Inputs!$B$15)*Inputs!$B$16*(1+Inputs!$B$11)^(G$2-1),0) -> 0 | H9: =IF(AND(H$1>=Units!$Q8,MOD(H$1-Units!$Q8,12)=0),IF(AND(Units!$L8=1,H$1=Units!$Q8),1,Inputs!$B$15)*Inputs!$B$16*(1+Inputs!$B$11)^(H$2-1),0) -> 0 | I9: =IF(AND(I$1>=Units!$Q8,MOD(I$1-Units!$Q8,12)=0),IF(AND(Units!$L8=1,I$1=Units!$Q8),1,Inputs!$B$15)*Inputs!$B$16*(1+Inputs!$B$11)^(I$2-1),0) -> 0 | J9: =IF(AND(J$1>=Units!$Q8,MOD(J$1-Units!$Q8,12)=0),IF(AND(Units!$L8=1,J$1=Units!$Q8),1,Inputs!$B$15)*Inputs!$B$16*(1+Inputs!$B$11)^(J$2-1),0) -> 0 | ... ED9: =IF(AND(ED$1>=Units!$Q8,MOD(ED$1-Units!$Q8,12)=0),IF(AND(Units!$L8=1,ED$1=Units!$Q8),1,Inputs!$B$15)*Inputs!$B$16*(1+Inputs!$B$11)^(ED$2-1),0) -> 0
A10: =Units!A9 -> 108 | C10: =IF(AND(C$1>=Units!$Q9,MOD(C$1-Units!$Q9,12)=0),IF(AND(Units!$L9=1,C$1=Units!$Q9),1,Inputs!$B$15)*Inputs!$B$16*(1+Inputs!$B$11)^(C$2-1),0) -> 0 | D10: =IF(AND(D$1>=Units!$Q9,MOD(D$1-Units!$Q9,12)=0),IF(AND(Units!$L9=1,D$1=Units!$Q9),1,Inputs!$B$15)*Inputs!$B$16*(1+Inputs!$B$11)^(D$2-1),0) -> 0 | E10: =IF(AND(E$1>=Units!$Q9,MOD(E$1-Units!$Q9,12)=0),IF(AND(Units!$L9=1,E$1=Units!$Q9),1,Inputs!$B$15)*Inputs!$B$16*(1+Inputs!$B$11)^(E$2-1),0) -> 0 | F10: =IF(AND(F$1>=Units!$Q9,MOD(F$1-Units!$Q9,12)=0),IF(AND(Units!$L9=1,F$1=Units!$Q9),1,Inputs!$B$15)*Inputs!$B$16*(1+Inputs!$B$11)^(F$2-1),0) -> 0 | G10: =IF(AND(G$1>=Units!$Q9,MOD(G$1-Units!$Q9,12)=0),IF(AND(Units!$L9=1,G$1=Units!$Q9),1,Inputs!$B$15)*Inputs!$B$16*(1+Inputs!$B$11)^(G$2-1),0) -> 0 | H10: =IF(AND(H$1>=Units!$Q9,MOD(H$1-Units!$Q9,12)=0),IF(AND(Units!$L9=1,H$1=Units!$Q9),1,Inputs!$B$15)*Inputs!$B$16*(1+Inputs!$B$11)^(H$2-1),0) -> 0 | I10: =IF(AND(I$1>=Units!$Q9,MOD(I$1-Units!$Q9,12)=0),IF(AND(Units!$L9=1,I$1=Units!$Q9),1,Inputs!$B$15)*Inputs!$B$16*(1+Inputs!$B$11)^(I$2-1),0) -> 0 | J10: =IF(AND(J$1>=Units!$Q9,MOD(J$1-Units!$Q9,12)=0),IF(AND(Units!$L9=1,J$1=Units!$Q9),1,Inputs!$B$15)*Inputs!$B$16*(1+Inputs!$B$11)^(J$2-1),0) -> 500 | ... ED10: =IF(AND(ED$1>=Units!$Q9,MOD(ED$1-Units!$Q9,12)=0),IF(AND(Units!$L9=1,ED$1=Units!$Q9),1,Inputs!$B$15)*Inputs!$B$16*(1+Inputs!$B$11)^(ED$2-1),0) -> 0
A11: =Units!A10 -> 109 | C11: =IF(AND(C$1>=Units!$Q10,MOD(C$1-Units!$Q10,12)=0),IF(AND(Units!$L10=1,C$1=Units!$Q10),1,Inputs!$B$15)*Inputs!$B$16*(1+Inputs!$B$11)^(C$2-1),0) -> 0 | D11: =IF(AND(D$1>=Units!$Q10,MOD(D$1-Units!$Q10,12)=0),IF(AND(Units!$L10=1,D$1=Units!$Q10),1,Inputs!$B$15)*Inputs!$B$16*(1+Inputs!$B$11)^(D$2-1),0) -> 0 | E11: =IF(AND(E$1>=Units!$Q10,MOD(E$1-Units!$Q10,12)=0),IF(AND(Units!$L10=1,E$1=Units!$Q10),1,Inputs!$B$15)*Inputs!$B$16*(1+Inputs!$B$11)^(E$2-1),0) -> 0 | F11: =IF(AND(F$1>=Units!$Q10,MOD(F$1-Units!$Q10,12)=0),IF(AND(Units!$L10=1,F$1=Units!$Q10),1,Inputs!$B$15)*Inputs!$B$16*(1+Inputs!$B$11)^(F$2-1),0) -> 0 | G11: =IF(AND(G$1>=Units!$Q10,MOD(G$1-Units!$Q10,12)=0),IF(AND(Units!$L10=1,G$1=Units!$Q10),1,Inputs!$B$15)*Inputs!$B$16*(1+Inputs!$B$11)^(G$2-1),0) -> 0 | H11: =IF(AND(H$1>=Units!$Q10,MOD(H$1-Units!$Q10,12)=0),IF(AND(Units!$L10=1,H$1=Units!$Q10),1,Inputs!$B$15)*Inputs!$B$16*(1+Inputs!$B$11)^(H$2-1),0) -> 0 | I11: =IF(AND(I$1>=Units!$Q10,MOD(I$1-Units!$Q10,12)=0),IF(AND(Units!$L10=1,I$1=Units!$Q10),1,Inputs!$B$15)*Inputs!$B$16*(1+Inputs!$B$11)^(I$2-1),0) -> 0 | J11: =IF(AND(J$1>=Units!$Q10,MOD(J$1-Units!$Q10,12)=0),IF(AND(Units!$L10=1,J$1=Units!$Q10),1,Inputs!$B$15)*Inputs!$B$16*(1+Inputs!$B$11)^(J$2-1),0) -> 0 | ... ED11: =IF(AND(ED$1>=Units!$Q10,MOD(ED$1-Units!$Q10,12)=0),IF(AND(Units!$L10=1,ED$1=Units!$Q10),1,Inputs!$B$15)*Inputs!$B$16*(1+Inputs!$B$11)^(ED$2-1),0) -> 0
A12: =Units!A11 -> 110 | C12: =IF(AND(C$1>=Units!$Q11,MOD(C$1-Units!$Q11,12)=0),IF(AND(Units!$L11=1,C$1=Units!$Q11),1,Inputs!$B$15)*Inputs!$B$16*(1+Inputs!$B$11)^(C$2-1),0) -> 0 | D12: =IF(AND(D$1>=Units!$Q11,MOD(D$1-Units!$Q11,12)=0),IF(AND(Units!$L11=1,D$1=Units!$Q11),1,Inputs!$B$15)*Inputs!$B$16*(1+Inputs!$B$11)^(D$2-1),0) -> 0 | E12: =IF(AND(E$1>=Units!$Q11,MOD(E$1-Units!$Q11,12)=0),IF(AND(Units!$L11=1,E$1=Units!$Q11),1,Inputs!$B$15)*Inputs!$B$16*(1+Inputs!$B$11)^(E$2-1),0) -> 0 | F12: =IF(AND(F$1>=Units!$Q11,MOD(F$1-Units!$Q11,12)=0),IF(AND(Units!$L11=1,F$1=Units!$Q11),1,Inputs!$B$15)*Inputs!$B$16*(1+Inputs!$B$11)^(F$2-1),0) -> 0 | G12: =IF(AND(G$1>=Units!$Q11,MOD(G$1-Units!$Q11,12)=0),IF(AND(Units!$L11=1,G$1=Units!$Q11),1,Inputs!$B$15)*Inputs!$B$16*(1+Inputs!$B$11)^(G$2-1),0) -> 0 | H12: =IF(AND(H$1>=Units!$Q11,MOD(H$1-Units!$Q11,12)=0),IF(AND(Units!$L11=1,H$1=Units!$Q11),1,Inputs!$B$15)*Inputs!$B$16*(1+Inputs!$B$11)^(H$2-1),0) -> 0 | I12: =IF(AND(I$1>=Units!$Q11,MOD(I$1-Units!$Q11,12)=0),IF(AND(Units!$L11=1,I$1=Units!$Q11),1,Inputs!$B$15)*Inputs!$B$16*(1+Inputs!$B$11)^(I$2-1),0) -> 0 | J12: =IF(AND(J$1>=Units!$Q11,MOD(J$1-Units!$Q11,12)=0),IF(AND(Units!$L11=1,J$1=Units!$Q11),1,Inputs!$B$15)*Inputs!$B$16*(1+Inputs!$B$11)^(J$2-1),0) -> 0 | ... ED12: =IF(AND(ED$1>=Units!$Q11,MOD(ED$1-Units!$Q11,12)=0),IF(AND(Units!$L11=1,ED$1=Units!$Q11),1,Inputs!$B$15)*Inputs!$B$16*(1+Inputs!$B$11)^(ED$2-1),0) -> 671.95819
A13: =Units!A12 -> 111 | C13: =IF(AND(C$1>=Units!$Q12,MOD(C$1-Units!$Q12,12)=0),IF(AND(Units!$L12=1,C$1=Units!$Q12),1,Inputs!$B$15)*Inputs!$B$16*(1+Inputs!$B$11)^(C$2-1),0) -> 0 | D13: =IF(AND(D$1>=Units!$Q12,MOD(D$1-Units!$Q12,12)=0),IF(AND(Units!$L12=1,D$1=Units!$Q12),1,Inputs!$B$15)*Inputs!$B$16*(1+Inputs!$B$11)^(D$2-1),0) -> 0 | E13: =IF(AND(E$1>=Units!$Q12,MOD(E$1-Units!$Q12,12)=0),IF(AND(Units!$L12=1,E$1=Units!$Q12),1,Inputs!$B$15)*Inputs!$B$16*(1+Inputs!$B$11)^(E$2-1),0) -> 0 | F13: =IF(AND(F$1>=Units!$Q12,MOD(F$1-Units!$Q12,12)=0),IF(AND(Units!$L12=1,F$1=Units!$Q12),1,Inputs!$B$15)*Inputs!$B$16*(1+Inputs!$B$11)^(F$2-1),0) -> 0 | G13: =IF(AND(G$1>=Units!$Q12,MOD(G$1-Units!$Q12,12)=0),IF(AND(Units!$L12=1,G$1=Units!$Q12),1,Inputs!$B$15)*Inputs!$B$16*(1+Inputs!$B$11)^(G$2-1),0) -> 0 | H13: =IF(AND(H$1>=Units!$Q12,MOD(H$1-Units!$Q12,12)=0),IF(AND(Units!$L12=1,H$1=Units!$Q12),1,Inputs!$B$15)*Inputs!$B$16*(1+Inputs!$B$11)^(H$2-1),0) -> 0 | I13: =IF(AND(I$1>=Units!$Q12,MOD(I$1-Units!$Q12,12)=0),IF(AND(Units!$L12=1,I$1=Units!$Q12),1,Inputs!$B$15)*Inputs!$B$16*(1+Inputs!$B$11)^(I$2-1),0) -> 0 | J13: =IF(AND(J$1>=Units!$Q12,MOD(J$1-Units!$Q12,12)=0),IF(AND(Units!$L12=1,J$1=Units!$Q12),1,Inputs!$B$15)*Inputs!$B$16*(1+Inputs!$B$11)^(J$2-1),0) -> 500 | ... ED13: =IF(AND(ED$1>=Units!$Q12,MOD(ED$1-Units!$Q12,12)=0),IF(AND(Units!$L12=1,ED$1=Units!$Q12),1,Inputs!$B$15)*Inputs!$B$16*(1+Inputs!$B$11)^(ED$2-1),0) -> 0
A14: =Units!A13 -> 112 | C14: =IF(AND(C$1>=Units!$Q13,MOD(C$1-Units!$Q13,12)=0),IF(AND(Units!$L13=1,C$1=Units!$Q13),1,Inputs!$B$15)*Inputs!$B$16*(1+Inputs!$B$11)^(C$2-1),0) -> 0 | D14: =IF(AND(D$1>=Units!$Q13,MOD(D$1-Units!$Q13,12)=0),IF(AND(Units!$L13=1,D$1=Units!$Q13),1,Inputs!$B$15)*Inputs!$B$16*(1+Inputs!$B$11)^(D$2-1),0) -> 0 | E14: =IF(AND(E$1>=Units!$Q13,MOD(E$1-Units!$Q13,12)=0),IF(AND(Units!$L13=1,E$1=Units!$Q13),1,Inputs!$B$15)*Inputs!$B$16*(1+Inputs!$B$11)^(E$2-1),0) -> 0 | F14: =IF(AND(F$1>=Units!$Q13,MOD(F$1-Units!$Q13,12)=0),IF(AND(Units!$L13=1,F$1=Units!$Q13),1,Inputs!$B$15)*Inputs!$B$16*(1+Inputs!$B$11)^(F$2-1),0) -> 500 | G14: =IF(AND(G$1>=Units!$Q13,MOD(G$1-Units!$Q13,12)=0),IF(AND(Units!$L13=1,G$1=Units!$Q13),1,Inputs!$B$15)*Inputs!$B$16*(1+Inputs!$B$11)^(G$2-1),0) -> 0 | H14: =IF(AND(H$1>=Units!$Q13,MOD(H$1-Units!$Q13,12)=0),IF(AND(Units!$L13=1,H$1=Units!$Q13),1,Inputs!$B$15)*Inputs!$B$16*(1+Inputs!$B$11)^(H$2-1),0) -> 0 | I14: =IF(AND(I$1>=Units!$Q13,MOD(I$1-Units!$Q13,12)=0),IF(AND(Units!$L13=1,I$1=Units!$Q13),1,Inputs!$B$15)*Inputs!$B$16*(1+Inputs!$B$11)^(I$2-1),0) -> 0 | J14: =IF(AND(J$1>=Units!$Q13,MOD(J$1-Units!$Q13,12)=0),IF(AND(Units!$L13=1,J$1=Units!$Q13),1,Inputs!$B$15)*Inputs!$B$16*(1+Inputs!$B$11)^(J$2-1),0) -> 0 | ... ED14: =IF(AND(ED$1>=Units!$Q13,MOD(ED$1-Units!$Q13,12)=0),IF(AND(Units!$L13=1,ED$1=Units!$Q13),1,Inputs!$B$15)*Inputs!$B$16*(1+Inputs!$B$11)^(ED$2-1),0) -> 0
... A122: =Units!A121 -> 430 | C122: =IF(AND(C$1>=Units!$Q121,MOD(C$1-Units!$Q121,12)=0),IF(AND(Units!$L121=1,C$1=Units!$Q121),1,Inputs!$B$15)*Inputs!$B$16*(1+Inputs!$B$11)^(C$2-1),0) -> 0 | D122: =IF(AND(D$1>=Units!$Q121,MOD(D$1-Units!$Q121,12)=0),IF(AND(Units!$L121=1,D$1=Units!$Q121),1,Inputs!$B$15)*Inputs!$B$16*(1+Inputs!$B$11)^(D$2-1),0) -> 0 | E122: =IF(AND(E$1>=Units!$Q121,MOD(E$1-Units!$Q121,12)=0),IF(AND(Units!$L121=1,E$1=Units!$Q121),1,Inputs!$B$15)*Inputs!$B$16*(1+Inputs!$B$11)^(E$2-1),0) -> 0 | F122: =IF(AND(F$1>=Units!$Q121,MOD(F$1-Units!$Q121,12)=0),IF(AND(Units!$L121=1,F$1=Units!$Q121),1,Inputs!$B$15)*Inputs!$B$16*(1+Inputs!$B$11)^(F$2-1),0) -> 0 | G122: =IF(AND(G$1>=Units!$Q121,MOD(G$1-Units!$Q121,12)=0),IF(AND(Units!$L121=1,G$1=Units!$Q121),1,Inputs!$B$15)*Inputs!$B$16*(1+Inputs!$B$11)^(G$2-1),0) -> 0 | H122: =IF(AND(H$1>=Units!$Q121,MOD(H$1-Units!$Q121,12)=0),IF(AND(Units!$L121=1,H$1=Units!$Q121),1,Inputs!$B$15)*Inputs!$B$16*(1+Inputs!$B$11)^(H$2-1),0) -> 0 | I122: =IF(AND(I$1>=Units!$Q121,MOD(I$1-Units!$Q121,12)=0),IF(AND(Units!$L121=1,I$1=Units!$Q121),1,Inputs!$B$15)*Inputs!$B$16*(1+Inputs!$B$11)^(I$2-1),0) -> 0 | J122: =IF(AND(J$1>=Units!$Q121,MOD(J$1-Units!$Q121,12)=0),IF(AND(Units!$L121=1,J$1=Units!$Q121),1,Inputs!$B$15)*Inputs!$B$16*(1+Inputs!$B$11)^(J$2-1),0) -> 0 | ... ED122: =IF(AND(ED$1>=Units!$Q121,MOD(ED$1-Units!$Q121,12)=0),IF(AND(Units!$L121=1,ED$1=Units!$Q121),1,Inputs!$B$15)*Inputs!$B$16*(1+Inputs!$B$11)^(ED$2-1),0) -> 0

Sheet Monthly
A1: Month | B1: Year | C1: GPR | D1: Market rent on leased units | E1: Current rent (leased) | F1: Loss to lease | G1: Absorption vacancy | H1: Occupied units | I1: Turnover cost | J1: Loan: opening balance | K1: Payment | L1: Interest | M1: Principal | N1: Closing balance
A2: 1 | B2: =ROUNDUP(A2/12,0) -> 1 | C2: =SUM(INDEX(Mkt!$C$3:$ED$122,0,A2)) -> 194430 | D2: =SUMIF(Units!$P$2:$P$121,"<="&A2,INDEX(Mkt!$C$3:$ED$122,0,A2)) -> 191055 | E2: =SUM(INDEX(Rent!$C$3:$ED$122,0,A2)) -> 185825.5 | F2: =D2-E2 -> 5229.5 | G2: =C2-D2 -> 3375 | H2: =COUNTIF(Units!$P$2:$P$121,"<="&A2) -> 118 | I2: =SUM(INDEX(Turnover!$C$3:$ED$122,0,A2)) -> 7000 | J2: =Returns!$C$8 -> 12591864 | K2: =IF(A2>Inputs!$B$21*12,0,IF(A2<=Inputs!$B$24*12,J2*(Inputs!$B$23/12),Returns!$C$11)) -> 68205.931 | L2: =IF(A2>Inputs!$B$21*12,0,J2*(Inputs!$B$23/12)) -> 68205.931 | M2: =K2-L2 -> 0 | N2: =J2-M2 -> 12591864
A3: 2 | B3: =ROUNDUP(A3/12,0) -> 1 | C3: =SUM(INDEX(Mkt!$C$3:$ED$122,0,A3)) -> 194430 | D3: =SUMIF(Units!$P$2:$P$121,"<="&A3,INDEX(Mkt!$C$3:$ED$122,0,A3)) -> 194430 | E3: =SUM(INDEX(Rent!$C$3:$ED$122,0,A3)) -> 189386.75 | F3: =D3-E3 -> 5043.25 | G3: =C3-D3 -> 0 | H3: =COUNTIF(Units!$P$2:$P$121,"<="&A3) -> 120 | I3: =SUM(INDEX(Turnover!$C$3:$ED$122,0,A3)) -> 4500 | J3: =N2 -> 12591864 | K3: =IF(A3>Inputs!$B$21*12,0,IF(A3<=Inputs!$B$24*12,J3*(Inputs!$B$23/12),Returns!$C$11)) -> 68205.931 | L3: =IF(A3>Inputs!$B$21*12,0,J3*(Inputs!$B$23/12)) -> 68205.931 | M3: =K3-L3 -> 0 | N3: =J3-M3 -> 12591864
A4: 3 | B4: =ROUNDUP(A4/12,0) -> 1 | C4: =SUM(INDEX(Mkt!$C$3:$ED$122,0,A4)) -> 194430 | D4: =SUMIF(Units!$P$2:$P$121,"<="&A4,INDEX(Mkt!$C$3:$ED$122,0,A4)) -> 194430 | E4: =SUM(INDEX(Rent!$C$3:$ED$122,0,A4)) -> 189781 | F4: =D4-E4 -> 4649 | G4: =C4-D4 -> 0 | H4: =COUNTIF(Units!$P$2:$P$121,"<="&A4) -> 120 | I4: =SUM(INDEX(Turnover!$C$3:$ED$122,0,A4)) -> 6000 | J4: =N3 -> 12591864 | K4: =IF(A4>Inputs!$B$21*12,0,IF(A4<=Inputs!$B$24*12,J4*(Inputs!$B$23/12),Returns!$C$11)) -> 68205.931 | L4: =IF(A4>Inputs!$B$21*12,0,J4*(Inputs!$B$23/12)) -> 68205.931 | M4: =K4-L4 -> 0 | N4: =J4-M4 -> 12591864
A5: 4 | B5: =ROUNDUP(A5/12,0) -> 1 | C5: =SUM(INDEX(Mkt!$C$3:$ED$122,0,A5)) -> 194430 | D5: =SUMIF(Units!$P$2:$P$121,"<="&A5,INDEX(Mkt!$C$3:$ED$122,0,A5)) -> 194430 | E5: =SUM(INDEX(Rent!$C$3:$ED$122,0,A5)) -> 190324.38 | F5: =D5-E5 -> 4105.625 | G5: =C5-D5 -> 0 | H5: =COUNTIF(Units!$P$2:$P$121,"<="&A5) -> 120 | I5: =SUM(INDEX(Turnover!$C$3:$ED$122,0,A5)) -> 5500 | J5: =N4 -> 12591864 | K5: =IF(A5>Inputs!$B$21*12,0,IF(A5<=Inputs!$B$24*12,J5*(Inputs!$B$23/12),Returns!$C$11)) -> 68205.931 | L5: =IF(A5>Inputs!$B$21*12,0,J5*(Inputs!$B$23/12)) -> 68205.931 | M5: =K5-L5 -> 0 | N5: =J5-M5 -> 12591864
A6: 5 | B6: =ROUNDUP(A6/12,0) -> 1 | C6: =SUM(INDEX(Mkt!$C$3:$ED$122,0,A6)) -> 194430 | D6: =SUMIF(Units!$P$2:$P$121,"<="&A6,INDEX(Mkt!$C$3:$ED$122,0,A6)) -> 194430 | E6: =SUM(INDEX(Rent!$C$3:$ED$122,0,A6)) -> 190432.38 | F6: =D6-E6 -> 3997.625 | G6: =C6-D6 -> 0 | H6: =COUNTIF(Units!$P$2:$P$121,"<="&A6) -> 120 | I6: =SUM(INDEX(Turnover!$C$3:$ED$122,0,A6)) -> 2500 | J6: =N5 -> 12591864 | K6: =IF(A6>Inputs!$B$21*12,0,IF(A6<=Inputs!$B$24*12,J6*(Inputs!$B$23/12),Returns!$C$11)) -> 68205.931 | L6: =IF(A6>Inputs!$B$21*12,0,J6*(Inputs!$B$23/12)) -> 68205.931 | M6: =K6-L6 -> 0 | N6: =J6-M6 -> 12591864
A7: 6 | B7: =ROUNDUP(A7/12,0) -> 1 | C7: =SUM(INDEX(Mkt!$C$3:$ED$122,0,A7)) -> 194430 | D7: =SUMIF(Units!$P$2:$P$121,"<="&A7,INDEX(Mkt!$C$3:$ED$122,0,A7)) -> 194430 | E7: =SUM(INDEX(Rent!$C$3:$ED$122,0,A7)) -> 190970.5 | F7: =D7-E7 -> 3459.5 | G7: =C7-D7 -> 0 | H7: =COUNTIF(Units!$P$2:$P$121,"<="&A7) -> 120 | I7: =SUM(INDEX(Turnover!$C$3:$ED$122,0,A7)) -> 3000 | J7: =N6 -> 12591864 | K7: =IF(A7>Inputs!$B$21*12,0,IF(A7<=Inputs!$B$24*12,J7*(Inputs!$B$23/12),Returns!$C$11)) -> 68205.931 | L7: =IF(A7>Inputs!$B$21*12,0,J7*(Inputs!$B$23/12)) -> 68205.931 | M7: =K7-L7 -> 0 | N7: =J7-M7 -> 12591864
A8: 7 | B8: =ROUNDUP(A8/12,0) -> 1 | C8: =SUM(INDEX(Mkt!$C$3:$ED$122,0,A8)) -> 194430 | D8: =SUMIF(Units!$P$2:$P$121,"<="&A8,INDEX(Mkt!$C$3:$ED$122,0,A8)) -> 194430 | E8: =SUM(INDEX(Rent!$C$3:$ED$122,0,A8)) -> 191333 | F8: =D8-E8 -> 3097 | G8: =C8-D8 -> 0 | H8: =COUNTIF(Units!$P$2:$P$121,"<="&A8) -> 120 | I8: =SUM(INDEX(Turnover!$C$3:$ED$122,0,A8)) -> 4500 | J8: =N7 -> 12591864 | K8: =IF(A8>Inputs!$B$21*12,0,IF(A8<=Inputs!$B$24*12,J8*(Inputs!$B$23/12),Returns!$C$11)) -> 68205.931 | L8: =IF(A8>Inputs!$B$21*12,0,J8*(Inputs!$B$23/12)) -> 68205.931 | M8: =K8-L8 -> 0 | N8: =J8-M8 -> 12591864
A9: 8 | B9: =ROUNDUP(A9/12,0) -> 1 | C9: =SUM(INDEX(Mkt!$C$3:$ED$122,0,A9)) -> 194430 | D9: =SUMIF(Units!$P$2:$P$121,"<="&A9,INDEX(Mkt!$C$3:$ED$122,0,A9)) -> 194430 | E9: =SUM(INDEX(Rent!$C$3:$ED$122,0,A9)) -> 191737.38 | F9: =D9-E9 -> 2692.625 | G9: =C9-D9 -> 0 | H9: =COUNTIF(Units!$P$2:$P$121,"<="&A9) -> 120 | I9: =SUM(INDEX(Turnover!$C$3:$ED$122,0,A9)) -> 5000 | J9: =N8 -> 12591864 | K9: =IF(A9>Inputs!$B$21*12,0,IF(A9<=Inputs!$B$24*12,J9*(Inputs!$B$23/12),Returns!$C$11)) -> 68205.931 | L9: =IF(A9>Inputs!$B$21*12,0,J9*(Inputs!$B$23/12)) -> 68205.931 | M9: =K9-L9 -> 0 | N9: =J9-M9 -> 12591864
A10: 9 | B10: =ROUNDUP(A10/12,0) -> 1 | C10: =SUM(INDEX(Mkt!$C$3:$ED$122,0,A10)) -> 194430 | D10: =SUMIF(Units!$P$2:$P$121,"<="&A10,INDEX(Mkt!$C$3:$ED$122,0,A10)) -> 194430 | E10: =SUM(INDEX(Rent!$C$3:$ED$122,0,A10)) -> 191960 | F10: =D10-E10 -> 2470 | G10: =C10-D10 -> 0 | H10: =COUNTIF(Units!$P$2:$P$121,"<="&A10) -> 120 | I10: =SUM(INDEX(Turnover!$C$3:$ED$122,0,A10)) -> 5500 | J10: =N9 -> 12591864 | K10: =IF(A10>Inputs!$B$21*12,0,IF(A10<=Inputs!$B$24*12,J10*(Inputs!$B$23/12),Returns!$C$11)) -> 68205.931 | L10: =IF(A10>Inputs!$B$21*12,0,J10*(Inputs!$B$23/12)) -> 68205.931 | M10: =K10-L10 -> 0 | N10: =J10-M10 -> 12591864
A11: 10 | B11: =ROUNDUP(A11/12,0) -> 1 | C11: =SUM(INDEX(Mkt!$C$3:$ED$122,0,A11)) -> 194430 | D11: =SUMIF(Units!$P$2:$P$121,"<="&A11,INDEX(Mkt!$C$3:$ED$122,0,A11)) -> 194430 | E11: =SUM(INDEX(Rent!$C$3:$ED$122,0,A11)) -> 192325.12 | F11: =D11-E11 -> 2104.875 | G11: =C11-D11 -> 0 | H11: =COUNTIF(Units!$P$2:$P$121,"<="&A11) -> 120 | I11: =SUM(INDEX(Turnover!$C$3:$ED$122,0,A11)) -> 3500 | J11: =N10 -> 12591864 | K11: =IF(A11>Inputs!$B$21*12,0,IF(A11<=Inputs!$B$24*12,J11*(Inputs!$B$23/12),Returns!$C$11)) -> 68205.931 | L11: =IF(A11>Inputs!$B$21*12,0,J11*(Inputs!$B$23/12)) -> 68205.931 | M11: =K11-L11 -> 0 | N11: =J11-M11 -> 12591864
A12: 11 | B12: =ROUNDUP(A12/12,0) -> 1 | C12: =SUM(INDEX(Mkt!$C$3:$ED$122,0,A12)) -> 194430 | D12: =SUMIF(Units!$P$2:$P$121,"<="&A12,INDEX(Mkt!$C$3:$ED$122,0,A12)) -> 194430 | E12: =SUM(INDEX(Rent!$C$3:$ED$122,0,A12)) -> 192669.12 | F12: =D12-E12 -> 1760.875 | G12: =C12-D12 -> 0 | H12: =COUNTIF(Units!$P$2:$P$121,"<="&A12) -> 120 | I12: =SUM(INDEX(Turnover!$C$3:$ED$122,0,A12)) -> 3500 | J12: =N11 -> 12591864 | K12: =IF(A12>Inputs!$B$21*12,0,IF(A12<=Inputs!$B$24*12,J12*(Inputs!$B$23/12),Returns!$C$11)) -> 68205.931 | L12: =IF(A12>Inputs!$B$21*12,0,J12*(Inputs!$B$23/12)) -> 68205.931 | M12: =K12-L12 -> 0 | N12: =J12-M12 -> 12591864
A13: 12 | B13: =ROUNDUP(A13/12,0) -> 1 | C13: =SUM(INDEX(Mkt!$C$3:$ED$122,0,A13)) -> 194430 | D13: =SUMIF(Units!$P$2:$P$121,"<="&A13,INDEX(Mkt!$C$3:$ED$122,0,A13)) -> 194430 | E13: =SUM(INDEX(Rent!$C$3:$ED$122,0,A13)) -> 192959.38 | F13: =D13-E13 -> 1470.625 | G13: =C13-D13 -> 0 | H13: =COUNTIF(Units!$P$2:$P$121,"<="&A13) -> 120 | I13: =SUM(INDEX(Turnover!$C$3:$ED$122,0,A13)) -> 5000 | J13: =N12 -> 12591864 | K13: =IF(A13>Inputs!$B$21*12,0,IF(A13<=Inputs!$B$24*12,J13*(Inputs!$B$23/12),Returns!$C$11)) -> 68205.931 | L13: =IF(A13>Inputs!$B$21*12,0,J13*(Inputs!$B$23/12)) -> 68205.931 | M13: =K13-L13 -> 0 | N13: =J13-M13 -> 12591864
A14: 13 | B14: =ROUNDUP(A14/12,0) -> 2 | C14: =SUM(INDEX(Mkt!$C$3:$ED$122,0,A14)) -> 200262.9 | D14: =SUMIF(Units!$P$2:$P$121,"<="&A14,INDEX(Mkt!$C$3:$ED$122,0,A14)) -> 200262.9 | E14: =SUM(INDEX(Rent!$C$3:$ED$122,0,A14)) -> 194045.42 | F14: =D14-E14 -> 6217.475 | G14: =C14-D14 -> 0 | H14: =COUNTIF(Units!$P$2:$P$121,"<="&A14) -> 120 | I14: =SUM(INDEX(Turnover!$C$3:$ED$122,0,A14)) -> 10815 | J14: =N13 -> 12591864 | K14: =IF(A14>Inputs!$B$21*12,0,IF(A14<=Inputs!$B$24*12,J14*(Inputs!$B$23/12),Returns!$C$11)) -> 68205.931 | L14: =IF(A14>Inputs!$B$21*12,0,J14*(Inputs!$B$23/12)) -> 68205.931 | M14: =K14-L14 -> 0 | N14: =J14-M14 -> 12591864
... A133: 132 | B133: =ROUNDUP(A133/12,0) -> 11 | C133: =SUM(INDEX(Mkt!$C$3:$ED$122,0,A133)) -> 261297.66 | D133: =SUMIF(Units!$P$2:$P$121,"<="&A133,INDEX(Mkt!$C$3:$ED$122,0,A133)) -> 261297.66 | E133: =SUM(INDEX(Rent!$C$3:$ED$122,0,A133)) -> 261297.66 | F133: =D133-E133 -> 0 | G133: =C133-D133 -> 0 | H133: =COUNTIF(Units!$P$2:$P$121,"<="&A133) -> 120 | I133: =SUM(INDEX(Turnover!$C$3:$ED$122,0,A133)) -> 6719.5819 | J133: =N132 -> 11163528 | K133: =IF(A133>Inputs!$B$21*12,0,IF(A133<=Inputs!$B$24*12,J133*(Inputs!$B$23/12),Returns!$C$11)) -> 0 | L133: =IF(A133>Inputs!$B$21*12,0,J133*(Inputs!$B$23/12)) -> 0 | M133: =K133-L133 -> 0 | N133: =J133-M133 -> 11163528
